Workbook
Name \\\: recuperação [1]tubulão2011!$A$29:$J$29
Name \\\: recuperação [1]tubulão2011!$A$29:$J$29
Name \\\: recuperação [1]tubulão2011!$A$29:$J$29
Name \c: #REF!
Name \c: #REF!
Name \c: #REF!
Name \i: #REF!
Name \i: #REF!
Name \i: #REF!
Name \L: #REF!
Name \L: #REF!
Name \L: #REF!
Name \M: #REF!
Name \M: #REF!
Name \M: #REF!
Name \O: #REF!
Name \O: #REF!
Name \O: #REF!
Name \p: #REF!
Name \p: #REF!
Name \p: #REF!
Name \Q: #REF!
Name \Q: #REF!
Name \Q: #REF!
Name \R: #REF!
Name \R: #REF!
Name \R: #REF!
Name \S: #REF!
Name \S: #REF!
Name \S: #REF!
Name \T: #REF!
Name \T: #REF!
Name \T: #REF!
Name \u: #REF!
Name \u: #REF!
Name \u: #REF!
Name \X: #REF!
Name \X: #REF!
Name \X: #REF!
Name \Z: #REF!
Name \Z: #REF!
Name \Z: #REF!
Name ____Orc2000: #REF!
Name ____Orc2000: #REF!
Name ____Orc2000: #REF!
Name ___Orc2000: #REF!
Name ___Orc2000: #REF!
Name ___Orc2000: #REF!
Name __Orc2000: #REF!
Name __Orc2000: #REF!
Name __Orc2000: #REF!
Name _1_US: "Dolar Exchange"
Name _1994: #REF!
Name _1994: #REF!
Name _1994: #REF!
Name _1995: #REF!
Name _1995: #REF!
Name _1995: #REF!
Name _1996: #REF!
Name _1996: #REF!

Sheet Índice
B6: Ítem exigido pelo Termo de referência | K6: Localização
K7: Planilha | L7: Célula | M7: Link
B9: Painel de controle (sumário); | K9: Controle | L9: A1 | M9: ='LOTE 3'!$A$1 -> Controle
B10: Demonstração de Fluxo de Caixa Direto e Indireto; | K10: MF | L10: A170 | M10: =#REF! -> #REF!
B11: Cálculo dos indicadores econômicos: Valor Presente Líquido (VPL), Taxa Interna de Retorno (TIR) do Projeto, Payback, etc.; | K11: MF | L11: A40 | M11: =#REF! -> #REF!
B12: Investimentos e manutenções periódicas (CAPEX); | K12: Capex | L12: A6 | M12: =Capex!$A$6 -> CAPEX
B13: Depreciações e amortizações; | K13: MF | L13: A1446 | M13: =#REF! -> #REF!
B14: Receitas:
B15: Receitas de contraprestação | K15: Receita de CP | L15: A7 | M15: ='Receita CP'!$A$7 -> Contraprestação anual
B16: Receitas acessórias | K16: Receita Acessórias | L16: A1 | M16: ='Receita Acessórias'!$A$1 -> Receitas Acessórias
B17: Custos de operação e manutenção (OPEX); | K17: Opex | L17: A22 | M17: =Opex!$A$53 -> Opex / Por item [valores reais]
B18: Custo médio ponderado de capital (WACC); e | K18: MF | L18: A1518 | M18: =#REF! -> #REF!
B19: Análises de Sensibilidade. | K19: Controle | L19: A202 | M19: ='LOTE 3'!#REF! -> #REF!
B20: Value For Money do Projeto e Justificativa Econômica da Concessão | K20: VfM | L20: A1 | M20: =VfM!A1 -> Value for Money
B21: Análise de Impacto Orçamentário e Fiscal | K21: VfM | L21: A66 | M21: =VfM!A66 -> Projeção comprometimento RCL / Cenários cobrança taxa do lixo
B22: estrutura de taxas e tributos existentes e propostos | K22: VfM | L22: A72 | M22: =VfM!A72 -> Cenário 1: taxa de R$ 14,8 por domicílio / mês
B32: Planilha | F32: Conteúdo
B34: Controle | F34: Input de variáveis sensíveis e visão do resultado do modelo
B35: Premissas | F35: Premissas financeiras, impostos etc
B36: MF | F36: Modelo Econômico-Financeiro
B37: VfM | F37: Análise quantitativa de Value for Money
B38: Operacional | F38: Construção da geração de resíduos por município, tipo de resíduo e outros
B39: Receita de CP | F39: Cálculo da receitas de contraprestação
B40: Receitas acessórias | F40: Cálculo da receitas acessórias a serem exploradas pelo concessionário
B41: Opex | F41: Custos operacionais
B42: Opex_Input | F42: Inputs de custos operacionais dos Estudos de Infraestrutura e operação
B43: Capex | F43: Cronograma de desembolso do Capex e cálculo depreciação
B44: Capex_Input | F44: Inputs de dados de investimentos dos Estudos de Infraestrutura e operação
... B58: Transferido | F58: Célula transferida de outra planilha

Sheet LOTE 3
A1: Controle
BL3: Com inflação | BO3: Alternativa 1
A4: Modelo Real ou nominal | B4: Com inflação | D4: WACC | E4: 0.1 | BL4: Sem inflação
A5: VPL | B5: ='DRE_URE MARÍLIA-BIO+GAS'!I80 -> 95957006 | C5: MM R$ | D5: TIR projeto | E5: ='DRE_URE MARÍLIA-BIO+GAS'!I79 -> 0.11637598
D6: Payback | E6: ='DRE_URE MARÍLIA-BIO+GAS'!I81 -> 6.7 | F6: COM LPU | G6: SEM LPU
A7: Contraprestação fixa | B7: 2.8540916 | C7: MM R$/ano | F7: 2.8540916 | G7: 2.8540916
A8: Saldo final ativo financeiro | B8: =#REF! -> #REF! | F8: =#REF! -> #REF! | G8: =#REF! -> #REF!
A9: Contraprestação variável - Parcela B Volume | B9: 110 | C9: R$/ton | F9: 110 | G9: 110
A10: Contraprestação variável - Parcela C População | B10: 4.7269692 | C10: R$/hab/mês | F10: 4.7269692 | G10: 2.9928665
A12: Sensibilidade preço de recicláveis | B12: 0 | F12: 0 | G12: 0
A13: Sensibilidade crédito recicláveis | B13: 0 | F13: 0 | G13: 0
A14: Outorga variável | B14: 0 | F14: 0 | G14: 0
A15: Anos de carência de outorga variável | B15: 0 | F15: 0 | G15: 0
A16: Primeiro ano de pagamento integral | B16: 1 | F16: 1 | G16: 1
A18: Fator Capex | B18: 1 | F18: 1 | G18: 1
A19: Fator Opex | B19: 1 | F19: 1 | G19: 1
A21: Capital social mínimo 1o ano | B21: 10 | C21: MM R$ | F21: 10 | G21: 10
A23: Considera limpeza urbana? | B23: 1 | C23: [1=sim;0=não] | F23: 1 | G23: 0
A25: Alavancagem alvo | B25: 1 | F25: 1 | G25: 1
A27: Síntese
A28: Componentes de valor / Waterfall VPL
H29: =YEAR(Premissas!$D$13) -> 2025 | I29: =H29+1 -> 2026 | J29: =I29+1 -> 2027 | K29: =J29+1 -> 2028 | L29: =K29+1 -> 2029 | M29: =L29+1 -> 2030 | N29: =M29+1 -> 2031 | O29: =N29+1 -> 2032 | P29: =O29+1 -> 2033 | ... AP29: =AO29+1 -> 2059
A30: Índice de inflação brasileira (IPCA) | H30: =MacroEco!AA$8 -> 1.0714036 | I30: =MacroEco!AB$8 -> 1.1035457 | J30: =MacroEco!AC$8 -> 1.1366521 | K30: =MacroEco!AD$8 -> 1.1707517 | L30: =MacroEco!AE$8 -> 1.2058742 | M30: =MacroEco!AF$8 -> 1.2420504 | N30: =MacroEco!AG$8 -> 1.2793119 | O30: =MacroEco!AH$8 -> 1.3176913 | ... AP30: =MacroEco!BI$8 -> 2.9269732
A32: Em termos nominais
A33: Receita Bruta - URE MARÍLIA - BIO+GAS | D33: =SUM(H33:AQ33) -> 1.0075865e+09 | H33: =SUM(H34:H39) -> 4710.4288 | I33: =SUM(I34:I39) -> 19031970 | J33: =SUM(J34:J39) -> 29951356 | K33: =SUM(K34:K39) -> 29951549 | L33: =SUM(L34:L39) -> 29951750 | M33: =SUM(M34:M39) -> 29951957 | N33: =SUM(N34:N39) -> 29952173 | O33: =SUM(O34:O39) -> 29952397 | ... AP33: =SUM(AP34:AP39) -> 29962351
A34: (+) Receita Contraprestação fixa | D34: =SUM(H34:AQ34) -> 229132800 | H34: ='DRE_URE MARÍLIA-BIO+GAS'!E8 -> 0 | I34: ='DRE_URE MARÍLIA-BIO+GAS'!F8 -> 6739200 | J34: ='DRE_URE MARÍLIA-BIO+GAS'!G8 -> 6739200 | K34: ='DRE_URE MARÍLIA-BIO+GAS'!H8 -> 6739200 | L34: ='DRE_URE MARÍLIA-BIO+GAS'!I8 -> 6739200 | M34: ='DRE_URE MARÍLIA-BIO+GAS'!J8 -> 6739200 | N34: ='DRE_URE MARÍLIA-BIO+GAS'!K8 -> 6739200 | O34: ='DRE_URE MARÍLIA-BIO+GAS'!L8 -> 6739200 | ... AP34: ='DRE_URE MARÍLIA-BIO+GAS'!AM8 -> 6739200
A35: (+) Receita Reciclável | D35: =SUM(H35:AQ35) -> 332157 | H35: ='Receita Acessórias'!O18 -> 4710.4288 | I35: ='Receita Acessórias'!P18 -> 4890.2048 | J35: ='Receita Acessórias'!Q18 -> 5075.7357 | K35: ='Receita Acessórias'!R18 -> 5268.8133 | L35: ='Receita Acessórias'!S18 -> 5469.748 | M35: ='Receita Acessórias'!T18 -> 5677.1311 | N35: ='Receita Acessórias'!U18 -> 5892.9261 | O35: ='Receita Acessórias'!V18 -> 6117.478 | ... AO35: ='Receita Acessórias'!AV18 -> 16071.17 | AP35: =AO35 -> 16071.17
A36: (+) Receita Biometano | D36: =SUM(H36:AQ36) -> 257040000 | H36: ='DRE_URE MARÍLIA-BIO+GAS'!E5 -> 0 | I36: ='DRE_URE MARÍLIA-BIO+GAS'!F5 -> 7560000 | J36: ='DRE_URE MARÍLIA-BIO+GAS'!G5 -> 7560000 | K36: ='DRE_URE MARÍLIA-BIO+GAS'!H5 -> 7560000 | L36: ='DRE_URE MARÍLIA-BIO+GAS'!I5 -> 7560000 | M36: ='DRE_URE MARÍLIA-BIO+GAS'!J5 -> 7560000 | N36: ='DRE_URE MARÍLIA-BIO+GAS'!K5 -> 7560000 | O36: ='DRE_URE MARÍLIA-BIO+GAS'!L5 -> 7560000 | ... AP36: ='DRE_URE MARÍLIA-BIO+GAS'!AM5 -> 7560000
A37: (+) Receita Energia Elétrica | D37: =SUM(H37:AQ37) -> 360333600 | H37: ='DRE_URE MARÍLIA-BIO+GAS'!E6 -> 0 | I37: ='DRE_URE MARÍLIA-BIO+GAS'!F6 -> 0 | J37: ='DRE_URE MARÍLIA-BIO+GAS'!G6 -> 10919200 | K37: ='DRE_URE MARÍLIA-BIO+GAS'!H6 -> 10919200 | L37: ='DRE_URE MARÍLIA-BIO+GAS'!I6 -> 10919200 | M37: ='DRE_URE MARÍLIA-BIO+GAS'!J6 -> 10919200 | N37: ='DRE_URE MARÍLIA-BIO+GAS'!K6 -> 10919200 | O37: ='DRE_URE MARÍLIA-BIO+GAS'!L6 -> 10919200 | ... AP37: ='DRE_URE MARÍLIA-BIO+GAS'!AM6 -> 10919200
A38: (+) Receita CO2 | D38: =SUM(H38:AQ38) -> 144585000 | H38: ='DRE_URE MARÍLIA-BIO+GAS'!E7 -> 0 | I38: ='DRE_URE MARÍLIA-BIO+GAS'!F7 -> 4252500 | J38: ='DRE_URE MARÍLIA-BIO+GAS'!G7 -> 4252500 | K38: ='DRE_URE MARÍLIA-BIO+GAS'!H7 -> 4252500 | L38: ='DRE_URE MARÍLIA-BIO+GAS'!I7 -> 4252500 | M38: ='DRE_URE MARÍLIA-BIO+GAS'!J7 -> 4252500 | N38: ='DRE_URE MARÍLIA-BIO+GAS'!K7 -> 4252500 | O38: ='DRE_URE MARÍLIA-BIO+GAS'!L7 -> 4252500 | ... AP38: ='DRE_URE MARÍLIA-BIO+GAS'!AM7 -> 4252500
A39: (+) CBIOS | D39: =SUM(H39:AQ39) -> 16162920 | H39: ='DRE_URE MARÍLIA-BIO+GAS'!E10 -> 0 | I39: ='DRE_URE MARÍLIA-BIO+GAS'!F10 -> 475380 | J39: ='DRE_URE MARÍLIA-BIO+GAS'!G10 -> 475380 | K39: ='DRE_URE MARÍLIA-BIO+GAS'!H10 -> 475380 | L39: ='DRE_URE MARÍLIA-BIO+GAS'!I10 -> 475380 | M39: ='DRE_URE MARÍLIA-BIO+GAS'!J10 -> 475380 | N39: ='DRE_URE MARÍLIA-BIO+GAS'!K10 -> 475380 | O39: ='DRE_URE MARÍLIA-BIO+GAS'!L10 -> 475380 | ... AP39: ='DRE_URE MARÍLIA-BIO+GAS'!AM10 -> 475380
A40: Impostos | D40: =SUM(H40:AQ40) -> -1.8693681e+08 | H40: =SUM(H41:H42) -> 0 | I40: =SUM(I41:I42) -> -4517822.2 | J40: =SUM(J41:J42) -> -5527848.2 | K40: =SUM(K41:K42) -> -5527848.2 | L40: =SUM(L41:L42) -> -5527848.2 | M40: =SUM(M41:M42) -> -5527848.2 | N40: =SUM(N41:N42) -> -5527848.2 | O40: =SUM(O41:O42) -> -5527848.2 | ... AP40: =SUM(AP41:AP42) -> -5527848.2
A41: (-) Impostos Serviço | D41: =SUM(H41:AQ41) -> -77905152 | H41: ='DRE_URE MARÍLIA-BIO+GAS'!E41 -> 0 | I41: ='DRE_URE MARÍLIA-BIO+GAS'!F41 -> -2291328 | J41: ='DRE_URE MARÍLIA-BIO+GAS'!G41 -> -2291328 | K41: ='DRE_URE MARÍLIA-BIO+GAS'!H41 -> -2291328 | L41: ='DRE_URE MARÍLIA-BIO+GAS'!I41 -> -2291328 | M41: ='DRE_URE MARÍLIA-BIO+GAS'!J41 -> -2291328 | N41: ='DRE_URE MARÍLIA-BIO+GAS'!K41 -> -2291328 | O41: ='DRE_URE MARÍLIA-BIO+GAS'!L41 -> -2291328 | ... AP41: ='DRE_URE MARÍLIA-BIO+GAS'!AM41 -> -2291328
A42: (-) Impostos Produto | D42: =SUM(H42:AQ42) -> -1.0903166e+08 | H42: ='DRE_URE MARÍLIA-BIO+GAS'!E12 -> 0 | I42: ='DRE_URE MARÍLIA-BIO+GAS'!F12 -> -2226494.2 | J42: ='DRE_URE MARÍLIA-BIO+GAS'!G12 -> -3236520.2 | K42: ='DRE_URE MARÍLIA-BIO+GAS'!H12 -> -3236520.2 | L42: ='DRE_URE MARÍLIA-BIO+GAS'!I12 -> -3236520.2 | M42: ='DRE_URE MARÍLIA-BIO+GAS'!J12 -> -3236520.2 | N42: ='DRE_URE MARÍLIA-BIO+GAS'!K12 -> -3236520.2 | O42: ='DRE_URE MARÍLIA-BIO+GAS'!L12 -> -3236520.2 | ... AP42: ='DRE_URE MARÍLIA-BIO+GAS'!AM12 -> -3236520.2
A43: OPEX | D43: =SUM(H43:AQ43) -> -1.7836593e+08 | H43: =SUM(H44:H44) -> -954720 | I43: =SUM(I44:I44) -> -5059006.2 | J43: =SUM(J44:J44) -> -5222794.2 | K43: =SUM(K44:K44) -> -5222794.2 | L43: =SUM(L44:L44) -> -5222794.2 | M43: =SUM(M44:M44) -> -5222794.2 | N43: =SUM(N44:N44) -> -5222794.2 | O43: =SUM(O44:O44) -> -5222794.2 | ... AP43: =SUM(AP44:AP44) -> -5222794.2
A44: (-) Custos com operacionais | D44: =SUM(I44:AQ44) -> -1.7741121e+08 | H44: =Opex!Z57*-1 -> -954720 | I44: =Opex!AA57*-1 -> -5059006.2 | J44: =Opex!AB57*-1 -> -5222794.2 | K44: =Opex!AC57*-1 -> -5222794.2 | L44: =Opex!AD57*-1 -> -5222794.2 | M44: =Opex!AE57*-1 -> -5222794.2 | N44: =Opex!AF57*-1 -> -5222794.2 | O44: =Opex!AG57*-1 -> -5222794.2 | ... AO44: =Opex!BG57*-1 -> -5222794.2 | AP44: =AO44 -> -5222794.2
A45: Custos de construção | D45: =SUM(H45:AQ45) -> -40600000 | H45: =H46 -> 0 | I45: =I46 -> -4060000 | J45: =J46 -> -4060000 | K45: =K46 -> -4060000 | L45: =L46 -> -4060000 | M45: =M46 -> -4060000 | N45: =N46 -> -4060000 | O45: =O46 -> -4060000 | ... AP45: =AP46 -> 0
A46: (-) Depreciação/Amortização | D46: =SUM(H46:AQ46) -> -40600000 | H46: ='DRE_URE MARÍLIA-BIO+GAS'!E36 -> 0 | I46: ='DRE_URE MARÍLIA-BIO+GAS'!F36 -> -4060000 | J46: ='DRE_URE MARÍLIA-BIO+GAS'!G36 -> -4060000 | K46: ='DRE_URE MARÍLIA-BIO+GAS'!H36 -> -4060000 | L46: ='DRE_URE MARÍLIA-BIO+GAS'!I36 -> -4060000 | M46: ='DRE_URE MARÍLIA-BIO+GAS'!J36 -> -4060000 | N46: ='DRE_URE MARÍLIA-BIO+GAS'!K36 -> -4060000 | O46: ='DRE_URE MARÍLIA-BIO+GAS'!L36 -> -4060000 | ... AP46: ='DRE_URE MARÍLIA-BIO+GAS'!AM36 -> 0
A47: (=) EBIT | D47: =SUM(H47:AQ47) -> 7.8004966e+08 | H47: =SUM(H48:H50) -> 4710.4288 | I47: =SUM(I48:I50) -> 10454148 | J47: =SUM(J48:J50) -> 20363507 | K47: =SUM(K48:K50) -> 20363701 | L47: =SUM(L48:L50) -> 20363901 | M47: =SUM(M48:M50) -> 20364109 | N47: =SUM(N48:N50) -> 20364325 | O47: =SUM(O48:O50) -> 20364549 | ... AP47: =SUM(AP48:AP50) -> 24434503
A48: (-) Impostos sobre EBIT | D48: =SUM(H48:AQ48) -> -1.8693681e+08 | H48: =H40 -> 0 | I48: =I40 -> -4517822.2 | J48: =J40 -> -5527848.2 | K48: =K40 -> -5527848.2 | L48: =L40 -> -5527848.2 | M48: =M40 -> -5527848.2 | N48: =N40 -> -5527848.2 | O48: =O40 -> -5527848.2 | ... AP48: =AP40 -> -5527848.2
A49: (+) Receita Bruta | D49: =SUM(H49:AQ49) -> 1.0075865e+09 | H49: =H33 -> 4710.4288 | I49: =I33 -> 19031970 | J49: =J33 -> 29951356 | K49: =K33 -> 29951549 | L49: =L33 -> 29951750 | M49: =M33 -> 29951957 | N49: =N33 -> 29952173 | O49: =O33 -> 29952397 | ... AP49: =AP33 -> 29962351
A50: (-) Depreciação/Amortização | D50: =SUM(H50:AQ50) -> -40600000 | H50: =H45 -> 0 | I50: =I45 -> -4060000 | J50: =J45 -> -4060000 | K50: =K45 -> -4060000 | L50: =L45 -> -4060000 | M50: =M45 -> -4060000 | N50: =N45 -> -4060000 | O50: =O45 -> -4060000 | ... AP50: =AP45 -> 0
A51: CAPEX | D51: =SUM(H51:AQ51) -> -1.0874747e+08 | H51: =H52 -> -1.0874747e+08 | I51: =I52 -> 0 | J51: =J52 -> 0 | K51: =K52 -> 0 | L51: =L52 -> 0 | M51: =M52 -> 0 | N51: =N52 -> 0 | O51: =O52 -> 0 | ... AP51: =AP52 -> 0
A52: (-) Licenciamento e Equipamentos | D52: =SUM(H52:AQ52) -> -1.0874747e+08 | H52: =Capex!O34*-1 -> -1.0874747e+08 | I52: =Capex!P34*-1 -> 0 | J52: =Capex!Q34*-1 -> 0 | K52: =Capex!R34*-1 -> 0 | L52: =Capex!S34*-1 -> 0 | M52: =Capex!T34*-1 -> 0 | N52: =Capex!U34*-1 -> 0 | O52: =Capex!V34*-1 -> 0 | ... AP52: =Capex!AW34*-1 -> 0
A54: Fluxo de caixa livre para firma | D54: =SUM(H54:AQ54) -> 9.1929558e+09 | H54: =H47+H51 -> -1.0874276e+08 | I54: =I47+I51+H54 -> -98288608 | J54: =J47+J51+I54 -> -77925101 | K54: =K47+K51+J54 -> -57561400 | L54: =L47+L51+K54 -> -37197499 | M54: =M47+M51+L54 -> -16833390 | N54: =N47+N51+M54 -> 3530935 | O54: =O47+O51+N54 -> 23895484 | P54: =P47+P51+O54 -> 44260266 | ... AP54: =AP47+AP51+AO54 -> 6.713022e+08
A57: Em termos reais
A58: =A33 -> Receita Bruta - URE MARÍLIA - BIO+GAS | D58: =SUM(H58:AQ58) -> 1.896446e+09 | H58: =SUM(H59:H64) -> 5046.7704 | I58: =SUM(I59:I64) -> 21002649 | J58: =SUM(J59:J64) -> 34044271 | K58: =SUM(K59:K64) -> 35065825 | L58: =SUM(L59:L64) -> 36118042 | M58: =SUM(M59:M64) -> 37201841 | N58: =SUM(N59:N64) -> 38318173 | O58: =SUM(O59:O64) -> 39468014 | ... AP58: =SUM(AP59:AP64) -> 87698999
A59: (+) Receita Contraprestação fixa | D59: =SUM(H59:AQ59) -> 4.2934021e+08 | H59: =H34*H30 -> 0 | I59: =I34*I30 -> 7437015.3 | J59: =J34*J30 -> 7660125.8 | K59: =K34*K30 -> 7889929.5 | L59: =L34*L30 -> 8126627.4 | M59: =M34*M30 -> 8370426.3 | N59: =N34*N30 -> 8621539 | O59: =O34*O30 -> 8880185.2 | ... AP59: =AP34*AP30 -> 19725458
A60: (+) Receita Reciclável | D60: =SUM(H60:AQ60) -> 681527.98 | H60: =H35*H30 -> 5046.7704 | I60: =I35*I30 -> 5396.5646 | J60: =J35*J30 -> 5769.3456 | K60: =K35*K30 -> 6168.4719 | L60: =L35*L30 -> 6595.828 | M60: =M35*M30 -> 7051.2831 | N60: =N35*N30 -> 7538.8908 | O60: =O35*O30 -> 8060.9475 | ... AP60: =AP35*AP30 -> 47039.885
A61: (+) Receita Biometano | D61: =SUM(H61:AQ61) -> 4.8163164e+08 | H61: =H36*H30 -> 0 | I61: =I36*I30 -> 8342805.6 | J61: =J36*J30 -> 8593089.8 | K61: =K36*K30 -> 8850882.5 | L61: =L36*L30 -> 9116409 | M61: =M36*M30 -> 9389901.2 | N61: =N36*N30 -> 9671598.3 | O61: =O36*O30 -> 9961746.2 | ... AP61: =AP36*AP30 -> 22127917
A62: (+) Receita Energia Elétrica | D62: =SUM(H62:AQ62) -> 6.8358935e+08 | H62: =H37*H30 -> 0 | I62: =I37*I30 -> 0 | J62: =J37*J30 -> 12411332 | K62: =K37*K30 -> 12783671 | L62: =L37*L30 -> 13167182 | M62: =M37*M30 -> 13562197 | N62: =N37*N30 -> 13969063 | O62: =O37*O30 -> 14388135 | ... AP62: =AP37*AP30 -> 31960206
A63: (+) Receita CO2 | D63: =SUM(H63:AQ63) -> 2.709178e+08 | H63: =H38*H30 -> 0 | I63: =I38*I30 -> 4692828.2 | J63: =J38*J30 -> 4833613 | K63: =K38*K30 -> 4978621.4 | L63: =L38*L30 -> 5127980 | M63: =M38*M30 -> 5281819.5 | N63: =N38*N30 -> 5440274 | O63: =O38*O30 -> 5603482.3 | ... AP63: =AP38*AP30 -> 12446954
A64: (+) CBIOS | D64: =SUM(H64:AQ64) -> 30285456 | H64: =H39*H30 -> 0 | I64: =I39*I30 -> 524603.56 | J64: =J39*J30 -> 540341.67 | K64: =K39*K30 -> 556551.92 | L64: =L39*L30 -> 573248.48 | M64: =M39*M30 -> 590445.93 | N64: =N39*N30 -> 608159.31 | O64: =O39*O30 -> 626404.09 | ... AP64: =AP39*AP30 -> 1391424.5
A65: Impostos | D65: =SUM(H65:AQ65) -> -3.5105293e+08 | H65: =SUM(H66:H67) -> 0 | I65: =SUM(I66:I67) -> -4985623.4 | J65: =SUM(J66:J67) -> -6283240.3 | K65: =SUM(K66:K67) -> -6471737.5 | L65: =SUM(L66:L67) -> -6665889.6 | M65: =SUM(M66:M67) -> -6865866.3 | N65: =SUM(N66:N67) -> -7071842.3 | O65: =SUM(O66:O67) -> -7283997.5 | ... AP65: =SUM(AP66:AP67) -> -16179864
A66: (-) Impostos Serviço | D66: =SUM(H66:AQ66) -> -1.4597567e+08 | H66: =H41*H30 -> 0 | I66: =I41*I30 -> -2528585.2 | J66: =J41*J30 -> -2604442.8 | K66: =K41*K30 -> -2682576 | L66: =L41*L30 -> -2763053.3 | M66: =M41*M30 -> -2845944.9 | N66: =N41*N30 -> -2931323.3 | O66: =O41*O30 -> -3019263 | ... AP66: =AP41*AP30 -> -6706655.6
A67: (-) Impostos Produto | D67: =SUM(H67:AQ67) -> -2.0507726e+08 | H67: =H42*H30 -> 0 | I67: =I42*I30 -> -2457038.2 | J67: =J42*J30 -> -3678797.5 | K67: =K42*K30 -> -3789161.4 | L67: =L42*L30 -> -3902836.3 | M67: =M42*M30 -> -4019921.4 | N67: =N42*N30 -> -4140519 | O67: =O42*O30 -> -4264734.6 | ... AP67: =AP42*AP30 -> -9473208
A68: OPEX | D68: =SUM(H68:AQ68) -> -3.3357534e+08 | H68: =SUM(H69:H69) -> -1022890.5 | I68: =SUM(I69:I69) -> -5582844.6 | J68: =SUM(J69:J69) -> -5936499.9 | K68: =SUM(K69:K69) -> -6114594.9 | L68: =SUM(L69:L69) -> -6298032.8 | M68: =SUM(M69:M69) -> -6486973.8 | N68: =SUM(N69:N69) -> -6681583 | O68: =SUM(O69:O69) -> -6882030.5 | ... AP68: =SUM(AP69:AP69) -> -15286979
A69: =A44 -> (-) Custos com operacionais | D69: =SUM(I69:AQ69) -> -3.3255245e+08 | H69: =H44*H30 -> -1022890.5 | I69: =I44*I30 -> -5582844.6 | J69: =J44*J30 -> -5936499.9 | K69: =K44*K30 -> -6114594.9 | L69: =L44*L30 -> -6298032.8 | M69: =M44*M30 -> -6486973.8 | N69: =N44*N30 -> -6681583 | O69: =O44*O30 -> -6882030.5 | ... AP69: =AP44*AP30 -> -15286979
A70: Custos de construção | D70: =SUM(H70:AQ70) -> -51362715 | H70: =SUM(H71:H71) -> 0 | I70: =SUM(I71:I71) -> -4480395.6 | J70: =SUM(J71:J71) -> -4614807.5 | K70: =SUM(K71:K71) -> -4753251.7 | L70: =SUM(L71:L71) -> -4895849.3 | M70: =SUM(M71:M71) -> -5042724.7 | N70: =SUM(N71:N71) -> -5194006.5 | O70: =SUM(O71:O71) -> -5349826.7 | ... AP70: =SUM(AP71:AP71) -> 0
A71: (-) Depreciação/Amortização | D71: =SUM(H71:AQ71) -> -51362715 | H71: =H46*H30 -> 0 | I71: =I46*I30 -> -4480395.6 | J71: =J46*J30 -> -4614807.5 | K71: =K46*K30 -> -4753251.7 | L71: =L46*L30 -> -4895849.3 | M71: =M46*M30 -> -5042724.7 | N71: =N46*N30 -> -5194006.5 | O71: =O46*O30 -> -5349826.7 | ... AP71: =AP46*AP30 -> 0
A72: (=) EBIT | D72: =SUM(H72:AQ72) -> 1.4940303e+09 | H72: =SUM(H73:H75) -> 5046.7704 | I72: =SUM(I73:I75) -> 11536630 | J72: =SUM(J73:J75) -> 23146223 | K72: =SUM(K73:K75) -> 23840836 | L72: =SUM(L73:L75) -> 24556303 | M72: =SUM(M73:M75) -> 25293250 | N72: =SUM(N73:N75) -> 26052324 | O72: =SUM(O73:O75) -> 26834189 | ... AP72: =SUM(AP73:AP75) -> 71519135
A73: (-) Impostos sobre EBIT | D73: =SUM(H73:AQ73) -> -3.5105293e+08 | H73: =H65 -> 0 | I73: =I65 -> -4985623.4 | J73: =J65 -> -6283240.3 | K73: =K65 -> -6471737.5 | L73: =L65 -> -6665889.6 | M73: =M65 -> -6865866.3 | N73: =N65 -> -7071842.3 | O73: =O65 -> -7283997.5 | ... AP73: =AP65 -> -16179864
A74: (+) Receita Bruta | D74: =SUM(H74:AQ74) -> 1.896446e+09 | H74: =H58 -> 5046.7704 | I74: =I58 -> 21002649 | J74: =J58 -> 34044271 | K74: =K58 -> 35065825 | L74: =L58 -> 36118042 | M74: =M58 -> 37201841 | N74: =N58 -> 38318173 | O74: =O58 -> 39468014 | ... AP74: =AP58 -> 87698999
A75: (-) Depreciação/Amortização | D75: =SUM(H75:AQ75) -> -51362715 | H75: =H70 -> 0 | I75: =I70 -> -4480395.6 | J75: =J70 -> -4614807.5 | K75: =K70 -> -4753251.7 | L75: =L70 -> -4895849.3 | M75: =M70 -> -5042724.7 | N75: =N70 -> -5194006.5 | O75: =O70 -> -5349826.7 | ... AP75: =AP70 -> 0
A76: CAPEX | D76: =SUM(H76:AQ76) -> -1.1651243e+08 | H76: =H77 -> -1.1651243e+08 | I76: =I77 -> 0 | J76: =J77 -> 0 | K76: =K77 -> 0 | L76: =L77 -> 0 | M76: =M77 -> 0 | N76: =N77 -> 0 | O76: =O77 -> 0 | ... AP76: =AP77 -> 0
A77: (-) Licenciamento e Equipamentos | D77: =SUM(H77:AQ77) -> -1.1651243e+08 | H77: =H52*H30 -> -1.1651243e+08 | I77: =I52*I30 -> 0 | J77: =J52*J30 -> 0 | K77: =K52*K30 -> 0 | L77: =L52*L30 -> 0 | M77: =M52*M30 -> 0 | N77: =N52*N30 -> 0 | O77: =O52*O30 -> 0 | ... AP77: =AP52*AP30 -> 0
A79: Fluxo de caixa livre para firma | D79: =SUM(H79:AQ79) -> 1.6926365e+10 | H79: =H72+H76 -> -1.1650738e+08 | I79: =I72+I76+H79 -> -1.0497075e+08 | J79: =J72+J76+I79 -> -81824528 | K79: =K72+K76+J79 -> -57983692 | L79: =L72+L76+K79 -> -33427388 | M79: =M72+M76+L79 -> -8134138.2 | N79: =N72+N76+M79 -> 17918186 | O79: =O72+O76+N79 -> 44752375 | P79: =P72+P76+O79 -> 72391906 | ... AP79: =AP72+AP76+AO79 -> 1.3775179e+09
A82: VPL
A83: Receita Bruta - URE MARÍLIA - BIO+GAS | D83: =H83 -> 3.7343332e+08 | H83: =SUM(H84:H89) -> 3.7343332e+08
A84: (+) Receita Contraprestação fixa | D84: =H84 -> 86256470 | H84: =NPV(10%,H59:AP59) -> 86256470
A85: (+) Receita Reciclável | D85: =H85 -> 102981.85 | H85: =NPV(10%,H60:AP60) -> 102981.85
A86: (+) Receita Biometano | D86: =H86 -> 96762066 | H86: =NPV(10%,H61:AP61) -> 96762066
A87: (+) Receita Energia Elétrica | D87: =H87 -> 1.2979865e+08 | H87: =NPV(10%,H62:AP62) -> 1.2979865e+08
A88: (+) Receita CO2 | D88: =H88 -> 54428662 | H88: =NPV(10%,H63:AP63) -> 54428662
A89: (+) CBIOS | D89: =H89 -> 6084490.9 | H89: =NPV(10%,H64:AP64) -> 6084490.9
A90: Impostos | D90: =H90 -> -69830953 | H90: =SUM(H91:H92) -> -69830953
A91: (-) Impostos Serviço | D91: =H91 -> -29327200 | H91: =NPV(10%,H66:AP66) -> -29327200
A92: (-) Impostos Produto | D92: =H92 -> -40503754 | H92: =NPV(10%,H67:AP67) -> -40503754
A93: OPEX | D93: =H93 -> -67628189 | H93: =SUM(H94:H94) -> -67628189
A94: =A69 -> (-) Custos com operacionais | D94: =H94 -> -67628189 | H94: =NPV(10%,H69:AP69) -> -67628189
A95: Custos de construção | D95: =H95 -> -28038086 | H95: =H96 -> -28038086
A96: (-) Depreciação/Amortização | D96: =H96 -> -28038086 | H96: =NPV(10%,H71:AP71) -> -28038086
A97: (=) EBIT | D97: =H97 -> 2.7556428e+08 | H97: =SUM(H98:H100) -> 2.7556428e+08
A98: (-) Impostos sobre EBIT | D98: =H98 -> -69830953 | H98: =NPV(10%,H73:AP73) -> -69830953
A99: (+) Receita Bruta | D99: =H99 -> 3.7343332e+08 | H99: =NPV(10%,H74:AP74) -> 3.7343332e+08
A100: (-) Depreciação/Amortização | D100: =H100 -> -28038086 | H100: =NPV(10%,H75:AP75) -> -28038086
A101: CAPEX | D101: =H101 -> -1.0592039e+08 | H101: =H102 -> -1.0592039e+08
A102: (-) Equipamentos | D102: =H102 -> -1.0592039e+08 | H102: =NPV(10%,H77:AP77) -> -1.0592039e+08
D103: =H103 -> 0
A104: Fluxo de caixa livre para firma | D104: =H104 -> 1.3759054e+09 | H104: =NPV(10%,H79:AP79) -> 1.3759054e+09
A107: Waterfall VPL
D108: TOTAL | E108: Base 100
A109: =A84 -> (+) Receita Contraprestação fixa | B109: =B84 -> 0 | C109: =C84 -> 0 | D109: =D84 -> 86256470 | E109: =D109/SUM($D$109:$D$119) -> 0.84552153
A110: =A85 -> (+) Receita Reciclável | B110: =B85 -> 0 | C110: =C85 -> 0 | D110: =D85 -> 102981.85 | E110: =D110/SUM($D$109:$D$119) -> 0.0010094706
A111: =A86 -> (+) Receita Biometano | B111: =B86 -> 0 | C111: =C86 -> 0 | D111: =D86 -> 96762066 | E111: =D111/SUM($D$109:$D$119) -> 0.94850171
A112: =A87 -> (+) Receita Energia Elétrica | B112: =B87 -> 0 | C112: =C87 -> 0 | D112: =D87 -> 1.2979865e+08 | E112: =D112/SUM($D$109:$D$119) -> 1.2723399
A113: =A88 -> (+) Receita CO2 | B113: =B88 -> 0 | C113: =C88 -> 0 | D113: =D88 -> 54428662 | E113: =D113/SUM($D$109:$D$119) -> 0.53353221
A114: =A89 -> (+) CBIOS | B114: =B89 -> 0 | C114: =C89 -> 0 | D114: =D89 -> 6084490.9 | E114: =D114/SUM($D$109:$D$119) -> 0.059642691
A115: =A91 -> (-) Impostos Serviço | B115: =B91 -> 0 | C115: =C91 -> 0 | D115: =D91 -> -29327200 | E115: =D115/SUM($D$109:$D$119) -> -0.28747732
A116: =A92 -> (-) Impostos Produto | B116: =B92 -> 0 | C116: =C92 -> 0 | D116: =D92 -> -40503754 | E116: =D116/SUM($D$109:$D$119) -> -0.39703451
...

Sheet Premissas
A1: Premissas | B1: Unidade | D1: VALOR ATIVO | E1: Unidade | F1: Fonte
A2: PARÂMETROS DE VALORAÇÃO
A3: Primeiro ano de projeção do modelo financeiro | D3: 2026 | E3: [ano] | F3: Alterar no início e manter fixo posteriormente (para manter inputs consistentes com anos)
A4: Ano base de inflação | D4: 2026 | E4: [ano]
A5: Data de valoração (31/12/....) | D5: 2026 | E5: [data]
A6: Taxa de desconto para projeto | B6: % a.a. real | D6: =#REF! -> #REF! | E6: % a.a. real
A7: Taxa de desconto para acionista | B7: % a.a. real | D7: =#REF! -> #REF! | E7: % a.a. real
A8: Modelo calculado em termos nominais ou reais? | D8: =MATCH('LOTE 3'!$B$4,'LOTE 3'!BL3:BL4,0) -> 1 | E8: [1: Nominais; 2: Reais]
A9: Considera receita financeira? | D9: 1 | E9: [1: Sim; 2: Não]
A11: PARÂMETROS DE CONTRATO
A12: TIMING
A13: Data de início de projeto | D13: 45658 | E13: [data]
A14: Anos de projeto | D14: 35 | E14: anos
A15: Término de projeto | D15: =EDATE(D13,12*D14) -> 58441 | E15: [data]
A16: 1o ano de projeto | D16: =YEAR(D13) -> 2025 | E16: [ano]
A17: 1o ano de operação | D17: 2027 | E17: [ano] | F17: [Utilizado para fins de início de depreciação e ativação de juros capitalizados]
A18: Último ano do projeto | D18: =YEAR(D15)-1 -> 2059 | E18: [ano]
A20: CAPEX GARANTIDO (reinvestimentos) | B20: ='LOTE 3'!$B$7 -> 2.8540916
A21: =Capex!A8 -> URE MARÍLIA - BIO+GÁS | B21: flag
A22: =Capex!A9 -> Custos pré-operacionais | B22: =IF($B$20>0,"G","NG") -> G | C22: [G: garantido; NG: não garantido]
A23: =Capex!A10 -> Licenciamento (estudos, projetos e licenças) | B23: NG | C23: [G: garantido; NG: não garantido]
A24: =Capex!A13 -> URE MARÍLIA - BIO
A25: =Capex!A14 -> Custos pré-operacionais | B25: =IF($B$20>0,"G","NG") -> G | C25: [G: garantido; NG: não garantido]
A26: =Capex!A15 -> Licenciamento (estudos, projetos e licenças) | B26: NG | C26: [G: garantido; NG: não garantido]
A27: =Capex!A18 -> URE MARÍLIA - GÁS
A28: =Capex!A19 -> Custos pré-operacionais | B28: =IF($B$20>0,"G","NG") -> G | C28: [G: garantido; NG: não garantido]
A29: =Capex!A20 -> Licenciamento (estudos, projetos e licenças) | B29: NG | C29: [G: garantido; NG: não garantido]
A31: FINANCIAMENTO | D31: =#REF! -> #REF! | E31: =#REF! -> #REF! | F31: =#REF! -> #REF! | G31: =#REF! -> #REF! | H31: =#REF! -> #REF! | I31: =#REF! -> #REF! | J31: =#REF! -> #REF! | K31: =#REF! -> #REF! | L31: =#REF! -> #REF!
D32: 1 | E32: 2 | F32: 3 | G32: 4 | H32: 5 | I32: 6 | J32: 7 | K32: 8 | L32: CAIXA
A33: Linha de financiamento | D33: FINEM | E33: FINEM | F33: FINEM | G33: FINEM | H33: FINEM | I33: FINEM | J33: FINEM | K33: FINEM
A34: Primeiro pagamento amortização | B34: data | D34: =#REF! -> #REF! | E34: =#REF! -> #REF! | F34: =#REF! -> #REF! | G34: =#REF! -> #REF! | H34: =#REF! -> #REF! | I34: =#REF! -> #REF! | J34: =#REF! -> #REF! | K34: =#REF! -> #REF! | L34: =#REF! -> #REF!
A35: Último pagamento amortização | B35: data | D35: =D34+D38 -> #REF! | E35: =E34+E38 -> #REF! | F35: =F34+F38 -> #REF! | G35: =G34+G38 -> #REF! | H35: =H34+H38 -> #REF! | I35: =I34+I38 -> #REF! | J35: =J34+J38 -> #REF! | K35: =K34+K38 -> #REF! | L35: =L34+L38 -> #REF!
A36: Início de captação | B36: data | D36: 2024 | E36: 2029 | F36: 2034 | G36: 2039 | H36: 2044 | I36: 2046 | J36: 2049 | K36: 2054
A37: Duração de captação | B37: anos | D37: 3 | E37: 1 | F37: 3 | G37: 1 | H37: 2 | I37: 1 | J37: 1 | K37: 2
A38: Prazo da amortização | B38: anos | D38: 31 | E38: 5 | F38: 5 | G38: 5 | H38: 5 | I38: 5 | J38: 5 | K38: 3 | L38: 20
A39: Prazo da carência | B39: anos | D39: 3 | E39: 1 | F39: 1 | G39: 1 | H39: 1 | I39: 1 | J39: 1 | K39: 1 | L39: 4
A40: Anos entre captação e primeiro pagamento de juros | B40: anos | D40: =D39 -> 3 | E40: =E39 -> 1 | F40: =F39 -> 1 | G40: =G39 -> 1 | H40: =H39 -> 1 | I40: =I39 -> 1 | J40: =J39 -> 1 | K40: =K39 -> 1 | L40: =L39 -> 4
A41: Alavancagem | B41: % | D41: 0 | E41: 0 | F41: 0 | G41: 0 | H41: 0 | I41: 0 | J41: 0 | K41: 0 | L41: 0
A43: Empréstimo Ponte
A44: Spread empréstimo ponte | D44: 0.03 | E44: % a.a.
A46: % máximo de financiamento com empréstimo ponte | D46: 0.5 | E46: % de capex financiável
A47: % de financiamento com empréstimo ponte | D47: =D$46*D57 -> 0.5 | E47: % de capex financiável | F47: Baseado em condições de financiamento do PIL 2015. Quando necessário, reduzido % de captação para permitir atendimento de covenants
A49: Ano de início de ciclo, captação de empréstimo ponte | D49: =D16 -> 2025 | E49: [ano]
A51: Empréstimo de Longo Prazo #1 - FINAME BK AQUISIÇÃO E COMERCIALIZAÇÃO | Q51: Ano | R51: Fator Alfa
A52: Método de financiamento | D52: 1 | E52: [1: SAC; 2: Price] | Q52: 2018 | R52: 0.57 | U52: Fonte fator alfa | V52: BNDES [Metodologia de cálculo da TLP]
A53: Spread FINEN | C53: FINEM | D53: =SUM(H53,J53,L53) -> 0.0725 | E53: % a.a. | H53: =(S57/R57) -> 0.0615 | I53: Custo Financeiro | J53: 0.011 | K53: Remuneração BNDES | L53: 0 | M53: Taxa de risco de crédito | Q53: 2019 | R53: 0.66 | U53: Fonte TLP | V53: BNDES [Histórico da parcela fixa da TLP]
A54: Spread FINAME | C54: FINAME | D54: =SUM(H54,J54,L54) -> 0.0845 | E54: % a.a. | H54: =(S57/R57) -> 0.0615 | I54: Custo Financeiro | J54: 0.013 | K54: Remuneração BNDES | L54: 0.01 | M54: Taxa de risco de crédito | Q54: 2020 | R54: 0.74 | U54: Fonte Remuneração BNDES | V54: BNDES [BK Aquisição e Comercialização]
A55: Taxa bancária | D55: 0 | E55: do valor captado | Q55: 2021 | R55: 0.83
Q56: 2022 | R56: 0.91
A57: % de financiamento máximo captado | D57: 1 | E57: % de máximo financiamento | F57: Valor que permite cumprimento de covenants | Q57: 2023 | R57: 1 | S57: 0.0615 | T57: 44986
A58: Tipo de taxa | D58: 1 | E58: [1: real; 2: nominal]
A60: Empréstimo de Longo Prazo #2 - CAIXA SANEAMENTO PARA TODOS
A61: Método de financiamento | D61: 1 | E61: [1: SAC; 2: Price]
A62: Juros nominal longo prazo CAIXA | D62: =SUM(H62,J62,L62) -> 0.09 | E62: % a.a. | H62: 0.06 | I62: Custo Financeiro | J62: 0.02 | K62: Remuneração BNDES | L62: 0.01 | M62: Taxa de risco de crédito
A63: Taxa bancária | D63: 0.005 | E63: do valor captado
A64: Máxima taxa bancária | D64: -300 | E64: M R$
A66: % máximo de financiamento com longo prazo CAIXA | D66: =Premissas!$L$41 -> 0 | E66: % de capex financiável
A67: % de financiamento máximo captado | D67: 1 | E67: % de máximo financiamento | F67: Valor que permite cumprimento de covenants
A68: % de financiamento com longo prazo CAIXA | D68: =D$66*D67 -> 0 | E68: % de capex financiável
A70: Prazo para estruturação de empréstimo de longo prazo | D70: 0 | E70: anos (para estruturar empréstimo de longo prazo)
A71: Ano de captação de empréstimo de longo prazo | D71: =D49+D70 -> 2025 | E71: [ano]
A72: Horizonte de captação do ciclo | D72: 2 | E72: anos
A73: Prazo de captação de empréstimo CAIXA | D73: =D72-D70 -> 2 | E73: anos | F73: Baseado em horizonte de captação do ciclo
A74: Ano de entrada em operação de ativo finaciado | D74: =D49+D72-1 -> 2026 | E74: [ano] | F74: Baseado em horizonte de captação do ciclo
A75: Tipo de taxa | D75: 1 | E75: [1: real; 2: nominal]
A77: Parcelas de amortização | D77: =Premissas!L38 -> 20 | E77: parcelas anuais | F77: https://www.caixa.gov.br/Downloads/fgts-manual-fomento-agente-operador/MFOM_SANEAMENTO_PARA_TODOS_VERSAO_3_26.pdf
A78: Anos entre captação e primeiro pagamento de amortização de empréstimo | D78: =Premissas!L39 -> 4 | E78: anos
A79: Anos entre captação e primeiro pagamento de juros de empréstimo | D79: 4 | E79: anos
A82: CAPEX DE MANUTENÇÃO
A83: % de valor reinvestido anualmente
A84: Com vida útil de 5 anos | D84: =PMT(D$6,D94,0,-100%,0) -> #REF! | E84: % de valor reinvestido a.a. | F84: Valor necessário de investimento ano a ano, ajustado por fator de desconto, para permitir reposição de ativo ao final de sua vida útil
A85: Com vida útil de 10 anos | D85: =PMT(D$6,D95,0,-100%,0) -> #REF! | E85: % de valor reinvestido a.a. | F85: Valor necessário de investimento ano a ano, ajustado por fator de desconto, para permitir reposição de ativo ao final de sua vida útil
A86: Com vida útil de 25 anos | D86: =PMT(D$6,D96,0,-100%,0) -> #REF! | E86: % de valor reinvestido a.a. | F86: Valor necessário de investimento ano a ano, ajustado por fator de desconto, para permitir reposição de ativo ao final de sua vida útil
A88: Auxiliar: Vida útil fiscal
A89: Com vida útil fiscal de 5 anos | D89: 5 | E89: anos
A90: Com vida útil fiscal de 10 anos | D90: 10 | E90: anos
A91: Com vida útil fiscal de 25 anos | D91: 25 | E91: anos
A93: Auxiliar: Vida útil efetiva
A94: Com vida útil fiscal de 5 anos | D94: =D89*D$98 -> 7.5 | E94: anos
A95: Com vida útil fiscal de 10 anos | D95: =D90*D$98 -> 15 | E95: anos
A96: Com vida útil fiscal de 25 anos | D96: =D91*D$98 -> 37.5 | E96: anos
A98: Vida útil efetiva, como proporção de vida útil fiscal | D98: 1.5 | E98: % de vida útil fiscal
A101: DIVIDENDOS
A102: Reserva Legal
A103: Reserva Legal | D103: 0.05 | E103: % do lucro líquido
A104: Limite para constituição da reserva legal | D104: 0.2 | E104: % do capital social
A106: Meta de pagamento de dividendos
A107: Meta pagamento de dividendos | D107: 1 | E107: % Lucro líquido ajustado pela Reserva Legal
A110: PREMISSAS FINANCEIRAS
A111: Alíquotas Impostos
A112: ISS | D112: Planilha Receita Tarifária
A113: PIS/Cofins
A114: Não Cumulativo | D114: 0.0925 | E114: % receita bruta
A115: Cumulativo | D115: 0.0365 | E115: % receita bruta
A116: PIS/COFINS sobre Receita Financeira
A117: Não Cumulativo | D117: 0.0465 | E117: % receita financeira | F117: Decreto nº 8.426, de 1º de abril de 2015
A118: Cumulativo | D118: 0 | E118: % receita financeira
A119: Créditos gerados com Opex no período
A120: Pessoal | D120: 0 | E120: % sobre PIS/Cofins não cumulativo Opex
A121: Outros Custos | D121: 0.8 | E121: % sobre PIS/Cofins não cumulativo Opex
...

Sheet Apoio
F2: Projeção Macroeconômica – Brasil (% a.a.) | Q2: Projeção Anual de Demanda de RSD – Marília/SP (2025–2059)
F4: Horizonte: 35 anos
F6: Ano | G6: IPCA (%) | H6: Selic (%) | I6: PIB (%) | K6: Ano | M6: Selic | N6: IPCA | O6: PIB | Q6: Ano | R6: População estimada | S6: Geração de RSD (t/dia) | T6: Geração de RSD (t/ano) | V6: Ano | X6: População | Y6: RSU | Z6: RSU
F7: 2025 | G7: 4.8 | H7: 15 | I7: 2.2 | M7: % a.a. | N7: % a.a. | O7: % a.a. | Q7: 2025 | R7: 248526 | S7: 201.5 | T7: 63070 | Y7: t/dia | Z7: t/ano
F8: 2026 | G8: 4.3 | H8: 12.3 | I8: 1.8 | K8: 1 | L8: 2026 | M8: 15 | N8: 4.8 | O8: 2.2 | Q8: 2026 | R8: 250440 | S8: 203.1 | T8: 63570 | V8: 1 | W8: 2026 | X8: 248526 | Y8: 201.5 | Z8: 63070
F9: 2027 | G9: 3.9 | H9: 10.5 | I9: 1.8 | K9: 2 | L9: 2027 | M9: 12.3 | N9: 4.3 | O9: 1.8 | Q9: 2027 | R9: 252369 | S9: 204.6 | T9: 64060 | V9: 2 | W9: 2027 | X9: 250440 | Y9: 203.1 | Z9: 63570
F10: 2028 | G10: 3.7 | H10: 9.5 | I10: 2 | K10: 3 | L10: 2028 | M10: 10.5 | N10: 3.9 | O10: 1.8 | Q10: 2028 | R10: 254313 | S10: 206.2 | T10: 64560 | V10: 3 | W10: 2028 | X10: 252369 | Y10: 204.6 | Z10: 64060
F11: 2029 | G11: 3.6 | H11: 9 | I11: 2.1 | K11: 4 | L11: 2029 | M11: 9.5 | N11: 3.7 | O11: 2 | Q11: 2029 | R11: 256230 | S11: 207.8 | T11: 65070 | V11: 4 | W11: 2029 | X11: 254313 | Y11: 206.2 | Z11: 64560
F12: 2030 | G12: 3.5 | H12: 8.8 | I12: 2.2 | K12: 5 | L12: 2030 | M12: 9 | N12: 3.6 | O12: 2.1 | Q12: 2030 | R12: 258242 | S12: 209.4 | T12: 65570 | V12: 5 | W12: 2030 | X12: 256230 | Y12: 207.8 | Z12: 65070
F13: 2031 | G13: 3.4 | H13: 8.6 | I13: 2.3 | K13: 6 | L13: 2031 | M13: 8.8 | N13: 3.5 | O13: 2.2 | Q13: 2031 | R13: 260277 | S13: 211.1 | T13: 66080 | V13: 6 | W13: 2031 | X13: 258242 | Y13: 209.4 | Z13: 65570
F14: 2032 | G14: 3.3 | H14: 8.4 | I14: 2.4 | K14: 7 | L14: 2032 | M14: 8.6 | N14: 3.4 | O14: 2.3 | Q14: 2032 | R14: 262335 | S14: 212.8 | T14: 66600 | V14: 7 | W14: 2032 | X14: 260277 | Y14: 211.1 | Z14: 66080
F15: 2033 | G15: 3.2 | H15: 8.2 | I15: 2.5 | K15: 8 | L15: 2033 | M15: 8.4 | N15: 3.3 | O15: 2.4 | Q15: 2033 | R15: 264416 | S15: 214.5 | T15: 67120 | V15: 8 | W15: 2033 | X15: 262335 | Y15: 212.8 | Z15: 66600
F16: 2034 | G16: 3.1 | H16: 8 | I16: 2.5 | K16: 9 | L16: 2034 | M16: 8.2 | N16: 3.2 | O16: 2.5 | Q16: 2034 | R16: 266189 | S16: 215.9 | T16: 67590 | V16: 9 | W16: 2034 | X16: 264416 | Y16: 214.5 | Z16: 67120
F17: 2035 | G17: 3 | H17: 7.8 | I17: 2.6 | K17: 10 | L17: 2035 | M17: 8 | N17: 3.1 | O17: 2.5 | Q17: 2035 | R17: 268315 | S17: 217.7 | T17: 68140 | V17: 10 | W17: 2035 | X17: 266189 | Y17: 215.9 | Z17: 67590
F18: 2036 | G18: 3 | H18: 7.6 | I18: 2.6 | K18: 11 | L18: 2036 | M18: 7.8 | N18: 3 | O18: 2.6 | Q18: 2036 | R18: 270463 | S18: 219.4 | T18: 68690 | V18: 11 | W18: 2036 | X18: 268315 | Y18: 217.7 | Z18: 68140
F19: 2037 | G19: 3 | H19: 7.5 | I19: 2.6 | K19: 12 | L19: 2037 | M19: 7.6 | N19: 3 | O19: 2.6 | Q19: 2037 | R19: 272633 | S19: 221.2 | T19: 69250 | V19: 12 | W19: 2037 | X19: 270463 | Y19: 219.4 | Z19: 68690
... F41: 2059 | G41: 3 | H41: 6.5 | I41: 2.6 | K41: 34 | L41: 2059 | M41: 6.5 | N41: 3 | O41: 2.6 | Q41: 2059 | R41: 321923 | S41: 261.1 | T41: 81730 | V41: 34 | W41: 2059 | X41: 319686 | Y41: 259.2 | Z41: 81130
K42: 35 | L42: 2060 | M42: 6.5 | N42: 3 | O42: 2.6 | V42: 35 | W42: 2060 | X42: 321923 | Y42: 261.1 | Z42: 81730
H47: 0.45 | I47: 0.34 | J47: 0.05 | K47: 0.16
F48: Ano | G48: Geração de RSD (t/ano) | H48: úmida | I48: seca | J48: metais /vidros | K48: Rejeitos | M48: Materiais segregados
F49: 2025 | G49: 63070 | H49: =$H47*G49 -> 28381.5 | I49: =G49*$I$47 -> 21443.8 | J49: =G49*$J$47 -> 3153.5 | K49: =G49*$K$47 -> 10091.2 | M49: Ano | O49: RSU | P49: Metais Vidros | Q49: Fração Úmida | R49: Fração Seca | S49: Rejeitos
F50: 2026 | G50: 63570 | H50: =$H$47*G50 -> 28606.5 | I50: =G50*$I$47 -> 21613.8 | J50: =G50*$J$47 -> 3178.5 | K50: =G50*$K$47 -> 10171.2 | O50: t/ano | P50: t/ano | Q50: t/ano | R50: t/ano | S50: t/ano
F51: 2027 | G51: 64060 | H51: =$H$47*G51 -> 28827 | I51: =G51*$I$47 -> 21780.4 | J51: =G51*$J$47 -> 3203 | K51: =G51*$K$47 -> 10249.6 | M51: 1 | N51: 2026 | O51: 63070 | P51: 3153.5 | Q51: 28381.5 | R51: 21443.8 | S51: 10091.2
F52: 2028 | G52: 64560 | H52: =$H$47*G52 -> 29052 | I52: =G52*$I$47 -> 21950.4 | J52: =G52*$J$47 -> 3228 | K52: =G52*$K$47 -> 10329.6 | M52: 2 | N52: 2027 | O52: 63570 | P52: 3178.5 | Q52: 28606.5 | R52: 21613.8 | S52: 10171.2
F53: 2029 | G53: 65070 | H53: =$H$47*G53 -> 29281.5 | I53: =G53*$I$47 -> 22123.8 | J53: =G53*$J$47 -> 3253.5 | K53: =G53*$K$47 -> 10411.2 | M53: 3 | N53: 2028 | O53: 64060 | P53: 3203 | Q53: 28827 | R53: 21780.4 | S53: 10249.6
F54: 2030 | G54: 65570 | H54: =$H$47*G54 -> 29506.5 | I54: =G54*$I$47 -> 22293.8 | J54: =G54*$J$47 -> 3278.5 | K54: =G54*$K$47 -> 10491.2 | M54: 4 | N54: 2029 | O54: 64560 | P54: 3228 | Q54: 29052 | R54: 21950.4 | S54: 10329.6
F55: 2031 | G55: 66080 | H55: =$H$47*G55 -> 29736 | I55: =G55*$I$47 -> 22467.2 | J55: =G55*$J$47 -> 3304 | K55: =G55*$K$47 -> 10572.8 | M55: 5 | N55: 2030 | O55: 65070 | P55: 3253.5 | Q55: 29281.5 | R55: 22123.8 | S55: 10411.2
F56: 2032 | G56: 66600 | H56: =$H$47*G56 -> 29970 | I56: =G56*$I$47 -> 22644 | J56: =G56*$J$47 -> 3330 | K56: =G56*$K$47 -> 10656 | M56: 6 | N56: 2031 | O56: 65570 | P56: 3278.5 | Q56: 29506.5 | R56: 22293.8 | S56: 10491.2
F57: 2033 | G57: 67120 | H57: =$H$47*G57 -> 30204 | I57: =G57*$I$47 -> 22820.8 | J57: =G57*$J$47 -> 3356 | K57: =G57*$K$47 -> 10739.2 | M57: 7 | N57: 2032 | O57: 66080 | P57: 3304 | Q57: 29736 | R57: 22467.2 | S57: 10572.8
F58: 2034 | G58: 67590 | H58: =$H$47*G58 -> 30415.5 | I58: =G58*$I$47 -> 22980.6 | J58: =G58*$J$47 -> 3379.5 | K58: =G58*$K$47 -> 10814.4 | M58: 8 | N58: 2033 | O58: 66600 | P58: 3330 | Q58: 29970 | R58: 22644 | S58: 10656
F59: 2035 | G59: 68140 | H59: =$H$47*G59 -> 30663 | I59: =G59*$I$47 -> 23167.6 | J59: =G59*$J$47 -> 3407 | K59: =G59*$K$47 -> 10902.4 | M59: 9 | N59: 2034 | O59: 67120 | P59: 3356 | Q59: 30204 | R59: 22820.8 | S59: 10739.2
F60: 2036 | G60: 68690 | H60: =$H$47*G60 -> 30910.5 | I60: =G60*$I$47 -> 23354.6 | J60: =G60*$J$47 -> 3434.5 | K60: =G60*$K$47 -> 10990.4 | M60: 10 | N60: 2035 | O60: 67590 | P60: 3379.5 | Q60: 30415.5 | R60: 22980.6 | S60: 10814.4
F61: 2037 | G61: 69250 | H61: =$H$47*G61 -> 31162.5 | I61: =G61*$I$47 -> 23545 | J61: =G61*$J$47 -> 3462.5 | K61: =G61*$K$47 -> 11080 | M61: 11 | N61: 2036 | O61: 68140 | P61: 3407 | Q61: 30663 | R61: 23167.6 | S61: 10902.4
F62: 2038 | G62: 69800 | H62: =$H$47*G62 -> 31410 | I62: =G62*$I$47 -> 23732 | J62: =G62*$J$47 -> 3490 | K62: =G62*$K$47 -> 11168 | M62: 12 | N62: 2037 | O62: 68690 | P62: 3434.5 | Q62: 30910.5 | R62: 23354.6 | S62: 10990.4
... F83: 2059 | G83: 81730 | H83: =$H$47*G83 -> 36778.5 | I83: =G83*$I$47 -> 27788.2 | J83: =G83*$J$47 -> 4086.5 | K83: =G83*$K$47 -> 13076.8 | M83: 33 | N83: 2058 | O83: 80500 | P83: 4025 | Q83: 36225 | R83: 27370 | S83: 12880
M84: 34 | N84: 2059 | O84: 81130 | P84: 4056.5 | Q84: 36508.5 | R84: 27584.2 | S84: 12980.8
M85: 35 | N85: 2060 | O85: 81730 | P85: 4086.5 | Q85: 36778.5 | R85: 27788.2 | S85: 13076.8

Sheet VfM
A1: Value for Money | K1: =L1-1 -> 2021 | L1: =M1-1 -> 2022 | M1: =N1-1 -> 2023 | N1: =O1-1 -> 2024 | O1: =YEAR(Premissas!$D$13) -> 2025 | P1: =O1+1 -> 2026 | Q1: =P1+1 -> 2027 | R1: =Q1+1 -> 2028 | S1: =R1+1 -> 2029 | T1: =S1+1 -> 2030 | U1: =T1+1 -> 2031 | V1: =U1+1 -> 2032 | W1: =V1+1 -> 2033 | ... BA1: =AZ1+1 -> 2063
A2: Índice de inflação brasileira (IPCA) | L2: =MacroEco!X8 -> 0.93249867 | M2: =MacroEco!Y8 -> 0.98644232 | N2: =MacroEco!Z8 -> 1.0351726 | O2: =MacroEco!AA8 -> 1.0714036 | P2: =MacroEco!AB8 -> 1.1035457 | Q2: =MacroEco!AC8 -> 1.1366521 | R2: =MacroEco!AD8 -> 1.1707517 | S2: =MacroEco!AE8 -> 1.2058742 | ... BA2: =MacroEco!BM8 -> 0
A4: Concessão | D4: =Premissas!D6 -> #REF! | E4: a.a. real
A5: Remuneração do Poder Concedente | B5: MM R$ | D5: {=SUMPRODUCT(O5:AW5,(1/$O$2:$AW$2),$O$15:$AW$15)} -> #REF! | E5: MM R$@2021 | O5: 0 | P5: 0 | Q5: 0 | R5: 0 | S5: 0 | T5: 0 | U5: 0 | V5: 0 | W5: 0 | X5: 0 | Y5: 0 | Z5: 0 | AA5: 0 | AB5: 0 | AC5: 0 | AD5: 0 | AE5: 0 | AF5: 0 | AG5: 0 | AH5: 0 | AI5: 0 | AJ5: 0 | AK5: 0 | AL5: 0 | AM5: 0 | AN5: 0 | AO5: 0 | AP5: 0 | AQ5: 0 | AR5: 0 | AS5: 0 | AT5: 0 | AU5: 0 | AV5: 0 | AW5: 0 | AX5: 0 | AY5: 0 | AZ5: 0 | BA5: 0
A6: Fiscalização da Agência Reguladora | B6: MM R$ | D6: {=SUMPRODUCT(O6:AW6,(1/$O$2:$AW$2),$O$15:$AW$15)} -> #REF! | E6: MM R$@2021 | O6: 0 | P6: 0 | Q6: 0 | R6: 0 | S6: 0 | T6: 0 | U6: 0 | V6: 0 | W6: 0 | X6: 0 | Y6: 0 | Z6: 0 | AA6: 0 | AB6: 0 | AC6: 0 | AD6: 0 | AE6: 0 | AF6: 0 | AG6: 0 | AH6: 0 | AI6: 0 | AJ6: 0 | AK6: 0 | AL6: 0 | AM6: 0 | AN6: 0 | AO6: 0 | AP6: 0 | AQ6: 0 | AR6: 0 | AS6: 0 | AT6: 0 | AU6: 0 | AV6: 0 | AW6: 0 | AX6: 0 | AY6: 0 | AZ6: 0 | BA6: 0
A7: Custos e despesas | B7: MM R$ | D7: {=SUMPRODUCT(O7:AW7,(1/$O$2:$AW$2),$O$15:$AW$15)} -> #REF! | E7: MM R$@2021 | O7: 0 | P7: 0 | Q7: 0 | R7: 0 | S7: 0 | T7: 0 | U7: 0 | V7: 0 | W7: 0 | X7: 0 | Y7: 0 | Z7: 0 | AA7: 0 | AB7: 0 | AC7: 0 | AD7: 0 | AE7: 0 | AF7: 0 | AG7: 0 | AH7: 0 | AI7: 0 | AJ7: 0 | AK7: 0 | AL7: 0 | AM7: 0 | AN7: 0 | AO7: 0 | AP7: 0 | AQ7: 0 | AR7: 0 | AS7: 0 | AT7: 0 | AU7: 0 | AV7: 0 | AW7: 0 | AX7: 0 | AY7: 0 | AZ7: 0 | BA7: 0
A8: Contraprestação | B8: MM R$ | D8: {=SUMPRODUCT(O8:AW8,(1/$O$2:$AW$2),$O$15:$AW$15)} -> #REF! | E8: MM R$@2021 | O8: =-SUM(#REF!,#REF!) -> #REF! | P8: =-SUM(#REF!,#REF!) -> #REF! | Q8: =-SUM(#REF!,#REF!) -> #REF! | R8: =-SUM(#REF!,#REF!) -> #REF! | S8: =-SUM(#REF!,#REF!) -> #REF! | T8: =-SUM(#REF!,#REF!) -> #REF! | U8: =-SUM(#REF!,#REF!) -> #REF! | V8: =-SUM(#REF!,#REF!) -> #REF! | ... BA8: =-SUM(#REF!,#REF!) -> #REF!
A9: Investimentos | B9: MM R$ | D9: {=SUMPRODUCT(O9:AW9,(1/$O$2:$AW$2),$O$15:$AW$15)} -> #REF! | E9: MM R$@2021 | O9: 0 | P9: 0 | Q9: 0 | R9: 0 | S9: 0 | T9: 0 | U9: 0 | V9: 0 | W9: 0 | X9: 0 | Y9: 0 | Z9: 0 | AA9: 0 | AB9: 0 | AC9: 0 | AD9: 0 | AE9: 0 | AF9: 0 | AG9: 0 | AH9: 0 | AI9: 0 | AJ9: 0 | AK9: 0 | AL9: 0 | AM9: 0 | AN9: 0 | AO9: 0 | AP9: 0 | AQ9: 0 | AR9: 0 | AS9: 0 | AT9: 0 | AU9: 0 | AV9: 0 | AW9: 0 | AX9: 0 | AY9: 0 | AZ9: 0 | BA9: 0
A10: Sobrecustos operacionais | B10: MM R$ | D10: {=SUMPRODUCT(O10:AW10,(1/$O$2:$AW$2),$O$15:$AW$15)} -> #REF! | E10: MM R$@2021 | G10: 0 | H10: Sobrecusto/Desconto opção PSC | O10: =O7*$G10 -> 0 | P10: =P7*$G10 -> 0 | Q10: =Q7*$G10 -> 0 | R10: =R7*$G10 -> 0 | S10: =S7*$G10 -> 0 | T10: =T7*$G10 -> 0 | U10: =U7*$G10 -> 0 | V10: =V7*$G10 -> 0 | ... BA10: =BA7*$G10 -> 0
A11: Sobrecustos de obras | B11: MM R$ | D11: {=SUMPRODUCT(O11:AW11,(1/$O$2:$AW$2),$O$15:$AW$15)} -> #REF! | E11: MM R$@2021 | G11: 0 | H11: Sobrecusto/Desconto opção PSC | O11: =O9*$G11 -> 0 | P11: =P9*$G11 -> 0 | Q11: =Q9*$G11 -> 0 | R11: =R9*$G11 -> 0 | S11: =S9*$G11 -> 0 | T11: =T9*$G11 -> 0 | U11: =U9*$G11 -> 0 | V11: =V9*$G11 -> 0 | ... BA11: =BA9*$G11 -> 0
A12: Custos com licitação de obras | B12: MM R$ | D12: {=SUMPRODUCT(O12:AW12,(1/$O$2:$AW$2),$O$15:$AW$15)} -> #REF! | E12: MM R$@2021 | O12: 0 | P12: 0 | Q12: 0 | R12: 0 | S12: 0 | T12: 0 | U12: 0 | V12: 0 | W12: 0 | X12: 0 | Y12: 0 | Z12: 0 | AA12: 0 | AB12: 0 | AC12: 0 | AD12: 0 | AE12: 0 | AF12: 0 | AG12: 0 | AH12: 0 | AI12: 0 | AJ12: 0 | AK12: 0 | AL12: 0 | AM12: 0 | AN12: 0 | AO12: 0 | AP12: 0 | AQ12: 0 | AR12: 0 | AS12: 0 | AT12: 0 | AU12: 0 | AV12: 0 | AW12: 0 | AX12: 0 | AY12: 0 | AZ12: 0 | BA12: 0
A13: Impostos | B13: MM R$ | D13: {=SUMPRODUCT(O13:AW13,(1/$O$2:$AW$2),$O$15:$AW$15)} -> #REF! | E13: MM R$@2021 | O13: =-#REF!-#REF! -> #REF! | P13: =-#REF!-#REF! -> #REF! | Q13: =-#REF!-#REF! -> #REF! | R13: =-#REF!-#REF! -> #REF! | S13: =-#REF!-#REF! -> #REF! | T13: =-#REF!-#REF! -> #REF! | U13: =-#REF!-#REF! -> #REF! | V13: =-#REF!-#REF! -> #REF! | ... BA13: =-#REF!-#REF! -> #REF!
D14: =SUM(D5:D13) -> #REF!
A15: Fator de desconto | O15: =#REF! -> #REF! | P15: =#REF! -> #REF! | Q15: =#REF! -> #REF! | R15: =#REF! -> #REF! | S15: =#REF! -> #REF! | T15: =#REF! -> #REF! | U15: =#REF! -> #REF! | V15: =#REF! -> #REF! | ... BA15: =#REF! -> #REF!
A17: PSC | D17: 0.0617 | E17: a.a. real | F17: TESOURO IPCA+ 2035 com vencimento 15/05/2035 (https://www.tesourodireto.com.br/titulos/precos-e-taxas.htm) | G17: Acesso em: | H17: 45013
A18: Remuneração do Poder Concedente | B18: MM R$ | D18: {=SUMPRODUCT(O18:AW18,(1/$O$2:$AW$2),$O$28:$AW$28)} -> #REF! | E18: MM R$@2021 | O18: =SUM(#REF!) -> #REF! | P18: =SUM(#REF!) -> #REF! | Q18: =SUM(#REF!) -> #REF! | R18: =SUM(#REF!) -> #REF! | S18: =SUM(#REF!) -> #REF! | T18: =SUM(#REF!) -> #REF! | U18: =SUM(#REF!) -> #REF! | V18: =SUM(#REF!) -> #REF! | ... BA18: =SUM(#REF!) -> #REF!
A19: Fiscalização da Agência Reguladora | B19: MM R$ | D19: {=SUMPRODUCT(O19:AW19,(1/$O$2:$AW$2),$O$28:$AW$28)} -> #REF! | E19: MM R$@2021 | O19: 0 | P19: 0 | Q19: 0 | R19: 0 | S19: 0 | T19: 0 | U19: 0 | V19: 0 | W19: 0 | X19: 0 | Y19: 0 | Z19: 0 | AA19: 0 | AB19: 0 | AC19: 0 | AD19: 0 | AE19: 0 | AF19: 0 | AG19: 0 | AH19: 0 | AI19: 0 | AJ19: 0 | AK19: 0 | AL19: 0 | AM19: 0 | AN19: 0 | AO19: 0 | AP19: 0 | AQ19: 0 | AR19: 0 | AS19: 0 | AT19: 0 | AU19: 0 | AV19: 0 | AW19: 0 | AX19: 0 | AY19: 0 | AZ19: 0 | BA19: 0
A20: Custos e despesas | B20: MM R$ | D20: {=SUMPRODUCT(O20:AW20,(1/$O$2:$AW$2),$O$28:$AW$28)} -> #REF! | E20: MM R$@2021 | O20: =#REF! -> #REF! | P20: =#REF! -> #REF! | Q20: =#REF! -> #REF! | R20: =#REF! -> #REF! | S20: =#REF! -> #REF! | T20: =#REF! -> #REF! | U20: =#REF! -> #REF! | V20: =#REF! -> #REF! | ... BA20: =#REF! -> #REF!
A21: Contraprestação | B21: MM R$ | D21: {=SUMPRODUCT(O21:AW21,(1/$O$2:$AW$2),$O$28:$AW$28)} -> #REF! | E21: MM R$@2021 | O21: 0 | P21: 0 | Q21: 0 | R21: 0 | S21: 0 | T21: 0 | U21: 0 | V21: 0 | W21: 0 | X21: 0 | Y21: 0 | Z21: 0 | AA21: 0 | AB21: 0 | AC21: 0 | AD21: 0 | AE21: 0 | AF21: 0 | AG21: 0 | AH21: 0 | AI21: 0 | AJ21: 0 | AK21: 0 | AL21: 0 | AM21: 0 | AN21: 0 | AO21: 0 | AP21: 0 | AQ21: 0 | AR21: 0 | AS21: 0 | AT21: 0 | AU21: 0 | AV21: 0 | AW21: 0 | AX21: 0 | AY21: 0 | AZ21: 0 | BA21: 0
A22: Investimentos | B22: MM R$ | D22: {=SUMPRODUCT(O22:AW22,(1/$O$2:$AW$2),$O$28:$AW$28)} -> #REF! | E22: MM R$@2021 | O22: =#REF! -> #REF! | P22: =#REF! -> #REF! | Q22: =#REF! -> #REF! | R22: =#REF! -> #REF! | S22: =#REF! -> #REF! | T22: =#REF! -> #REF! | U22: =#REF! -> #REF! | V22: =#REF! -> #REF! | ... BA22: =#REF! -> #REF!
A23: Sobrecustos operacionais | B23: MM R$ | D23: {=SUMPRODUCT(O23:AW23,(1/$O$2:$AW$2),$O$28:$AW$28)} -> #REF! | E23: MM R$@2021 | G23: 0.2 | H23: Sobrecusto/Desconto opção PSC | O23: =O20*$G23 -> #REF! | P23: =P20*$G23 -> #REF! | Q23: =Q20*$G23 -> #REF! | R23: =R20*$G23 -> #REF! | S23: =S20*$G23 -> #REF! | T23: =T20*$G23 -> #REF! | U23: =U20*$G23 -> #REF! | V23: =V20*$G23 -> #REF! | ... BA23: =BA20*$G23 -> #REF!
A24: Sobrecustos de obras | B24: MM R$ | D24: {=SUMPRODUCT(O24:AW24,(1/$O$2:$AW$2),$O$28:$AW$28)} -> #REF! | E24: MM R$@2021 | G24: 0.2 | H24: Sobrecusto/Desconto opção PSC | O24: =O22*$G24 -> #REF! | P24: =P22*$G24 -> #REF! | Q24: =Q22*$G24 -> #REF! | R24: =R22*$G24 -> #REF! | S24: =S22*$G24 -> #REF! | T24: =T22*$G24 -> #REF! | U24: =U22*$G24 -> #REF! | V24: =V22*$G24 -> #REF! | ... BA24: =BA22*$G24 -> #REF!
A25: Custos com licitação de obras | B25: MM R$ | D25: {=SUMPRODUCT(O25:AW25,(1/$O$2:$AW$2),$O$28:$AW$28)} -> #REF! | E25: MM R$@2021 | G25: 0.0419 | O25: =$G25*(O22+O24) -> #REF! | P25: =$G25*(P22+P24) -> #REF! | Q25: =$G25*(Q22+Q24) -> #REF! | R25: =$G25*(R22+R24) -> #REF! | S25: =$G25*(S22+S24) -> #REF! | T25: =$G25*(T22+T24) -> #REF! | U25: =$G25*(U22+U24) -> #REF! | V25: =$G25*(V22+V24) -> #REF! | ... BA25: =$G25*(BA22+BA24) -> #REF!
A26: Impostos | B26: MM R$ | D26: {=SUMPRODUCT(O26:AW26,(1/$O$2:$AW$2),$O$28:$AW$28)} -> #REF! | E26: MM R$@2021 | O26: 0 | P26: 0 | Q26: 0 | R26: 0 | S26: 0 | T26: 0 | U26: 0 | V26: 0 | W26: 0 | X26: 0 | Y26: 0 | Z26: 0 | AA26: 0 | AB26: 0 | AC26: 0 | AD26: 0 | AE26: 0 | AF26: 0 | AG26: 0 | AH26: 0 | AI26: 0 | AJ26: 0 | AK26: 0 | AL26: 0 | AM26: 0 | AN26: 0 | AO26: 0 | AP26: 0 | AQ26: 0 | AR26: 0 | AS26: 0 | AT26: 0 | AU26: 0 | AV26: 0 | AW26: 0 | AX26: 0 | AY26: 0 | AZ26: 0 | BA26: 0
D27: =SUM(D18:D26) -> #REF!
A28: Fator de desconto | D28: =D14-D27 -> #REF! | O28: =1/((1+$D17)^O29) -> #REF! | P28: =1/((1+$D17)^P29) -> #REF! | Q28: =1/((1+$D17)^Q29) -> #REF! | R28: =1/((1+$D17)^R29) -> #REF! | S28: =1/((1+$D17)^S29) -> #REF! | T28: =1/((1+$D17)^T29) -> #REF! | U28: =1/((1+$D17)^U29) -> #REF! | V28: =1/((1+$D17)^V29) -> #REF! | ... BA28: =1/((1+$D17)^BA29) -> #REF!
O29: =#REF! -> #REF! | P29: =#REF! -> #REF! | Q29: =#REF! -> #REF! | R29: =#REF! -> #REF! | S29: =#REF! -> #REF! | T29: =#REF! -> #REF! | U29: =#REF! -> #REF! | V29: =#REF! -> #REF! | ... BA29: =#REF! -> #REF!
A31: CONTRAPRESTAÇÃO | B31: K R$
O32: =O33/O2 -> 6711208.8 | P32: =P33/P2 -> 6567403.3 | Q32: =Q33/Q2 -> 6425279.1 | R32: =R33/R2 -> 6286836.9 | S32: =S33/S2 -> 6151954.4 | T32: =T33/T2 -> 6018678.5 | U32: =U33/U2 -> 5888839 | V32: =V33/V2 -> 5762322.9 | ... AW32: =AW33/AW2 -> 3183751.1
A33: Contraprestação | D33: =1/1000 -> 0.001 | E33: K R$/MM R$ | M33: 30 | O33: ='Receita CP'!O7 -> 7190413.3 | P33: ='Receita CP'!P7 -> 7247429.9 | Q33: ='Receita CP'!Q7 -> 7303306.9 | R33: ='Receita CP'!R7 -> 7360324.7 | S33: ='Receita CP'!S7 -> 7418483.2 | T33: ='Receita CP'!T7 -> 7475502.2 | U33: ='Receita CP'!U7 -> 7533662.1 | V33: ='Receita CP'!V7 -> 7592962.7 | ... AW33: ='Receita CP'!AW7 -> 9318754
A35: RCL | K35: =SUM(K36:K36) -> 617.28054 | L35: =SUM(L36:L36) -> 712.44526 | M35: =SUM(M36:M36) -> 797.27606 | N35: =SUM(N36:N36) -> 859.92069 | O35: =SUM(O36:O36) -> 899.2207 | P35: =SUM(P36:P36) -> 943.85064 | Q35: =SUM(Q36:Q36) -> 991.51226 | R35: =SUM(R36:R36) -> 1041.3356 | ... AW35: =SUM(AW36:AW36) -> 4760.5982
B36: MM R$ | C36: finbraRREO | K36: 617.28054 | L36: 712.44526 | M36: 797.27606 | N36: =M36*(1+N$37)*(N$2/M$2) -> 859.92069 | O36: =N36*(1+O$37)*(O$2/N$2) -> 899.2207 | P36: =O36*(1+P$37)*(P$2/O$2) -> 943.85064 | Q36: =P36*(1+Q$37)*(Q$2/P$2) -> 991.51226 | R36: =Q36*(1+R$37)*(R$2/Q$2) -> 1041.3356 | S36: =R36*(1+S$37)*(S$2/R$2) -> 1093.6625 | T36: =S36*(1+T$37)*(T$2/S$2) -> 1148.6188 | U36: =T36*(1+U$37)*(U$2/T$2) -> 1206.3366 | ... AW36: =AV36*(1+AW$37)*(AW$2/AV$2) -> 4760.5982
A37: Txa. PIB real | B37: %a.a. | M37: =MacroEco!X34 -> 0.046194216 | N37: =MacroEco!Y34 -> 0.0278 | O37: =MacroEco!Z34 -> 0.01034 | P37: =MacroEco!AA34 -> 0.01906 | Q37: =MacroEco!AB34 -> 0.0199 | R37: =MacroEco!AC34 -> 0.01966 | S37: =MacroEco!AD34 -> 0.01966 | T37: =MacroEco!AE34 -> 0.01966 | ... BA37: =MacroEco!BL34 -> 0.01966
A39: %RCL | D39: =MAX(D40:D40) -> 7996.272 | F39: OBS> | G39: comprometimento da RCL reduz ao longo do tempo pq a diluição ocorre com o crescimento do PIB per capita | O39: =O33/O35 -> 7996.272 | P39: =P33/P35 -> 7678.5771 | Q39: =Q33/Q35 -> 7365.8261 | R39: =R33/R35 -> 7068.1584 | S39: =S33/S35 -> 6783.1561 | T39: =T33/T35 -> 6508.2535 | U39: =U33/U35 -> 6245.0744 | V39: =V33/V35 -> 5993.0809 | ... AW39: =AW33/AW35 -> 1957.4754
B40: % | D40: =MAX(O40:AW40) -> 7996.272 | E40: =IF(D40<5%,"ok","ERRO") -> ERRO | O40: =O33/O36 -> 7996.272 | P40: =P33/P36 -> 7678.5771 | Q40: =Q33/Q36 -> 7365.8261 | R40: =R33/R36 -> 7068.1584 | S40: =S33/S36 -> 6783.1561 | T40: =T33/T36 -> 6508.2535 | U40: =U33/U36 -> 6245.0744 | V40: =V33/V36 -> 5993.0809 | ... AW40: =AW33/AW36 -> 1957.4754
A42: Cenários com cobrança de taxa
A43: População atendida | B43: hab
A44: Habitantes por domicílio | D44: 2.4 | E44: hab/domicílio | O44: =OPERACIONAL!#REF! -> #REF! | P44: =OPERACIONAL!#REF! -> #REF! | Q44: =OPERACIONAL!#REF! -> #REF! | R44: =OPERACIONAL!K4 -> 254313 | S44: =OPERACIONAL!L4 -> 256230 | T44: =OPERACIONAL!M4 -> 258242 | U44: =OPERACIONAL!N4 -> 260277 | V44: =OPERACIONAL!O4 -> 262335 | W44: =OPERACIONAL!P4 -> 264416 | X44: =OPERACIONAL!Q4 -> 266189 | Y44: =OPERACIONAL!R4 -> 268315 | ... AW44: =OPERACIONAL!AP4 -> 321923
A45: Número de domicílios | O45: =O44/$D$44 -> #REF! | P45: =P44/$D$44 -> #REF! | Q45: =Q44/$D$44 -> #REF! | R45: =R44/$D$44 -> 105963.75 | S45: =S44/$D$44 -> 106762.5 | T45: =T44/$D$44 -> 107600.83 | U45: =U44/$D$44 -> 108448.75 | V45: =V44/$D$44 -> 109306.25 | ... AW45: =AW44/$D$44 -> 134134.58
A47: Cenário 1 | D47: =1/1000000 -> 1e-06 | E47: R$/MM R$
A48: Contraprestação real | B48: MM R$ @fev/23 | O48: =O33/O2 -> 6711208.8 | P48: =P33/P2 -> 6567403.3 | Q48: =Q33/Q2 -> 6425279.1 | R48: =R33/R2 -> 6286836.9 | S48: =S33/S2 -> 6151954.4 | T48: =T33/T2 -> 6018678.5 | U48: =U33/U2 -> 5888839 | V48: =V33/V2 -> 5762322.9 | ... AW48: =AW33/AW2 -> 3183751.1
A49: Taxa/Tarifa | B49: R$/dom/mês | D49: 14.8 | E49: R$/dom/mês | O49: =O48*1000000/O45/12 -> #REF! | P49: =P48*1000000/P45/12 -> #REF! | Q49: =Q48*1000000/Q45/12 -> #REF! | R49: =R48*1000000/R45/12 -> 4944172.6 | S49: =S48*1000000/S45/12 -> 4801900.2 | T49: =T48*1000000/T45/12 -> 4661270.1 | U49: =U48*1000000/U45/12 -> 4525055.3 | V49: =V48*1000000/V45/12 -> 4393102.6 | ... AW49: =AW48*1000000/AW45/12 -> 1977958.1
A50: Valor arrecadado | B50: MM R$ | O50: =O$45*$D49*12*$D47*O2 -> #REF! | P50: =P$45*$D49*12*$D47*P2 -> #REF! | Q50: =Q$45*$D49*12*$D47*Q2 -> #REF! | R50: =R$45*$D49*12*$D47*R2 -> 22.032565 | S50: =S$45*$D49*12*$D47*S2 -> 22.864605 | T50: =T$45*$D49*12*$D47*T2 -> 23.735469 | U50: =U$45*$D49*12*$D47*U2 -> 24.640185 | V50: =V$45*$D49*12*$D47*V2 -> 25.580065 | ... AW50: =AW$45*$D49*12*$D47*AW2 -> 69.727239
A52: Composição RCL
B54: 2020 | C54: % | D54: 2021 | E54: % | F54: 2022 | G54: %
A55: RCL | B55: =SUM(B56:B63) -> 718.68809 | C55: =B55/B$55 -> 1 | D55: =SUM(D56:D63) -> 753.66088 | E55: =D55/D$55 -> 1 | F55: =SUM(F56:F63) -> 797.27606 | G55: =F55/F$55 -> 1
A56: Impostos, Taxas e Contribuições de Melhoria | B56: 152.41401 | C56: =B56/B$55 -> 0.21207254 | D56: 175.75197 | E56: =D56/D$55 -> 0.23319768 | F56: 192.11746 | G56: =F56/F$55 -> 0.2409673
A57: Contribuições | B57: 11.188376 | C57: =B57/B$55 -> 0.015567777 | D57: 11.296536 | E57: =D57/D$55 -> 0.014988884 | F57: 12.291099 | G57: =F57/F$55 -> 0.015416365
A58: Receita Patrimonial | B58: 0.5292577 | C58: =B58/B$55 -> 0.00073642198 | D58: 14.469983 | E58: =D58/D$55 -> 0.019199595 | F58: 6.2519751 | G58: =F58/F$55 -> 0.0078416692
A59: Receita Agropecuária | B59: 0 | C59: =B59/B$55 -> 0 | D59: 0 | E59: =D59/D$55 -> 0 | F59: 0 | G59: =F59/F$55 -> 0
A60: Receita Industrial | B60: 0 | C60: =B60/B$55 -> 0 | D60: 0 | E60: =D60/D$55 -> 0 | F60: 0 | G60: =F60/F$55 -> 0
A61: Receita de Serviços | B61: 84.613004 | C61: =B61/B$55 -> 0.11773258 | D61: 78.98327 | E61: =D61/D$55 -> 0.10479948 | F61: 82.408541 | G61: =F61/F$55 -> 0.10336262
A62: Transferências Correntes | B62: 464.16052 | C62: =B62/B$55 -> 0.64584419 | D62: 468.41375 | E62: =D62/D$55 -> 0.62151792 | F62: 493.84319 | G62: =F62/F$55 -> 0.61941304
A63: Outras Receitas Correntes | B63: 5.7829221 | C63: =B63/B$55 -> 0.0080464977 | D63: 4.7453771 | E63: =D63/D$55 -> 0.0062964355 | F63: 10.363795 | G63: =F63/F$55 -> 0.012999004
A66: Projeção comprometimento RCL / Cenários cobrança taxa do lixo
C68: =O1 -> 2025 | D68: =P1 -> 2026 | E68: =Q1 -> 2027 | F68: =R1 -> 2028 | G68: =S1 -> 2029 | H68: =T1 -> 2030 | I68: =U1 -> 2031 | J68: =V1 -> 2032 | ... M68: =Y1 -> 2035
A69: Cenário base: sem cobrança de taxa | B69: RCL – sem cobrança de taxa | C69: =O35 -> 899.2207 | D69: =P35 -> 943.85064 | E69: =Q35 -> 991.51226 | F69: =R35 -> 1041.3356 | G69: =S35 -> 1093.6625 | H69: =T35 -> 1148.6188 | I69: =U35 -> 1206.3366 | J69: =V35 -> 1266.9548 | ... M69: =Y35 -> 1467.7056
B70: Contraprestação | C70: =O$33 -> 7190413.3 | D70: =P$33 -> 7247429.9 | E70: =Q$33 -> 7303306.9 | F70: =R$33 -> 7360324.7 | G70: =S$33 -> 7418483.2 | H70: =T$33 -> 7475502.2 | I70: =U$33 -> 7533662.1 | J70: =V$33 -> 7592962.7 | ... M70: =Y$33 -> 7768589.2
B71: Comprometimento de RCL (%) | C71: =C70/C69 -> 7996.272 | D71: =D70/D69 -> 7678.5771 | E71: =E70/E69 -> 7365.8261 | F71: =F70/F69 -> 7068.1584 | G71: =G70/G69 -> 6783.1561 | H71: =H70/H69 -> 6508.2535 | I71: =I70/I69 -> 6245.0744 | J71: =J70/J69 -> 5993.0809 | ... M71: =M70/M69 -> 5293.016
A72: =CONCATENATE("Cenário 1: taxa de R$ ",D49," por domicílio / mês") -> Cenário 1: taxa de R$ 14,8 por domicílio / mês | B72: RCL – Com cobrança de taxa de R$ 14,80 por domicílio / mês | C72: =C$69+O50 -> #REF! | D72: =D$69+P50 -> #REF! | E72: =E$69+Q50 -> #REF! | F72: =F$69+R50 -> 1063.3681 | G72: =G$69+S50 -> 1116.5271 | H72: =H$69+T50 -> 1172.3542 | I72: =I$69+U50 -> 1230.9768 | J72: =J$69+V50 -> 1292.5349 | ... M72: =M$69+Y50 -> 1496.2948
B73: Contraprestação | C73: =O$33 -> 7190413.3 | D73: =P$33 -> 7247429.9 | E73: =Q$33 -> 7303306.9 | F73: =R$33 -> 7360324.7 | G73: =S$33 -> 7418483.2 | H73: =T$33 -> 7475502.2 | I73: =U$33 -> 7533662.1 | J73: =V$33 -> 7592962.7 | ... M73: =Y$33 -> 7768589.2
B74: Comprometimento de RCL (%) | C74: =C73/C72 -> #REF! | D74: =D73/D72 -> #REF! | E74: =E73/E72 -> #REF! | F74: =F73/F72 -> 6921.709 | G74: =G73/G72 -> 6644.2484 | H74: =H73/H72 -> 6376.4875 | I74: =I73/I72 -> 6120.0682 | J74: =J73/J72 -> 5874.4741 | ... M74: =M73/M72 -> 5191.8841
L79: Resíduos | M79: Poda, capina e varrição | N79: Coleta | O79: Tratamento e destinação final
L80: RSU
L81: RCC
L82: RSS
L83: Limpeza Urbana

Sheet LOTE 1
A1: Controle
BM3: Com inflação | BP3: Alternativa 1
A4: Modelo Real ou nominal | B4: Com inflação | D4: WACC | E4: 0.1 | BM4: Sem inflação
A5: VPL | B5: ='DRE_URE MARÍLIA-BIO'!I80 -> 93296696 | C5: MM R$ | D5: TIR projeto | E5: ='DRE_URE MARÍLIA-BIO+GAS'!I79 -> 0.11637598
D6: Payback | E6: ='DRE_URE MARÍLIA-BIO+GAS'!I81 -> 6.7 | G6: COM LPU | H6: SEM LPU
A7: Contraprestação fixa | B7: 2.8540916 | C7: MM R$/ano | G7: 2.8540916 | H7: 2.8540916
A8: Saldo final ativo financeiro | B8: =#REF! -> #REF! | G8: =#REF! -> #REF! | H8: =#REF! -> #REF!
A9: Contraprestação variável - Parcela B Volume | B9: 110 | C9: R$/ton | G9: 110 | H9: 110
A10: Contraprestação variável - Parcela C População | B10: 4.7269692 | C10: R$/hab/mês | G10: 4.7269692 | H10: 2.9928665
A12: Sensibilidade preço de recicláveis | B12: 0 | G12: 0 | H12: 0
A13: Sensibilidade crédito recicláveis | B13: 0 | G13: 0 | H13: 0
A14: Outorga variável | B14: 0 | G14: 0 | H14: 0
A15: Anos de carência de outorga variável | B15: 0 | G15: 0 | H15: 0
A16: Primeiro ano de pagamento integral | B16: 1 | G16: 1 | H16: 1
A18: Fator Capex | B18: 1 | G18: 1 | H18: 1
A19: Fator Opex | B19: 1 | G19: 1 | H19: 1
A21: Capital social mínimo 1o ano | B21: 10 | C21: MM R$ | G21: 10 | H21: 10
A23: Considera limpeza urbana? | B23: 1 | C23: [1=sim;0=não] | G23: 1 | H23: 0
A25: Alavancagem alvo | B25: 1 | G25: 1 | H25: 1
A27: Síntese
A28: Componentes de valor / Waterfall VPL
I29: =YEAR(Premissas!$D$13) -> 2025 | J29: =I29+1 -> 2026 | K29: =J29+1 -> 2027 | L29: =K29+1 -> 2028 | M29: =L29+1 -> 2029 | N29: =M29+1 -> 2030 | O29: =N29+1 -> 2031 | P29: =O29+1 -> 2032 | Q29: =P29+1 -> 2033 | ... AQ29: =AP29+1 -> 2059
A30: Índice de inflação brasileira (IPCA) | I30: =MacroEco!AA$8 -> 1.0714036 | J30: =MacroEco!AB$8 -> 1.1035457 | K30: =MacroEco!AC$8 -> 1.1366521 | L30: =MacroEco!AD$8 -> 1.1707517 | M30: =MacroEco!AE$8 -> 1.2058742 | N30: =MacroEco!AF$8 -> 1.2420504 | O30: =MacroEco!AG$8 -> 1.2793119 | P30: =MacroEco!AH$8 -> 1.3176913 | ... AQ30: =MacroEco!BI$8 -> 2.9269732
A32: Em termos nominais
A33: Receita Bruta - URE MARÍLIA - BIO | D33: =SUM(I33:AR33) -> 6.4772826e+08 | I33: =SUM(I34:I38) -> 480090.43 | J33: =SUM(J34:J38) -> 19031970 | K33: =SUM(K34:K38) -> 19032156 | L33: =SUM(L34:L38) -> 19032349 | M33: =SUM(M34:M38) -> 19032550 | N33: =SUM(N34:N38) -> 19032757 | O33: =SUM(O34:O38) -> 19032973 | P33: =SUM(P34:P38) -> 19033197 | ... AQ33: =SUM(AQ34:AQ38) -> 19043151
A34: (+) Receita Contraprestação fixa | D34: =SUM(I34:AR34) -> 229132800 | I34: ='DRE_URE MARÍLIA-BIO+GAS'!E8 -> 0 | J34: ='DRE_URE MARÍLIA-BIO+GAS'!F8 -> 6739200 | K34: ='DRE_URE MARÍLIA-BIO+GAS'!G8 -> 6739200 | L34: ='DRE_URE MARÍLIA-BIO+GAS'!H8 -> 6739200 | M34: ='DRE_URE MARÍLIA-BIO+GAS'!I8 -> 6739200 | N34: ='DRE_URE MARÍLIA-BIO+GAS'!J8 -> 6739200 | O34: ='DRE_URE MARÍLIA-BIO+GAS'!K8 -> 6739200 | P34: ='DRE_URE MARÍLIA-BIO+GAS'!L8 -> 6739200 | ... AP34: ='DRE_URE MARÍLIA-BIO+GAS'!AL8 -> 6739200 | AQ34: =AP34 -> 6739200
A35: (+) Receita Reciclável | D35: =SUM(I35:AR35) -> 332157 | I35: ='Receita Acessórias'!O18 -> 4710.4288 | J35: ='Receita Acessórias'!P18 -> 4890.2048 | K35: ='Receita Acessórias'!Q18 -> 5075.7357 | L35: ='Receita Acessórias'!R18 -> 5268.8133 | M35: ='Receita Acessórias'!S18 -> 5469.748 | N35: ='Receita Acessórias'!T18 -> 5677.1311 | O35: ='Receita Acessórias'!U18 -> 5892.9261 | P35: ='Receita Acessórias'!V18 -> 6117.478 | ... AP35: ='Receita Acessórias'!AV18 -> 16071.17 | AQ35: =AP35 -> 16071.17
A36: (+) Receita Biometano | D36: =SUM(I36:AR36) -> 257040000 | I36: ='DRE_URE MARÍLIA-BIO+GAS'!E5 -> 0 | J36: ='DRE_URE MARÍLIA-BIO+GAS'!G5 -> 7560000 | K36: ='DRE_URE MARÍLIA-BIO+GAS'!H5 -> 7560000 | L36: ='DRE_URE MARÍLIA-BIO+GAS'!I5 -> 7560000 | M36: ='DRE_URE MARÍLIA-BIO+GAS'!J5 -> 7560000 | N36: ='DRE_URE MARÍLIA-BIO+GAS'!K5 -> 7560000 | O36: ='DRE_URE MARÍLIA-BIO+GAS'!L5 -> 7560000 | P36: ='DRE_URE MARÍLIA-BIO+GAS'!M5 -> 7560000 | Q36: ='DRE_URE MARÍLIA-BIO+GAS'!N5 -> 7560000 | ... AP36: ='DRE_URE MARÍLIA-BIO+GAS'!AM5 -> 7560000 | AQ36: =AP36 -> 7560000
A37: (+) Receita CO2 | D37: =SUM(I37:AR37) -> 144585000 | I37: ='DRE_URE MARÍLIA-BIO+GAS'!E7 -> 0 | J37: ='DRE_URE MARÍLIA-BIO+GAS'!G7 -> 4252500 | K37: ='DRE_URE MARÍLIA-BIO+GAS'!H7 -> 4252500 | L37: ='DRE_URE MARÍLIA-BIO+GAS'!I7 -> 4252500 | M37: ='DRE_URE MARÍLIA-BIO+GAS'!J7 -> 4252500 | N37: ='DRE_URE MARÍLIA-BIO+GAS'!K7 -> 4252500 | O37: ='DRE_URE MARÍLIA-BIO+GAS'!L7 -> 4252500 | P37: ='DRE_URE MARÍLIA-BIO+GAS'!M7 -> 4252500 | Q37: ='DRE_URE MARÍLIA-BIO+GAS'!N7 -> 4252500 | ... AP37: ='DRE_URE MARÍLIA-BIO+GAS'!AM7 -> 4252500 | AQ37: =AP37 -> 4252500
A38: (+) CBIOS | D38: =SUM(I38:AR38) -> 16638300 | I38: ='DRE_URE MARÍLIA-BIO+GAS'!F10 -> 475380 | J38: ='DRE_URE MARÍLIA-BIO+GAS'!G10 -> 475380 | K38: ='DRE_URE MARÍLIA-BIO+GAS'!H10 -> 475380 | L38: ='DRE_URE MARÍLIA-BIO+GAS'!I10 -> 475380 | M38: ='DRE_URE MARÍLIA-BIO+GAS'!J10 -> 475380 | N38: ='DRE_URE MARÍLIA-BIO+GAS'!K10 -> 475380 | O38: ='DRE_URE MARÍLIA-BIO+GAS'!L10 -> 475380 | P38: ='DRE_URE MARÍLIA-BIO+GAS'!M10 -> 475380 | ... AP38: ='DRE_URE MARÍLIA-BIO+GAS'!AM10 -> 475380 | AQ38: =AP38 -> 475380
A39: Impostos | D39: =SUM(I39:AR39) -> -1.8693681e+08 | I39: =SUM(I40:I41) -> 0 | J39: =SUM(J40:J41) -> -4517822.2 | K39: =SUM(K40:K41) -> -5527848.2 | L39: =SUM(L40:L41) -> -5527848.2 | M39: =SUM(M40:M41) -> -5527848.2 | N39: =SUM(N40:N41) -> -5527848.2 | O39: =SUM(O40:O41) -> -5527848.2 | P39: =SUM(P40:P41) -> -5527848.2 | ... AQ39: =SUM(AQ40:AQ41) -> -5527848.2
A40: (-) Impostos Serviço | D40: =SUM(I40:AR40) -> -77905152 | I40: ='DRE_URE MARÍLIA-BIO+GAS'!E41 -> 0 | J40: ='DRE_URE MARÍLIA-BIO+GAS'!F41 -> -2291328 | K40: ='DRE_URE MARÍLIA-BIO+GAS'!G41 -> -2291328 | L40: ='DRE_URE MARÍLIA-BIO+GAS'!H41 -> -2291328 | M40: ='DRE_URE MARÍLIA-BIO+GAS'!I41 -> -2291328 | N40: ='DRE_URE MARÍLIA-BIO+GAS'!J41 -> -2291328 | O40: ='DRE_URE MARÍLIA-BIO+GAS'!K41 -> -2291328 | P40: ='DRE_URE MARÍLIA-BIO+GAS'!L41 -> -2291328 | ... AQ40: ='DRE_URE MARÍLIA-BIO+GAS'!AM41 -> -2291328
A41: (-) Impostos Produto | D41: =SUM(I41:AR41) -> -1.0903166e+08 | I41: ='DRE_URE MARÍLIA-BIO+GAS'!E12 -> 0 | J41: ='DRE_URE MARÍLIA-BIO+GAS'!F12 -> -2226494.2 | K41: ='DRE_URE MARÍLIA-BIO+GAS'!G12 -> -3236520.2 | L41: ='DRE_URE MARÍLIA-BIO+GAS'!H12 -> -3236520.2 | M41: ='DRE_URE MARÍLIA-BIO+GAS'!I12 -> -3236520.2 | N41: ='DRE_URE MARÍLIA-BIO+GAS'!J12 -> -3236520.2 | O41: ='DRE_URE MARÍLIA-BIO+GAS'!K12 -> -3236520.2 | P41: ='DRE_URE MARÍLIA-BIO+GAS'!L12 -> -3236520.2 | ... AQ41: ='DRE_URE MARÍLIA-BIO+GAS'!AM12 -> -3236520.2
A42: OPEX | D42: =SUM(I42:AR42) -> -1.7836593e+08 | I42: =SUM(I43:I43) -> -954720 | J42: =SUM(J43:J43) -> -5059006.2 | K42: =SUM(K43:K43) -> -5222794.2 | L42: =SUM(L43:L43) -> -5222794.2 | M42: =SUM(M43:M43) -> -5222794.2 | N42: =SUM(N43:N43) -> -5222794.2 | O42: =SUM(O43:O43) -> -5222794.2 | P42: =SUM(P43:P43) -> -5222794.2 | ... AQ42: =SUM(AQ43:AQ43) -> -5222794.2
A43: (-) Custos com operacionais | D43: =SUM(J43:AR43) -> -1.7741121e+08 | I43: =Opex!Z57*-1 -> -954720 | J43: =Opex!AA57*-1 -> -5059006.2 | K43: =Opex!AB57*-1 -> -5222794.2 | L43: =Opex!AC57*-1 -> -5222794.2 | M43: =Opex!AD57*-1 -> -5222794.2 | N43: =Opex!AE57*-1 -> -5222794.2 | O43: =Opex!AF57*-1 -> -5222794.2 | P43: =Opex!AG57*-1 -> -5222794.2 | ... AP43: =Opex!BG57*-1 -> -5222794.2 | AQ43: =AP43 -> -5222794.2
A44: Custos de construção | D44: =SUM(I44:AR44) -> -40600000 | I44: =I45 -> 0 | J44: =J45 -> -4060000 | K44: =K45 -> -4060000 | L44: =L45 -> -4060000 | M44: =M45 -> -4060000 | N44: =N45 -> -4060000 | O44: =O45 -> -4060000 | P44: =P45 -> -4060000 | ... AQ44: =AQ45 -> 0
A45: (-) Depreciação/Amortização | D45: =SUM(I45:AR45) -> -40600000 | I45: ='DRE_URE MARÍLIA-BIO+GAS'!E36 -> 0 | J45: ='DRE_URE MARÍLIA-BIO+GAS'!F36 -> -4060000 | K45: ='DRE_URE MARÍLIA-BIO+GAS'!G36 -> -4060000 | L45: ='DRE_URE MARÍLIA-BIO+GAS'!H36 -> -4060000 | M45: ='DRE_URE MARÍLIA-BIO+GAS'!I36 -> -4060000 | N45: ='DRE_URE MARÍLIA-BIO+GAS'!J36 -> -4060000 | O45: ='DRE_URE MARÍLIA-BIO+GAS'!K36 -> -4060000 | P45: ='DRE_URE MARÍLIA-BIO+GAS'!L36 -> -4060000 | ... AQ45: ='DRE_URE MARÍLIA-BIO+GAS'!AM36 -> 0
A46: (=) EBIT | D46: =SUM(I46:AR46) -> 4.2019144e+08 | I46: =SUM(I47:I49) -> 480090.43 | J46: =SUM(J47:J49) -> 10454148 | K46: =SUM(K47:K49) -> 9444307.5 | L46: =SUM(L47:L49) -> 9444500.6 | M46: =SUM(M47:M49) -> 9444701.5 | N46: =SUM(N47:N49) -> 9444908.9 | O46: =SUM(O47:O49) -> 9445124.7 | P46: =SUM(P47:P49) -> 9445349.2 | ... AQ46: =SUM(AQ47:AQ49) -> 13515303
A47: (-) Impostos sobre EBIT | D47: =SUM(I47:AR47) -> -1.8693681e+08 | I47: =I39 -> 0 | J47: =J39 -> -4517822.2 | K47: =K39 -> -5527848.2 | L47: =L39 -> -5527848.2 | M47: =M39 -> -5527848.2 | N47: =N39 -> -5527848.2 | O47: =O39 -> -5527848.2 | P47: =P39 -> -5527848.2 | ... AQ47: =AQ39 -> -5527848.2
A48: (+) Receita Bruta | D48: =SUM(I48:AR48) -> 6.4772826e+08 | I48: =I33 -> 480090.43 | J48: =J33 -> 19031970 | K48: =K33 -> 19032156 | L48: =L33 -> 19032349 | M48: =M33 -> 19032550 | N48: =N33 -> 19032757 | O48: =O33 -> 19032973 | P48: =P33 -> 19033197 | ... AQ48: =AQ33 -> 19043151
A49: (-) Depreciação/Amortização | D49: =SUM(I49:AR49) -> -40600000 | I49: =I44 -> 0 | J49: =J44 -> -4060000 | K49: =K44 -> -4060000 | L49: =L44 -> -4060000 | M49: =M44 -> -4060000 | N49: =N44 -> -4060000 | O49: =O44 -> -4060000 | P49: =P44 -> -4060000 | ... AQ49: =AQ44 -> 0
A50: CAPEX | D50: =SUM(I50:AR50) -> -49820268 | I50: =I51 -> -49820268 | J50: =J51 -> 0 | K50: =K51 -> 0 | L50: =L51 -> 0 | M50: =M51 -> 0 | N50: =N51 -> 0 | O50: =O51 -> 0 | P50: =P51 -> 0 | ... AQ50: =AQ51 -> 0
A51: (-) Licenciamento e Equipamentos | D51: =SUM(I51:AR51) -> -49820268 | I51: =Capex!O46*-1 -> -49820268 | J51: =Capex!P46*-1 -> 0 | K51: =Capex!Q46*-1 -> 0 | L51: =Capex!R46*-1 -> 0 | M51: =Capex!S46*-1 -> 0 | N51: =Capex!T46*-1 -> 0 | O51: =Capex!U46*-1 -> 0 | P51: =Capex!V46*-1 -> 0 | ... AQ51: =Capex!AW46*-1 -> 0
A53: Fluxo de caixa livre para firma | D53: =SUM(I53:AR53) -> 5.1463748e+09 | I53: =I46+I50 -> -49340177 | J53: =J46+J50+I53 -> -38886030 | K53: =K46+K50+J53 -> -29441722 | L53: =L46+L50+K53 -> -19997221 | M53: =M46+M50+L53 -> -10552520 | N53: =N46+N50+M53 -> -1107611.1 | O53: =O46+O50+N53 -> 8337513.6 | P53: =P46+P50+O53 -> 17782863 | Q53: =Q46+Q50+P53 -> 27228445 | ... AQ53: =AQ46+AQ50+AP53 -> 3.7037117e+08
A56: Em termos reais
A57: =A33 -> Receita Bruta - URE MARÍLIA - BIO | D57: =SUM(I57:AR57) -> 1.213366e+09 | I57: =SUM(I58:I62) -> 514370.62 | J57: =SUM(J58:J62) -> 21002649 | K57: =SUM(K58:K62) -> 21632940 | L57: =SUM(L58:L62) -> 22282154 | M57: =SUM(M58:M62) -> 22950861 | N57: =SUM(N58:N62) -> 23639644 | O57: =SUM(O58:O62) -> 24349110 | P57: =SUM(P58:P62) -> 25079879 | ... AQ57: =SUM(AQ58:AQ62) -> 55738793
A58: (+) Receita Contraprestação fixa | D58: =SUM(I58:AR58) -> 4.2934021e+08 | I58: =I34*I30 -> 0 | J58: =J34*J30 -> 7437015.3 | K58: =K34*K30 -> 7660125.8 | L58: =L34*L30 -> 7889929.5 | M58: =M34*M30 -> 8126627.4 | N58: =N34*N30 -> 8370426.3 | O58: =O34*O30 -> 8621539 | P58: =P34*P30 -> 8880185.2 | ... AQ58: =AQ34*AQ30 -> 19725458
A59: (+) Receita Reciclável | D59: =SUM(I59:AR59) -> 681527.98 | I59: =I35*I30 -> 5046.7704 | J59: =J35*J30 -> 5396.5646 | K59: =K35*K30 -> 5769.3456 | L59: =L35*L30 -> 6168.4719 | M59: =M35*M30 -> 6595.828 | N59: =N35*N30 -> 7051.2831 | O59: =O35*O30 -> 7538.8908 | P59: =P35*P30 -> 8060.9475 | ... AQ59: =AQ35*AQ30 -> 47039.885
A60: (+) Receita Biometano | D60: =SUM(I60:AR60) -> 4.8163164e+08 | I60: =I36*I30 -> 0 | J60: =J36*J30 -> 8342805.6 | K60: =K36*K30 -> 8593089.8 | L60: =L36*L30 -> 8850882.5 | M60: =M36*M30 -> 9116409 | N60: =N36*N30 -> 9389901.2 | O60: =O36*O30 -> 9671598.3 | P60: =P36*P30 -> 9961746.2 | ... AQ60: =AQ36*AQ30 -> 22127917
A61: (+) Receita CO2 | D61: =SUM(I61:AR61) -> 2.709178e+08 | I61: =I37*I30 -> 0 | J61: =J37*J30 -> 4692828.2 | K61: =K37*K30 -> 4833613 | L61: =L37*L30 -> 4978621.4 | M61: =M37*M30 -> 5127980 | N61: =N37*N30 -> 5281819.5 | O61: =O37*O30 -> 5440274 | P61: =P37*P30 -> 5603482.3 | ... AQ61: =AQ37*AQ30 -> 12446954
A62: (+) CBIOS | D62: =SUM(I62:AR62) -> 30794780 | I62: =I38*I30 -> 509323.85 | J62: =J38*J30 -> 524603.56 | K62: =K38*K30 -> 540341.67 | L62: =L38*L30 -> 556551.92 | M62: =M38*M30 -> 573248.48 | N62: =N38*N30 -> 590445.93 | O62: =O38*O30 -> 608159.31 | P62: =P38*P30 -> 626404.09 | ... AQ62: =AQ38*AQ30 -> 1391424.5
A63: Impostos | D63: =SUM(I63:AR63) -> -3.5105293e+08 | I63: =SUM(I64:I65) -> 0 | J63: =SUM(J64:J65) -> -4985623.4 | K63: =SUM(K64:K65) -> -6283240.3 | L63: =SUM(L64:L65) -> -6471737.5 | M63: =SUM(M64:M65) -> -6665889.6 | N63: =SUM(N64:N65) -> -6865866.3 | O63: =SUM(O64:O65) -> -7071842.3 | P63: =SUM(P64:P65) -> -7283997.5 | ... AQ63: =SUM(AQ64:AQ65) -> -16179864
A64: (-) Impostos Serviço | D64: =SUM(I64:AR64) -> -1.4597567e+08 | I64: =I40*I30 -> 0 | J64: =J40*J30 -> -2528585.2 | K64: =K40*K30 -> -2604442.8 | L64: =L40*L30 -> -2682576 | M64: =M40*M30 -> -2763053.3 | N64: =N40*N30 -> -2845944.9 | O64: =O40*O30 -> -2931323.3 | P64: =P40*P30 -> -3019263 | ... AQ64: =AQ40*AQ30 -> -6706655.6
A65: (-) Impostos Produto | D65: =SUM(I65:AR65) -> -2.0507726e+08 | I65: =I41*I30 -> 0 | J65: =J41*J30 -> -2457038.2 | K65: =K41*K30 -> -3678797.5 | L65: =L41*L30 -> -3789161.4 | M65: =M41*M30 -> -3902836.3 | N65: =N41*N30 -> -4019921.4 | O65: =O41*O30 -> -4140519 | P65: =P41*P30 -> -4264734.6 | ... AQ65: =AQ41*AQ30 -> -9473208
A66: OPEX | D66: =SUM(I66:AR66) -> -3.3357534e+08 | I66: =SUM(I67:I67) -> -1022890.5 | J66: =SUM(J67:J67) -> -5582844.6 | K66: =SUM(K67:K67) -> -5936499.9 | L66: =SUM(L67:L67) -> -6114594.9 | M66: =SUM(M67:M67) -> -6298032.8 | N66: =SUM(N67:N67) -> -6486973.8 | O66: =SUM(O67:O67) -> -6681583 | P66: =SUM(P67:P67) -> -6882030.5 | ... AQ66: =SUM(AQ67:AQ67) -> -15286979
A67: =A43 -> (-) Custos com operacionais | D67: =SUM(J67:AR67) -> -3.3255245e+08 | I67: =I43*I30 -> -1022890.5 | J67: =J43*J30 -> -5582844.6 | K67: =K43*K30 -> -5936499.9 | L67: =L43*L30 -> -6114594.9 | M67: =M43*M30 -> -6298032.8 | N67: =N43*N30 -> -6486973.8 | O67: =O43*O30 -> -6681583 | P67: =P43*P30 -> -6882030.5 | ... AQ67: =AQ43*AQ30 -> -15286979
A68: Custos de construção | D68: =SUM(I68:AR68) -> -51362715 | I68: =SUM(I69:I69) -> 0 | J68: =SUM(J69:J69) -> -4480395.6 | K68: =SUM(K69:K69) -> -4614807.5 | L68: =SUM(L69:L69) -> -4753251.7 | M68: =SUM(M69:M69) -> -4895849.3 | N68: =SUM(N69:N69) -> -5042724.7 | O68: =SUM(O69:O69) -> -5194006.5 | P68: =SUM(P69:P69) -> -5349826.7 | ... AQ68: =SUM(AQ69:AQ69) -> 0
A69: (-) Depreciação/Amortização | D69: =SUM(I69:AR69) -> -51362715 | I69: =I45*I30 -> 0 | J69: =J45*J30 -> -4480395.6 | K69: =K45*K30 -> -4614807.5 | L69: =L45*L30 -> -4753251.7 | M69: =M45*M30 -> -4895849.3 | N69: =N45*N30 -> -5042724.7 | O69: =O45*O30 -> -5194006.5 | P69: =P45*P30 -> -5349826.7 | ... AQ69: =AQ45*AQ30 -> 0
A70: (=) EBIT | D70: =SUM(I70:AR70) -> 8.1095031e+08 | I70: =SUM(I71:I73) -> 514370.62 | J70: =SUM(J71:J73) -> 11536630 | K70: =SUM(K71:K73) -> 10734892 | L70: =SUM(L71:L73) -> 11057165 | M70: =SUM(M71:M73) -> 11389122 | N70: =SUM(N71:N73) -> 11731053 | O70: =SUM(O71:O73) -> 12083261 | P70: =SUM(P71:P73) -> 12446055 | ... AQ70: =SUM(AQ71:AQ73) -> 39558929
A71: (-) Impostos sobre EBIT | D71: =SUM(I71:AR71) -> -3.5105293e+08 | I71: =I63 -> 0 | J71: =J63 -> -4985623.4 | K71: =K63 -> -6283240.3 | L71: =L63 -> -6471737.5 | M71: =M63 -> -6665889.6 | N71: =N63 -> -6865866.3 | O71: =O63 -> -7071842.3 | P71: =P63 -> -7283997.5 | ... AQ71: =AQ63 -> -16179864
A72: (+) Receita Bruta | D72: =SUM(I72:AR72) -> 1.213366e+09 | I72: =I57 -> 514370.62 | J72: =J57 -> 21002649 | K72: =K57 -> 21632940 | L72: =L57 -> 22282154 | M72: =M57 -> 22950861 | N72: =N57 -> 23639644 | O72: =O57 -> 24349110 | P72: =P57 -> 25079879 | ... AQ72: =AQ57 -> 55738793
A73: (-) Depreciação/Amortização | D73: =SUM(I73:AR73) -> -51362715 | I73: =I68 -> 0 | J73: =J68 -> -4480395.6 | K73: =K68 -> -4614807.5 | L73: =L68 -> -4753251.7 | M73: =M68 -> -4895849.3 | N73: =N68 -> -5042724.7 | O73: =O68 -> -5194006.5 | P73: =P68 -> -5349826.7 | ... AQ73: =AQ68 -> 0
A74: CAPEX | D74: =SUM(I74:AR74) -> -53377615 | I74: =I75 -> -53377615 | J74: =J75 -> 0 | K74: =K75 -> 0 | L74: =L75 -> 0 | M74: =M75 -> 0 | N74: =N75 -> 0 | O74: =O75 -> 0 | P74: =P75 -> 0 | ... AQ74: =AQ75 -> 0
A75: (-) Licenciamento e Equipamentos | D75: =SUM(I75:AR75) -> -53377615 | I75: =I51*I30 -> -53377615 | J75: =J51*J30 -> 0 | K75: =K51*K30 -> 0 | L75: =L51*L30 -> 0 | M75: =M51*M30 -> 0 | N75: =N51*N30 -> 0 | O75: =O51*O30 -> 0 | P75: =P51*P30 -> 0 | ... AQ75: =AQ51*AQ30 -> 0
A77: Fluxo de caixa livre para firma | D77: =SUM(I77:AR77) -> 9.3364737e+09 | I77: =I70+I74 -> -52863244 | J77: =J70+J74+I77 -> -41326614 | K77: =K70+K74+J77 -> -30591722 | L77: =L70+L74+K77 -> -19534558 | M77: =M70+M74+L77 -> -8145435.7 | N77: =N70+N74+M77 -> 3585617.4 | O77: =O70+O74+N77 -> 15668878 | P77: =P70+P74+O77 -> 28114933 | Q77: =Q70+Q74+P77 -> 40934685 | ... AQ77: =AQ70+AQ74+AP77 -> 7.5757269e+08
A80: VPL
A81: Receita Bruta - URE MARÍLIA - BIO | D81: =I81 -> 2.4409769e+08 | I81: =SUM(I82:I86) -> 2.4409769e+08
A82: (+) Receita Contraprestação fixa | D82: =I82 -> 86256470 | I82: =NPV(10%,I58:AQ58) -> 86256470
A83: (+) Receita Reciclável | D83: =I83 -> 102981.85 | I83: =NPV(10%,I59:AQ59) -> 102981.85
A84: (+) Receita Biometano | D84: =I84 -> 96762066 | I84: =NPV(10%,I60:AQ60) -> 96762066
A85: (+) Receita CO2 | D85: =I85 -> 54428662 | I85: =NPV(10%,I61:AQ61) -> 54428662
A86: (+) CBIOS | D86: =I86 -> 6547512.5 | I86: =NPV(10%,I62:AQ62) -> 6547512.5
A87: Impostos | D87: =I87 -> -69830953 | I87: =SUM(I88:I89) -> -69830953
A88: (-) Impostos Serviço | D88: =I88 -> -29327200 | I88: =NPV(10%,I64:AQ64) -> -29327200
A89: (-) Impostos Produto | D89: =I89 -> -40503754 | I89: =NPV(10%,I65:AQ65) -> -40503754
A90: OPEX | D90: =I90 -> -67628189 | I90: =SUM(I91:I91) -> -67628189
A91: =A67 -> (-) Custos com operacionais | D91: =I91 -> -67628189 | I91: =NPV(10%,I67:AQ67) -> -67628189
A92: Custos de construção | D92: =I92 -> -28038086 | I92: =I93 -> -28038086
A93: (-) Depreciação/Amortização | D93: =I93 -> -28038086 | I93: =NPV(10%,I69:AQ69) -> -28038086
A94: (=) EBIT | D94: =I94 -> 1.4622865e+08 | I94: =SUM(I95:I97) -> 1.4622865e+08
A95: (-) Impostos sobre EBIT | D95: =I95 -> -69830953 | I95: =NPV(10%,I71:AQ71) -> -69830953
A96: (+) Receita Bruta | D96: =I96 -> 2.4409769e+08 | I96: =NPV(10%,I72:AQ72) -> 2.4409769e+08
A97: (-) Depreciação/Amortização | D97: =I97 -> -28038086 | I97: =NPV(10%,I73:AQ73) -> -28038086
A98: CAPEX | D98: =I98 -> -48525104 | I98: =I99 -> -48525104
A99: (-) Equipamentos | D99: =I99 -> -48525104 | I99: =NPV(10%,I75:AQ75) -> -48525104
D100: =I100 -> 0
A101: Fluxo de caixa livre para firma | D101: =I101 -> 8.0516359e+08 | I101: =NPV(10%,I77:AQ77) -> 8.0516359e+08
A104: Waterfall VPL
D105: TOTAL | E105: Base 100
A106: =A82 -> (+) Receita Contraprestação fixa | B106: =B82 -> 0 | C106: =C82 -> 0 | D106: =D82 -> 86256470 | E106: =D106/SUM($D$106:$D$115) -> 2.8680113
A107: =A83 -> (+) Receita Reciclável | B107: =B83 -> 0 | C107: =C83 -> 0 | D107: =D83 -> 102981.85 | E107: =D107/SUM($D$106:$D$115) -> 0.003424127
A108: =A84 -> (+) Receita Biometano | B108: =B84 -> 0 | C108: =C84 -> 0 | D108: =D84 -> 96762066 | E108: =D108/SUM($D$106:$D$115) -> 3.2173203
A109: =A85 -> (+) Receita CO2 | B109: =B85 -> 0 | C109: =C85 -> 0 | D109: =D85 -> 54428662 | E109: =D109/SUM($D$106:$D$115) -> 1.8097427
A110: =A86 -> (+) CBIOS | B110: =B86 -> 0 | C110: =C86 -> 0 | D110: =D86 -> 6547512.5 | E110: =D110/SUM($D$106:$D$115) -> 0.21770355
A111: =A88 -> (-) Impostos Serviço | B111: =B88 -> 0 | C111: =C88 -> 0 | D111: =D88 -> -29327200 | E111: =D111/SUM($D$106:$D$115) -> -0.97512383
A112: =A89 -> (-) Impostos Produto | B112: =B89 -> 0 | C112: =C89 -> 0 | D112: =D89 -> -40503754 | E112: =D112/SUM($D$106:$D$115) -> -1.3467421
A113: =A91 -> (-) Custos com operacionais | B113: =B91 -> 0 | C113: =C91 -> 0 | D113: =D91 -> -67628189 | E113: =D113/SUM($D$106:$D$115) -> -2.2486244
A114: =A93 -> (-) Depreciação/Amortização | B114: =B93 -> 0 | C114: =C93 -> 0 | D114: =D93 -> -28038086 | E114: =D114/SUM($D$106:$D$115) -> -0.93226105
A115: =A99 -> (-) Equipamentos | B115: =B99 -> 0 | C115: =C99 -> 0 | D115: =D99 -> -48525104 | E115: =D115/SUM($D$106:$D$115) -> -1.6134505
A116: VPL | D116: =SUM(D106:D115) -> 30075360 | E116: =D116/SUM($D$106:$D$115) -> 1

Sheet LOTE 2
A1: Controle
BM3: Com inflação | BP3: Alternativa 1
A4: Modelo Real ou nominal | B4: Com inflação | D4: WACC | E4: 0.1 | BM4: Sem inflação
A5: VPL | B5: ='DRE_URE MARÍLIA-GAS'!I80 -> 62373297 | C5: MM R$ | D5: TIR projeto | E5: ='DRE_URE MARÍLIA-BIO+GAS'!I79 -> 0.11637598
D6: Payback | E6: ='DRE_URE MARÍLIA-BIO+GAS'!I81 -> 6.7 | G6: COM LPU | H6: SEM LPU
A7: Contraprestação fixa | B7: 2.8540916 | C7: MM R$/ano | G7: 2.8540916 | H7: 2.8540916
A8: Saldo final ativo financeiro | B8: =#REF! -> #REF! | G8: =#REF! -> #REF! | H8: =#REF! -> #REF!
A9: Contraprestação variável - Parcela B Volume | B9: 110 | C9: R$/ton | G9: 110 | H9: 110
A10: Contraprestação variável - Parcela C População | B10: 4.7269692 | C10: R$/hab/mês | G10: 4.7269692 | H10: 2.9928665
A12: Sensibilidade preço de recicláveis | B12: 0 | G12: 0 | H12: 0
A13: Sensibilidade crédito recicláveis | B13: 0 | G13: 0 | H13: 0
A14: Outorga variável | B14: 0 | G14: 0 | H14: 0
A15: Anos de carência de outorga variável | B15: 0 | G15: 0 | H15: 0
A16: Primeiro ano de pagamento integral | B16: 1 | G16: 1 | H16: 1
A18: Fator Capex | B18: 1 | G18: 1 | H18: 1
A19: Fator Opex | B19: 1 | G19: 1 | H19: 1
A21: Capital social mínimo 1o ano | B21: 10 | C21: MM R$ | G21: 10 | H21: 10
A23: Considera limpeza urbana? | B23: 1 | C23: [1=sim;0=não] | G23: 1 | H23: 0
A25: Alavancagem alvo | B25: 1 | G25: 1 | H25: 1
A27: Síntese
A28: Componentes de valor / Waterfall VPL
I29: =YEAR(Premissas!$D$13) -> 2025 | J29: =I29+1 -> 2026 | K29: =J29+1 -> 2027 | L29: =K29+1 -> 2028 | M29: =L29+1 -> 2029 | N29: =M29+1 -> 2030 | O29: =N29+1 -> 2031 | P29: =O29+1 -> 2032 | Q29: =P29+1 -> 2033 | ... AQ29: =AP29+1 -> 2059
A30: Índice de inflação brasileira (IPCA) | I30: =MacroEco!AA$8 -> 1.0714036 | J30: =MacroEco!AB$8 -> 1.1035457 | K30: =MacroEco!AC$8 -> 1.1366521 | L30: =MacroEco!AD$8 -> 1.1707517 | M30: =MacroEco!AE$8 -> 1.2058742 | N30: =MacroEco!AF$8 -> 1.2420504 | O30: =MacroEco!AG$8 -> 1.2793119 | P30: =MacroEco!AH$8 -> 1.3176913 | ... AQ30: =MacroEco!BI$8 -> 2.9269732
A32: Em termos nominais
A33: Receita Bruta - URE MARÍLIA - GAS | D33: =SUM(I33:AR33) -> 7.6194106e+08 | I33: =SUM(I34:I38) -> 480090.43 | J33: =SUM(J34:J38) -> 22391170 | K33: =SUM(K34:K38) -> 22391356 | L33: =SUM(L34:L38) -> 22391549 | M33: =SUM(M34:M38) -> 22391750 | N33: =SUM(N34:N38) -> 22391957 | O33: =SUM(O34:O38) -> 22392173 | P33: =SUM(P34:P38) -> 22392397 | ... AQ33: =SUM(AQ34:AQ38) -> 22402351
A34: (+) Receita Contraprestação fixa | D34: =SUM(I34:AR34) -> 229132800 | I34: ='DRE_URE MARÍLIA-BIO+GAS'!E8 -> 0 | J34: ='DRE_URE MARÍLIA-BIO+GAS'!F8 -> 6739200 | K34: ='DRE_URE MARÍLIA-BIO+GAS'!G8 -> 6739200 | L34: ='DRE_URE MARÍLIA-BIO+GAS'!H8 -> 6739200 | M34: ='DRE_URE MARÍLIA-BIO+GAS'!I8 -> 6739200 | N34: ='DRE_URE MARÍLIA-BIO+GAS'!J8 -> 6739200 | O34: ='DRE_URE MARÍLIA-BIO+GAS'!K8 -> 6739200 | P34: ='DRE_URE MARÍLIA-BIO+GAS'!L8 -> 6739200 | ... AP34: ='DRE_URE MARÍLIA-BIO+GAS'!AL8 -> 6739200 | AQ34: =AP34 -> 6739200
A35: (+) Receita Reciclável | D35: =SUM(I35:AR35) -> 332157 | I35: ='Receita Acessórias'!O18 -> 4710.4288 | J35: ='Receita Acessórias'!P18 -> 4890.2048 | K35: ='Receita Acessórias'!Q18 -> 5075.7357 | L35: ='Receita Acessórias'!R18 -> 5268.8133 | M35: ='Receita Acessórias'!S18 -> 5469.748 | N35: ='Receita Acessórias'!T18 -> 5677.1311 | O35: ='Receita Acessórias'!U18 -> 5892.9261 | P35: ='Receita Acessórias'!V18 -> 6117.478 | ... AP35: ='Receita Acessórias'!AV18 -> 16071.17 | AQ35: =AP35 -> 16071.17
A36: (+) Receita Energia Elétrica | D36: =SUM(I36:AR36) -> 371252800 | I36: ='DRE_URE MARÍLIA-BIO+GAS'!E6 -> 0 | J36: ='DRE_URE MARÍLIA-BIO+GAS'!G6 -> 10919200 | K36: ='DRE_URE MARÍLIA-BIO+GAS'!H6 -> 10919200 | L36: ='DRE_URE MARÍLIA-BIO+GAS'!I6 -> 10919200 | M36: ='DRE_URE MARÍLIA-BIO+GAS'!J6 -> 10919200 | N36: ='DRE_URE MARÍLIA-BIO+GAS'!K6 -> 10919200 | O36: ='DRE_URE MARÍLIA-BIO+GAS'!L6 -> 10919200 | P36: ='DRE_URE MARÍLIA-BIO+GAS'!M6 -> 10919200 | Q36: ='DRE_URE MARÍLIA-BIO+GAS'!N6 -> 10919200 | ... AP36: ='DRE_URE MARÍLIA-BIO+GAS'!AM6 -> 10919200 | AQ36: =AP36 -> 10919200
A37: (+) Receita CO2 | D37: =SUM(I37:AR37) -> 144585000 | I37: ='DRE_URE MARÍLIA-BIO+GAS'!E7 -> 0 | J37: ='DRE_URE MARÍLIA-BIO+GAS'!G7 -> 4252500 | K37: ='DRE_URE MARÍLIA-BIO+GAS'!H7 -> 4252500 | L37: ='DRE_URE MARÍLIA-BIO+GAS'!I7 -> 4252500 | M37: ='DRE_URE MARÍLIA-BIO+GAS'!J7 -> 4252500 | N37: ='DRE_URE MARÍLIA-BIO+GAS'!K7 -> 4252500 | O37: ='DRE_URE MARÍLIA-BIO+GAS'!L7 -> 4252500 | P37: ='DRE_URE MARÍLIA-BIO+GAS'!M7 -> 4252500 | Q37: ='DRE_URE MARÍLIA-BIO+GAS'!N7 -> 4252500 | ... AP37: ='DRE_URE MARÍLIA-BIO+GAS'!AM7 -> 4252500 | AQ37: =AP37 -> 4252500
A38: (+) CBIOS | D38: =SUM(I38:AR38) -> 16638300 | I38: ='DRE_URE MARÍLIA-BIO+GAS'!F10 -> 475380 | J38: ='DRE_URE MARÍLIA-BIO+GAS'!G10 -> 475380 | K38: ='DRE_URE MARÍLIA-BIO+GAS'!H10 -> 475380 | L38: ='DRE_URE MARÍLIA-BIO+GAS'!I10 -> 475380 | M38: ='DRE_URE MARÍLIA-BIO+GAS'!J10 -> 475380 | N38: ='DRE_URE MARÍLIA-BIO+GAS'!K10 -> 475380 | O38: ='DRE_URE MARÍLIA-BIO+GAS'!L10 -> 475380 | P38: ='DRE_URE MARÍLIA-BIO+GAS'!M10 -> 475380 | ... AP38: ='DRE_URE MARÍLIA-BIO+GAS'!AM10 -> 475380 | AQ38: =AP38 -> 475380
A39: Impostos | D39: =SUM(I39:AR39) -> -1.8693681e+08 | I39: =SUM(I40:I41) -> 0 | J39: =SUM(J40:J41) -> -4517822.2 | K39: =SUM(K40:K41) -> -5527848.2 | L39: =SUM(L40:L41) -> -5527848.2 | M39: =SUM(M40:M41) -> -5527848.2 | N39: =SUM(N40:N41) -> -5527848.2 | O39: =SUM(O40:O41) -> -5527848.2 | P39: =SUM(P40:P41) -> -5527848.2 | ... AQ39: =SUM(AQ40:AQ41) -> -5527848.2
A40: (-) Impostos Serviço | D40: =SUM(I40:AR40) -> -77905152 | I40: ='DRE_URE MARÍLIA-BIO+GAS'!E41 -> 0 | J40: ='DRE_URE MARÍLIA-BIO+GAS'!F41 -> -2291328 | K40: ='DRE_URE MARÍLIA-BIO+GAS'!G41 -> -2291328 | L40: ='DRE_URE MARÍLIA-BIO+GAS'!H41 -> -2291328 | M40: ='DRE_URE MARÍLIA-BIO+GAS'!I41 -> -2291328 | N40: ='DRE_URE MARÍLIA-BIO+GAS'!J41 -> -2291328 | O40: ='DRE_URE MARÍLIA-BIO+GAS'!K41 -> -2291328 | P40: ='DRE_URE MARÍLIA-BIO+GAS'!L41 -> -2291328 | ... AQ40: ='DRE_URE MARÍLIA-BIO+GAS'!AM41 -> -2291328
A41: (-) Impostos Produto | D41: =SUM(I41:AR41) -> -1.0903166e+08 | I41: ='DRE_URE MARÍLIA-BIO+GAS'!E12 -> 0 | J41: ='DRE_URE MARÍLIA-BIO+GAS'!F12 -> -2226494.2 | K41: ='DRE_URE MARÍLIA-BIO+GAS'!G12 -> -3236520.2 | L41: ='DRE_URE MARÍLIA-BIO+GAS'!H12 -> -3236520.2 | M41: ='DRE_URE MARÍLIA-BIO+GAS'!I12 -> -3236520.2 | N41: ='DRE_URE MARÍLIA-BIO+GAS'!J12 -> -3236520.2 | O41: ='DRE_URE MARÍLIA-BIO+GAS'!K12 -> -3236520.2 | P41: ='DRE_URE MARÍLIA-BIO+GAS'!L12 -> -3236520.2 | ... AQ41: ='DRE_URE MARÍLIA-BIO+GAS'!AM12 -> -3236520.2
A42: OPEX | D42: =SUM(I42:AR42) -> -1.7836593e+08 | I42: =SUM(I43:I43) -> -954720 | J42: =SUM(J43:J43) -> -5059006.2 | K42: =SUM(K43:K43) -> -5222794.2 | L42: =SUM(L43:L43) -> -5222794.2 | M42: =SUM(M43:M43) -> -5222794.2 | N42: =SUM(N43:N43) -> -5222794.2 | O42: =SUM(O43:O43) -> -5222794.2 | P42: =SUM(P43:P43) -> -5222794.2 | ... AQ42: =SUM(AQ43:AQ43) -> -5222794.2
A43: (-) Custos com operacionais | D43: =SUM(J43:AR43) -> -1.7741121e+08 | I43: =Opex!Z57*-1 -> -954720 | J43: =Opex!AA57*-1 -> -5059006.2 | K43: =Opex!AB57*-1 -> -5222794.2 | L43: =Opex!AC57*-1 -> -5222794.2 | M43: =Opex!AD57*-1 -> -5222794.2 | N43: =Opex!AE57*-1 -> -5222794.2 | O43: =Opex!AF57*-1 -> -5222794.2 | P43: =Opex!AG57*-1 -> -5222794.2 | ... AP43: =Opex!BG57*-1 -> -5222794.2 | AQ43: =AP43 -> -5222794.2
A44: Custos de construção | D44: =SUM(I44:AR44) -> -40600000 | I44: =I45 -> 0 | J44: =J45 -> -4060000 | K44: =K45 -> -4060000 | L44: =L45 -> -4060000 | M44: =M45 -> -4060000 | N44: =N45 -> -4060000 | O44: =O45 -> -4060000 | P44: =P45 -> -4060000 | ... AQ44: =AQ45 -> 0
A45: (-) Depreciação/Amortização | D45: =SUM(I45:AR45) -> -40600000 | I45: ='DRE_URE MARÍLIA-BIO+GAS'!E36 -> 0 | J45: ='DRE_URE MARÍLIA-BIO+GAS'!F36 -> -4060000 | K45: ='DRE_URE MARÍLIA-BIO+GAS'!G36 -> -4060000 | L45: ='DRE_URE MARÍLIA-BIO+GAS'!H36 -> -4060000 | M45: ='DRE_URE MARÍLIA-BIO+GAS'!I36 -> -4060000 | N45: ='DRE_URE MARÍLIA-BIO+GAS'!J36 -> -4060000 | O45: ='DRE_URE MARÍLIA-BIO+GAS'!K36 -> -4060000 | P45: ='DRE_URE MARÍLIA-BIO+GAS'!L36 -> -4060000 | ... AQ45: ='DRE_URE MARÍLIA-BIO+GAS'!AM36 -> 0
A46: (=) EBIT | D46: =SUM(I46:AR46) -> 5.3440424e+08 | I46: =SUM(I47:I49) -> 480090.43 | J46: =SUM(J47:J49) -> 13813348 | K46: =SUM(K47:K49) -> 12803507 | L46: =SUM(L47:L49) -> 12803701 | M46: =SUM(M47:M49) -> 12803901 | N46: =SUM(N47:N49) -> 12804109 | O46: =SUM(O47:O49) -> 12804325 | P46: =SUM(P47:P49) -> 12804549 | ... AQ46: =SUM(AQ47:AQ49) -> 16874503
A47: (-) Impostos sobre EBIT | D47: =SUM(I47:AR47) -> -1.8693681e+08 | I47: =I39 -> 0 | J47: =J39 -> -4517822.2 | K47: =K39 -> -5527848.2 | L47: =L39 -> -5527848.2 | M47: =M39 -> -5527848.2 | N47: =N39 -> -5527848.2 | O47: =O39 -> -5527848.2 | P47: =P39 -> -5527848.2 | ... AQ47: =AQ39 -> -5527848.2
A48: (+) Receita Bruta | D48: =SUM(I48:AR48) -> 7.6194106e+08 | I48: =I33 -> 480090.43 | J48: =J33 -> 22391170 | K48: =K33 -> 22391356 | L48: =L33 -> 22391549 | M48: =M33 -> 22391750 | N48: =N33 -> 22391957 | O48: =O33 -> 22392173 | P48: =P33 -> 22392397 | ... AQ48: =AQ33 -> 22402351
A49: (-) Depreciação/Amortização | D49: =SUM(I49:AR49) -> -40600000 | I49: =I44 -> 0 | J49: =J44 -> -4060000 | K49: =K44 -> -4060000 | L49: =L44 -> -4060000 | M49: =M44 -> -4060000 | N49: =N44 -> -4060000 | O49: =O44 -> -4060000 | P49: =P44 -> -4060000 | ... AQ49: =AQ44 -> 0
A50: CAPEX | D50: =SUM(I50:AR50) -> -58927199 | I50: =I51 -> -58927199 | J50: =J51 -> 0 | K50: =K51 -> 0 | L50: =L51 -> 0 | M50: =M51 -> 0 | N50: =N51 -> 0 | O50: =O51 -> 0 | P50: =P51 -> 0 | ... AQ50: =AQ51 -> 0
A51: (-) Licenciamento e Equipamentos | D51: =SUM(I51:AR51) -> -58927199 | I51: =Capex!O57*-1 -> -58927199 | J51: =Capex!P57*-1 -> 0 | K51: =Capex!Q57*-1 -> 0 | L51: =Capex!R57*-1 -> 0 | M51: =Capex!S57*-1 -> 0 | N51: =Capex!T57*-1 -> 0 | O51: =Capex!U57*-1 -> 0 | P51: =Capex!V57*-1 -> 0 | ... AQ51: =Capex!AW57*-1 -> 0
A53: Fluxo de caixa livre para firma | D53: =SUM(I53:AR53) -> 6.8263563e+09 | I53: =I46+I50 -> -58447108 | J53: =J46+J50+I53 -> -44633760 | K53: =K46+K50+J53 -> -31830253 | L53: =L46+L50+K53 -> -19026552 | M53: =M46+M50+L53 -> -6222650.7 | N53: =N46+N50+M53 -> 6581458.2 | O53: =O46+O50+N53 -> 19385783 | P53: =P46+P50+O53 -> 32190332 | Q53: =Q46+Q50+P53 -> 44995114 | ... AQ53: =AQ46+AQ50+AP53 -> 4.7547704e+08
A56: Em termos reais
A57: =A33 -> Receita Bruta - URE MARÍLIA - GAS | D57: =SUM(I57:AR57) -> 1.4273735e+09 | I57: =SUM(I58:I62) -> 514370.62 | J57: =SUM(J58:J62) -> 24709680 | K57: =SUM(K58:K62) -> 25451181 | L57: =SUM(L58:L62) -> 26214943 | M57: =SUM(M58:M62) -> 27001633 | N57: =SUM(N58:N62) -> 27811940 | O57: =SUM(O58:O62) -> 28646574 | P57: =SUM(P58:P62) -> 29506267 | ... AQ57: =SUM(AQ58:AQ62) -> 65571081
A58: (+) Receita Contraprestação fixa | D58: =SUM(I58:AR58) -> 4.2934021e+08 | I58: =I34*I30 -> 0 | J58: =J34*J30 -> 7437015.3 | K58: =K34*K30 -> 7660125.8 | L58: =L34*L30 -> 7889929.5 | M58: =M34*M30 -> 8126627.4 | N58: =N34*N30 -> 8370426.3 | O58: =O34*O30 -> 8621539 | P58: =P34*P30 -> 8880185.2 | ... AQ58: =AQ34*AQ30 -> 19725458
A59: (+) Receita Reciclável | D59: =SUM(I59:AR59) -> 681527.98 | I59: =I35*I30 -> 5046.7704 | J59: =J35*J30 -> 5396.5646 | K59: =K35*K30 -> 5769.3456 | L59: =L35*L30 -> 6168.4719 | M59: =M35*M30 -> 6595.828 | N59: =N35*N30 -> 7051.2831 | O59: =O35*O30 -> 7538.8908 | P59: =P35*P30 -> 8060.9475 | ... AQ59: =AQ35*AQ30 -> 47039.885
A60: (+) Receita Energia Elétrica | D60: =SUM(I60:AR60) -> 6.9563918e+08 | I60: =I36*I30 -> 0 | J60: =J36*J30 -> 12049836 | K60: =K36*K30 -> 12411332 | L60: =L36*L30 -> 12783671 | M60: =M36*M30 -> 13167182 | N60: =N36*N30 -> 13562197 | O60: =O36*O30 -> 13969063 | P60: =P36*P30 -> 14388135 | ... AQ60: =AQ36*AQ30 -> 31960206
A61: (+) Receita CO2 | D61: =SUM(I61:AR61) -> 2.709178e+08 | I61: =I37*I30 -> 0 | J61: =J37*J30 -> 4692828.2 | K61: =K37*K30 -> 4833613 | L61: =L37*L30 -> 4978621.4 | M61: =M37*M30 -> 5127980 | N61: =N37*N30 -> 5281819.5 | O61: =O37*O30 -> 5440274 | P61: =P37*P30 -> 5603482.3 | ... AQ61: =AQ37*AQ30 -> 12446954
A62: (+) CBIOS | D62: =SUM(I62:AR62) -> 30794780 | I62: =I38*I30 -> 509323.85 | J62: =J38*J30 -> 524603.56 | K62: =K38*K30 -> 540341.67 | L62: =L38*L30 -> 556551.92 | M62: =M38*M30 -> 573248.48 | N62: =N38*N30 -> 590445.93 | O62: =O38*O30 -> 608159.31 | P62: =P38*P30 -> 626404.09 | ... AQ62: =AQ38*AQ30 -> 1391424.5
A63: Impostos | D63: =SUM(I63:AR63) -> -3.5105293e+08 | I63: =SUM(I64:I65) -> 0 | J63: =SUM(J64:J65) -> -4985623.4 | K63: =SUM(K64:K65) -> -6283240.3 | L63: =SUM(L64:L65) -> -6471737.5 | M63: =SUM(M64:M65) -> -6665889.6 | N63: =SUM(N64:N65) -> -6865866.3 | O63: =SUM(O64:O65) -> -7071842.3 | P63: =SUM(P64:P65) -> -7283997.5 | ... AQ63: =SUM(AQ64:AQ65) -> -16179864
A64: (-) Impostos Serviço | D64: =SUM(I64:AR64) -> -1.4597567e+08 | I64: =I40*I30 -> 0 | J64: =J40*J30 -> -2528585.2 | K64: =K40*K30 -> -2604442.8 | L64: =L40*L30 -> -2682576 | M64: =M40*M30 -> -2763053.3 | N64: =N40*N30 -> -2845944.9 | O64: =O40*O30 -> -2931323.3 | P64: =P40*P30 -> -3019263 | ... AQ64: =AQ40*AQ30 -> -6706655.6
A65: (-) Impostos Produto | D65: =SUM(I65:AR65) -> -2.0507726e+08 | I65: =I41*I30 -> 0 | J65: =J41*J30 -> -2457038.2 | K65: =K41*K30 -> -3678797.5 | L65: =L41*L30 -> -3789161.4 | M65: =M41*M30 -> -3902836.3 | N65: =N41*N30 -> -4019921.4 | O65: =O41*O30 -> -4140519 | P65: =P41*P30 -> -4264734.6 | ... AQ65: =AQ41*AQ30 -> -9473208
A66: OPEX | D66: =SUM(I66:AR66) -> -3.3357534e+08 | I66: =SUM(I67:I67) -> -1022890.5 | J66: =SUM(J67:J67) -> -5582844.6 | K66: =SUM(K67:K67) -> -5936499.9 | L66: =SUM(L67:L67) -> -6114594.9 | M66: =SUM(M67:M67) -> -6298032.8 | N66: =SUM(N67:N67) -> -6486973.8 | O66: =SUM(O67:O67) -> -6681583 | P66: =SUM(P67:P67) -> -6882030.5 | ... AQ66: =SUM(AQ67:AQ67) -> -15286979
A67: =A43 -> (-) Custos com operacionais | D67: =SUM(J67:AR67) -> -3.3255245e+08 | I67: =I43*I30 -> -1022890.5 | J67: =J43*J30 -> -5582844.6 | K67: =K43*K30 -> -5936499.9 | L67: =L43*L30 -> -6114594.9 | M67: =M43*M30 -> -6298032.8 | N67: =N43*N30 -> -6486973.8 | O67: =O43*O30 -> -6681583 | P67: =P43*P30 -> -6882030.5 | ... AQ67: =AQ43*AQ30 -> -15286979
A68: Custos de construção | D68: =SUM(I68:AR68) -> -51362715 | I68: =SUM(I69:I69) -> 0 | J68: =SUM(J69:J69) -> -4480395.6 | K68: =SUM(K69:K69) -> -4614807.5 | L68: =SUM(L69:L69) -> -4753251.7 | M68: =SUM(M69:M69) -> -4895849.3 | N68: =SUM(N69:N69) -> -5042724.7 | O68: =SUM(O69:O69) -> -5194006.5 | P68: =SUM(P69:P69) -> -5349826.7 | ... AQ68: =SUM(AQ69:AQ69) -> 0
A69: (-) Depreciação/Amortização | D69: =SUM(I69:AR69) -> -51362715 | I69: =I45*I30 -> 0 | J69: =J45*J30 -> -4480395.6 | K69: =K45*K30 -> -4614807.5 | L69: =L45*L30 -> -4753251.7 | M69: =M45*M30 -> -4895849.3 | N69: =N45*N30 -> -5042724.7 | O69: =O45*O30 -> -5194006.5 | P69: =P45*P30 -> -5349826.7 | ... AQ69: =AQ45*AQ30 -> 0
A70: (=) EBIT | D70: =SUM(I70:AR70) -> 1.0249578e+09 | I70: =SUM(I71:I73) -> 514370.62 | J70: =SUM(J71:J73) -> 15243661 | K70: =SUM(K71:K73) -> 14553134 | L70: =SUM(L71:L73) -> 14989954 | M70: =SUM(M71:M73) -> 15439895 | N70: =SUM(N71:N73) -> 15903349 | O70: =SUM(O71:O73) -> 16380725 | P70: =SUM(P71:P73) -> 16872443 | ... AQ70: =SUM(AQ71:AQ73) -> 49391218
A71: (-) Impostos sobre EBIT | D71: =SUM(I71:AR71) -> -3.5105293e+08 | I71: =I63 -> 0 | J71: =J63 -> -4985623.4 | K71: =K63 -> -6283240.3 | L71: =L63 -> -6471737.5 | M71: =M63 -> -6665889.6 | N71: =N63 -> -6865866.3 | O71: =O63 -> -7071842.3 | P71: =P63 -> -7283997.5 | ... AQ71: =AQ63 -> -16179864
A72: (+) Receita Bruta | D72: =SUM(I72:AR72) -> 1.4273735e+09 | I72: =I57 -> 514370.62 | J72: =J57 -> 24709680 | K72: =K57 -> 25451181 | L72: =L57 -> 26214943 | M72: =M57 -> 27001633 | N72: =N57 -> 27811940 | O72: =O57 -> 28646574 | P72: =P57 -> 29506267 | ... AQ72: =AQ57 -> 65571081
A73: (-) Depreciação/Amortização | D73: =SUM(I73:AR73) -> -51362715 | I73: =I68 -> 0 | J73: =J68 -> -4480395.6 | K73: =K68 -> -4614807.5 | L73: =L68 -> -4753251.7 | M73: =M68 -> -4895849.3 | N73: =N68 -> -5042724.7 | O73: =O68 -> -5194006.5 | P73: =P68 -> -5349826.7 | ... AQ73: =AQ68 -> 0
A74: CAPEX | D74: =SUM(I74:AR74) -> -63134813 | I74: =I75 -> -63134813 | J74: =J75 -> 0 | K74: =K75 -> 0 | L74: =L75 -> 0 | M74: =M75 -> 0 | N74: =N75 -> 0 | O74: =O75 -> 0 | P74: =P75 -> 0 | ... AQ74: =AQ75 -> 0
A75: (-) Licenciamento e Equipamentos | D75: =SUM(I75:AR75) -> -63134813 | I75: =I51*I30 -> -63134813 | J75: =J51*J30 -> 0 | K75: =K51*K30 -> 0 | L75: =L51*L30 -> 0 | M75: =M51*M30 -> 0 | N75: =N51*N30 -> 0 | O75: =O51*O30 -> 0 | P75: =P51*P30 -> 0 | ... AQ75: =AQ51*AQ30 -> 0
A77: Fluxo de caixa livre para firma | D77: =SUM(I77:AR77) -> 1.2141262e+10 | I77: =I70+I74 -> -62620443 | J77: =J70+J74+I77 -> -47376782 | K77: =K70+K74+J77 -> -32823648 | L77: =L70+L74+K77 -> -17833695 | M77: =M70+M74+L77 -> -2393800.1 | N77: =N70+N74+M77 -> 13509549 | O77: =O70+O74+N77 -> 29890274 | P77: =P70+P74+O77 -> 46762717 | Q77: =Q70+Q74+P77 -> 64141650 | ... AQ77: =AQ70+AQ74+AP77 -> 9.6182304e+08
A80: VPL
A81: Receita Bruta - URE MARÍLIA - GAS | D81: =I81 -> 2.8709282e+08 | I81: =SUM(I82:I86) -> 2.8709282e+08
A82: (+) Receita Contraprestação fixa | D82: =I82 -> 86256470 | I82: =NPV(10%,I58:AQ58) -> 86256470
A83: (+) Receita Reciclável | D83: =I83 -> 102981.85 | I83: =NPV(10%,I59:AQ59) -> 102981.85
A84: (+) Receita Energia Elétrica | D84: =I84 -> 1.3975719e+08 | I84: =NPV(10%,I60:AQ60) -> 1.3975719e+08
A85: (+) Receita CO2 | D85: =I85 -> 54428662 | I85: =NPV(10%,I61:AQ61) -> 54428662
A86: (+) CBIOS | D86: =I86 -> 6547512.5 | I86: =NPV(10%,I62:AQ62) -> 6547512.5
A87: Impostos | D87: =I87 -> -69830953 | I87: =SUM(I88:I89) -> -69830953
A88: (-) Impostos Serviço | D88: =I88 -> -29327200 | I88: =NPV(10%,I64:AQ64) -> -29327200
A89: (-) Impostos Produto | D89: =I89 -> -40503754 | I89: =NPV(10%,I65:AQ65) -> -40503754
A90: OPEX | D90: =I90 -> -67628189 | I90: =SUM(I91:I91) -> -67628189
A91: =A67 -> (-) Custos com operacionais | D91: =I91 -> -67628189 | I91: =NPV(10%,I67:AQ67) -> -67628189
A92: Custos de construção | D92: =I92 -> -28038086 | I92: =I93 -> -28038086
A93: (-) Depreciação/Amortização | D93: =I93 -> -28038086 | I93: =NPV(10%,I69:AQ69) -> -28038086
A94: (=) EBIT | D94: =I94 -> 1.8922378e+08 | I94: =SUM(I95:I97) -> 1.8922378e+08
A95: (-) Impostos sobre EBIT | D95: =I95 -> -69830953 | I95: =NPV(10%,I71:AQ71) -> -69830953
A96: (+) Receita Bruta | D96: =I96 -> 2.8709282e+08 | I96: =NPV(10%,I72:AQ72) -> 2.8709282e+08
A97: (-) Depreciação/Amortização | D97: =I97 -> -28038086 | I97: =NPV(10%,I73:AQ73) -> -28038086
A98: CAPEX | D98: =I98 -> -57395285 | I98: =I99 -> -57395285
A99: (-) Equipamentos | D99: =I99 -> -57395285 | I99: =NPV(10%,I75:AQ75) -> -57395285
D100: =I100 -> 0
A101: Fluxo de caixa livre para firma | D101: =I101 -> 1.1078573e+09 | I101: =NPV(10%,I77:AQ77) -> 1.1078573e+09
A104: Waterfall VPL
D105: TOTAL | E105: Base 100
A106: =A82 -> (+) Receita Contraprestação fixa | B106: =B82 -> 0 | C106: =C82 -> 0 | D106: =D82 -> 86256470 | E106: =D106/SUM($D$106:$D$115) -> 1.3435524
A107: =A83 -> (+) Receita Reciclável | B107: =B83 -> 0 | C107: =C83 -> 0 | D107: =D83 -> 102981.85 | E107: =D107/SUM($D$106:$D$115) -> 0.0016040711
A108: =A84 -> (+) Receita Energia Elétrica | B108: =B84 -> 0 | C108: =C84 -> 0 | D108: =D84 -> 1.3975719e+08 | E108: =D108/SUM($D$106:$D$115) -> 2.176893
A109: =A85 -> (+) Receita CO2 | B109: =B85 -> 0 | C109: =C85 -> 0 | D109: =D85 -> 54428662 | E109: =D109/SUM($D$106:$D$115) -> 0.84779448
A110: =A86 -> (+) CBIOS | B110: =B86 -> 0 | C110: =C86 -> 0 | D110: =D86 -> 6547512.5 | E110: =D110/SUM($D$106:$D$115) -> 0.1019857
A111: =A88 -> (-) Impostos Serviço | B111: =B88 -> 0 | C111: =C88 -> 0 | D111: =D88 -> -29327200 | E111: =D111/SUM($D$106:$D$115) -> -0.45680781
A112: =A89 -> (-) Impostos Produto | B112: =B89 -> 0 | C112: =C89 -> 0 | D112: =D89 -> -40503754 | E112: =D112/SUM($D$106:$D$115) -> -0.63089662
A113: =A91 -> (-) Custos com operacionais | B113: =B91 -> 0 | C113: =C91 -> 0 | D113: =D91 -> -67628189 | E113: =D113/SUM($D$106:$D$115) -> -1.0533936
A114: =A93 -> (-) Depreciação/Amortização | B114: =B93 -> 0 | C114: =C93 -> 0 | D114: =D93 -> -28038086 | E114: =D114/SUM($D$106:$D$115) -> -0.43672826
A115: =A99 -> (-) Equipamentos | B115: =B99 -> 0 | C115: =C99 -> 0 | D115: =D99 -> -57395285 | E115: =D115/SUM($D$106:$D$115) -> -0.89400334
A116: VPL | D116: =SUM(D106:D115) -> 64200303 | E116: =D116/SUM($D$106:$D$115) -> 1

Sheet OPERACIONAL
B1: Unid | C1: Fonte | E1: Fator 1 | F1: Unid fator 1 | H1: 2025 | I1: =H1+1 -> 2026 | J1: =I1+1 -> 2027 | K1: =J1+1 -> 2028 | L1: =K1+1 -> 2029 | M1: =L1+1 -> 2030 | N1: =M1+1 -> 2031 | O1: =N1+1 -> 2032 | P1: =O1+1 -> 2033 | ... AP1: =AO1+1 -> 2059
H2: 1 | I2: 2 | J2: 3 | K2: 4 | L2: 5 | M2: 6 | N2: 7 | O2: 8 | P2: 9 | Q2: 10 | R2: 11 | S2: 12 | T2: 13 | U2: 14
A3: POPULAÇÃO E DEMANDA
A4: População atendida | B4: hab | E4: =AVERAGE(H4:AP4) -> 283215.76 | F4: hab | H4: 236158.93 | I4: 241443.17 | J4: 246845.64 | K4: =Apoio!$R10 -> 254313 | L4: =Apoio!$R11 -> 256230 | M4: =Apoio!$R12 -> 258242 | N4: =Apoio!$R13 -> 260277 | O4: =Apoio!$R14 -> 262335 | P4: =Apoio!$R15 -> 264416 | Q4: =Apoio!$R16 -> 266189 | R4: =Apoio!$R17 -> 268315 | S4: =Apoio!$R18 -> 270463 | T4: =Apoio!$R19 -> 272633 | U4: =Apoio!$R20 -> 274826 | V4: =Apoio!$R21 -> 276540 | W4: =Apoio!$R22 -> 278670 | X4: =Apoio!$R23 -> 280823 | Y4: =Apoio!$R24 -> 283000 | Z4: =Apoio!$R25 -> 285200 | AA4: =Apoio!$R26 -> 287296 | AB4: =Apoio!$R28 -> 291807 | AC4: =Apoio!$R29 -> 294098 | AD4: =Apoio!$R29 -> 294098 | AE4: =Apoio!$R30 -> 296413 | AF4: =Apoio!$R31 -> 298476 | AG4: =Apoio!$R32 -> 300781 | AH4: =Apoio!$R33 -> 303110 | AI4: =Apoio!$R34 -> 305463 | AJ4: =Apoio!$R35 -> 307841 | AK4: =Apoio!$R36 -> 310095 | AL4: =Apoio!$R37 -> 312455 | AM4: =Apoio!$R38 -> 314840 | AN4: =Apoio!$R39 -> 317250 | AO4: =Apoio!$R40 -> 319686 | AP4: =Apoio!$R41 -> 321923
A6: DEMANDA DE RESÍDUOS | H6: =SUM(H7) -> 63070 | I6: =SUM(I7) -> 63570 | J6: =SUM(J7) -> 64060 | K6: =SUM(K7) -> 64560 | L6: =SUM(L7) -> 65070 | M6: =SUM(M7) -> 65570 | N6: =SUM(N7) -> 66080 | O6: =SUM(O7) -> 66600 | ... AP6: =SUM(AP7) -> 81730
A7: Geração RSD | B7: t/ano | H7: =Apoio!$T7 -> 63070 | I7: =Apoio!$T8 -> 63570 | J7: =Apoio!$T9 -> 64060 | K7: =Apoio!$T10 -> 64560 | L7: =Apoio!$T11 -> 65070 | M7: =Apoio!$T12 -> 65570 | N7: =Apoio!$T13 -> 66080 | O7: =Apoio!$T14 -> 66600 | P7: =Apoio!$T15 -> 67120 | Q7: =Apoio!$T16 -> 67590 | R7: =Apoio!$T17 -> 68140 | S7: =Apoio!$T18 -> 68690 | T7: =Apoio!$T19 -> 69250 | U7: =Apoio!$T20 -> 69800 | V7: =Apoio!$T21 -> 70210 | W7: =Apoio!$T22 -> 70790 | X7: =Apoio!$T23 -> 71330 | Y7: =Apoio!$T24 -> 71890 | Z7: =Apoio!$T25 -> 72450 | AA7: =Apoio!$T26 -> 72930 | AB7: =Apoio!$T27 -> 73510 | AC7: =Apoio!$T28 -> 74040 | AD7: =Apoio!$T29 -> 74650 | AE7: =Apoio!$T30 -> 75220 | AF7: =Apoio!$T31 -> 75780 | AG7: =Apoio!$T32 -> 76350 | AH7: =Apoio!$T33 -> 76920 | AI7: =Apoio!$T34 -> 77530 | AJ7: =Apoio!$T35 -> 78120 | AK7: =Apoio!$T36 -> 78700 | AL7: =Apoio!$T37 -> 79320 | AM7: =Apoio!$T38 -> 79910 | AN7: =Apoio!$T39 -> 80500 | AO7: =Apoio!$T40 -> 81130 | AP7: =Apoio!$T41 -> 81730
A8: Rejeito | B8: t/ano | E8: 0.16 | H8: =H7*$E$8 -> 10091.2 | I8: =I7*$E$8 -> 10171.2 | J8: =J7*$E$8 -> 10249.6 | K8: =K7*$E$8 -> 10329.6 | L8: =L7*$E$8 -> 10411.2 | M8: =M7*$E$8 -> 10491.2 | N8: =N7*$E$8 -> 10572.8 | O8: =O7*$E$8 -> 10656 | ... AP8: =AP7*$E$8 -> 13076.8
A10: VALORIZAÇÃO DE RESÍDUOS
A11: Fração Úmida | B11: t/ano | E11: 0.45 | H11: =H7*$E$11 -> 28381.5 | I11: =I7*$E$11 -> 28606.5 | J11: =J7*$E$11 -> 28827 | K11: =K7*$E$11 -> 29052 | L11: =L7*$E$11 -> 29281.5 | M11: =M7*$E$11 -> 29506.5 | N11: =N7*$E$11 -> 29736 | O11: =O7*$E$11 -> 29970 | ... AP11: =AP7*$E$11 -> 36778.5
A12: Fração Seca | B12: t/ano | E12: 0.34 | H12: =H7*$E$12 -> 21443.8 | I12: =I7*$E$12 -> 21613.8 | J12: =J7*$E$12 -> 21780.4 | K12: =K7*$E$12 -> 21950.4 | L12: =L7*$E$12 -> 22123.8 | M12: =M7*$E$12 -> 22293.8 | N12: =N7*$E$12 -> 22467.2 | O12: =O7*$E$12 -> 22644 | ... AP12: =AP7*$E$12 -> 27788.2
A13: Metais e Vidros | B13: t/ano | E13: 0.05 | H13: =H7*$E$13 -> 3153.5 | I13: =I7*$E$13 -> 3178.5 | J13: =J7*$E$13 -> 3203 | K13: =K7*$E$13 -> 3228 | L13: =L7*$E$13 -> 3253.5 | M13: =M7*$E$13 -> 3278.5 | N13: =N7*$E$13 -> 3304 | O13: =O7*$E$13 -> 3330 | ... AP13: =AP7*$E$13 -> 4086.5
A15: REJEITOS NÃO VALORIZADOS | H15: =SUM(H17) -> 10091.2 | I15: =SUM(I17) -> 38777.7 | J15: =SUM(J17) -> 39076.6 | K15: =SUM(K17) -> 39381.6 | L15: =SUM(L17) -> 39692.7 | M15: =SUM(M17) -> 39997.7 | N15: =SUM(N17) -> 40308.8 | O15: =SUM(O17) -> 40626 | ... AP15: =SUM(AP17) -> 49855.3
A16: Aterro Sanitário
A17: Massa aterrada total | B17: t/ano | H17: =H8 -> 10091.2 | I17: =SUM(I11,I8) -> 38777.7 | J17: =SUM(J11,J8) -> 39076.6 | K17: =SUM(K11,K8) -> 39381.6 | L17: =SUM(L11,L8) -> 39692.7 | M17: =SUM(M11,M8) -> 39997.7 | N17: =SUM(N11,N8) -> 40308.8 | O17: =SUM(O11,O8) -> 40626 | P17: =SUM(P11,P8) -> 40943.2 | ... AP17: =SUM(AP11,AP8) -> 49855.3

Sheet Receita Acessórias
A1: Receitas Acessórias | B1: MMR$ | O1: 2024 | P1: =O1+1 -> 2025 | Q1: =P1+1 -> 2026 | R1: =Q1+1 -> 2027 | S1: =R1+1 -> 2028 | T1: =S1+1 -> 2029 | U1: =T1+1 -> 2030 | V1: =U1+1 -> 2031 | W1: =V1+1 -> 2032 | ... AV1: =AU1+1 -> 2057
A2: Premissas
A3: Geral
A4: =MacroEco!A$8 -> Índice de inflação brasileira (IPCA) | B4: =MacroEco!B$8 -> 44985 | E4: =Premissas!D$8 -> 1 | F4: [1: Nominais; 2: Reais] | O4: =MacroEco!AA$8 -> 1.0714036 | P4: =MacroEco!AB$8 -> 1.1035457 | Q4: =MacroEco!AC$8 -> 1.1366521 | R4: =MacroEco!AD$8 -> 1.1707517 | S4: =MacroEco!AE$8 -> 1.2058742 | T4: =MacroEco!AF$8 -> 1.2420504 | U4: =MacroEco!AG$8 -> 1.2793119 | V4: =MacroEco!AH$8 -> 1.3176913 | ... AV4: =MacroEco!BH$8 -> 2.8417216
A5: =MacroEco!A$11 -> Câmbio (nominal) (média do período) | B5: =MacroEco!B$11 -> R$/US$ | E5: =Premissas!D$8 -> 1 | F5: =Premissas!E$8 -> [1: Nominais; 2: Reais] | O5: =MacroEco!AA$11 -> 5.1 | P5: =MacroEco!AB$11 -> 5.15 | Q5: =MacroEco!AC$11 -> 5.2002875 | R5: =MacroEco!AD$11 -> 5.2510661 | S5: =MacroEco!AE$11 -> 5.3023405 | T5: =MacroEco!AF$11 -> 5.3541155 | U5: =MacroEco!AG$11 -> 5.4063961 | V5: =MacroEco!AH$11 -> 5.4591873 | ... AV5: =MacroEco!BH$11 -> 7.0283162
A6: =MacroEco!A$11 -> Câmbio (nominal) (média do período) | B6: =MacroEco!B$12 -> R$/Euro | E6: =Premissas!D$8 -> 1 | F6: =Premissas!E$8 -> [1: Nominais; 2: Reais] | O6: =MacroEco!AA$12 -> 5.496797 | P6: =MacroEco!AB$12 -> 5.5344095 | Q6: =MacroEco!AC$12 -> 5.5722794 | R6: =MacroEco!AD$12 -> 5.6104083 | S6: =MacroEco!AE$12 -> 5.6487982 | T6: =MacroEco!AF$12 -> 5.6874508 | U6: =MacroEco!AG$12 -> 5.7263679 | V6: =MacroEco!AH$12 -> 5.7655512 | ... AV6: =MacroEco!BH$12 -> 6.8840212
A8: Receitas Acessórias | B8: MMR$ | O8: =SUM(O9,#REF!) -> #REF! | P8: =SUM(P9,#REF!) -> #REF! | Q8: =SUM(Q9,#REF!) -> #REF! | R8: =SUM(R9,#REF!) -> #REF! | S8: =SUM(S9,#REF!) -> #REF! | T8: =SUM(T9,#REF!) -> #REF! | U8: =SUM(U9,#REF!) -> #REF! | V8: =SUM(V9,#REF!) -> #REF! | ... AV8: =SUM(AV9,#REF!) -> #REF!
A9: Recicláveis | O9: =SUM(O14) -> 4.7104288 | P9: =SUM(P14) -> 4.8902048 | Q9: =SUM(Q14) -> 5.0757357 | R9: =SUM(R14) -> 5.2688133 | S9: =SUM(S14) -> 5.469748 | T9: =SUM(T14) -> 5.6771311 | U9: =SUM(U14) -> 5.8929261 | V9: =SUM(V14) -> 6.117478 | ... AV9: =SUM(AV14) -> 16.07117
A10: Recicláveis valorizados | B10: ton/ano
A11: Vidro | B11: ton/ano | E11: 0.3 | O11: =OPERACIONAL!H$13*$E$11 -> 946.05 | P11: =OPERACIONAL!I$13*$E$11 -> 953.55 | Q11: =OPERACIONAL!J$13*$E$11 -> 960.9 | R11: =OPERACIONAL!K$13*$E$11 -> 968.4 | S11: =OPERACIONAL!L$13*$E$11 -> 976.05 | T11: =OPERACIONAL!M$13*$E$11 -> 983.55 | U11: =OPERACIONAL!N$13*$E$11 -> 991.2 | V11: =OPERACIONAL!O$13*$E$11 -> 999 | ... AV11: =OPERACIONAL!AO$13*$E$11 -> 1216.95
A12: Metal | B12: ton/ano | E12: 0.7 | O12: =OPERACIONAL!H$13*$E$12 -> 2207.45 | P12: =OPERACIONAL!I$13*$E$12 -> 2224.95 | Q12: =OPERACIONAL!J$13*$E$12 -> 2242.1 | R12: =OPERACIONAL!K$13*$E$12 -> 2259.6 | S12: =OPERACIONAL!L$13*$E$12 -> 2277.45 | T12: =OPERACIONAL!M$13*$E$12 -> 2294.95 | U12: =OPERACIONAL!N$13*$E$12 -> 2312.8 | V12: =OPERACIONAL!O$13*$E$12 -> 2331 | ... AV12: =OPERACIONAL!AO$13*$E$12 -> 2839.55
A14: Venda de Recicláveis | B14: R$/ton | E14: =1/1000 -> 0.001 | F14: K R$/MM R$ | O14: =$E14*O18 -> 4.7104288 | P14: =$E14*P18 -> 4.8902048 | Q14: =$E14*Q18 -> 5.0757357 | R14: =$E14*R18 -> 5.2688133 | S14: =$E14*S18 -> 5.469748 | T14: =$E14*T18 -> 5.6771311 | U14: =$E14*U18 -> 5.8929261 | V14: =$E14*V18 -> 6.117478 | ... AV14: =$E14*AV18 -> 16.07117
A15: Preços unitários | E15: ='LOTE 3'!$B$12 -> 0 | F15: sensibilidade preço recicláveis | I15: 44105
A16: Vidro | B16: R$/ton | E16: =I16*(1+$E$15)/INDEX(MacroEco!$55:$55,MATCH($I$15,MacroEco!$51:$51,0)) -> 96.548896 | F16: R$/ton | I16: 80 | J16: R$/ton | K16: CEMPRE | O16: =$E16*O$4 -> 103.44284 | P16: =$E16*P$4 -> 106.54612 | Q16: =$E16*Q$4 -> 109.7425 | R16: =$E16*R$4 -> 113.03478 | S16: =$E16*S$4 -> 116.42582 | T16: =$E16*T$4 -> 119.9186 | U16: =$E16*U$4 -> 123.51616 | V16: =$E16*V$4 -> 127.22164 | ... AV16: =$E16*AV$4 -> 274.36508
A17: Metal | B17: R$/ton | E17: =I17*(1+$E$15)/INDEX(MacroEco!$55:$55,MATCH($I$15,MacroEco!$51:$51,0)) -> 1950.2877 | F17: R$/ton | I17: 1616 | J17: R$/ton | K17: CEMPRE | O17: =$E17*O$4 -> 2089.5453 | P17: =$E17*P$4 -> 2152.2316 | Q17: =$E17*Q$4 -> 2216.7986 | R17: =$E17*R$4 -> 2283.3025 | S17: =$E17*S$4 -> 2351.8016 | T17: =$E17*T$4 -> 2422.3557 | U17: =$E17*U$4 -> 2495.0263 | V17: =$E17*V$4 -> 2569.8771 | ... AV17: =$E17*AV$4 -> 5542.1746
A18: Receita | O18: =SUM(O19:O20) -> 4710.4288 | P18: =SUM(P19:P20) -> 4890.2048 | Q18: =SUM(Q19:Q20) -> 5075.7357 | R18: =SUM(R19:R20) -> 5268.8133 | S18: =SUM(S19:S20) -> 5469.748 | T18: =SUM(T19:T20) -> 5677.1311 | U18: =SUM(U19:U20) -> 5892.9261 | V18: =SUM(V19:V20) -> 6117.478 | ... AV18: =SUM(AV19:AV20) -> 16071.17
A19: Vidro | B19: k R$ | O19: =PRODUCT(O16,O11)*$E$14 -> 97.862094 | P19: =PRODUCT(P16,P11)*$E$14 -> 101.59705 | Q19: =PRODUCT(Q16,Q11)*$E$14 -> 105.45157 | R19: =PRODUCT(R16,R11)*$E$14 -> 109.46288 | S19: =PRODUCT(S16,S11)*$E$14 -> 113.63742 | T19: =PRODUCT(T16,T11)*$E$14 -> 117.94594 | U19: =PRODUCT(U16,U11)*$E$14 -> 122.42921 | V19: =PRODUCT(V16,V11)*$E$14 -> 127.09442 | ... AV19: =PRODUCT(AV16,AV11)*$E$14 -> 333.88858
A20: Metal | B20: k R$ | O20: =PRODUCT(O17,O12)*$E$14 -> 4612.5667 | P20: =PRODUCT(P17,P12)*$E$14 -> 4788.6078 | Q20: =PRODUCT(Q17,Q12)*$E$14 -> 4970.2841 | R20: =PRODUCT(R17,R12)*$E$14 -> 5159.3504 | S20: =PRODUCT(S17,S12)*$E$14 -> 5356.1106 | T20: =PRODUCT(T17,T12)*$E$14 -> 5559.1851 | U20: =PRODUCT(U17,U12)*$E$14 -> 5770.4969 | V20: =PRODUCT(V17,V12)*$E$14 -> 5990.3836 | ... AV20: =PRODUCT(AV17,AV12)*$E$14 -> 15737.282
A23: Biometano | O23: =SUM(O28) -> 4.7104288 | P23: =SUM(P28) -> 4.8902048 | Q23: =SUM(Q28) -> 5.0757357 | R23: =SUM(R28) -> 5.2688133 | S23: =SUM(S28) -> 5.469748 | T23: =SUM(T28) -> 5.6771311 | U23: =SUM(U28) -> 5.8929261 | V23: =SUM(V28) -> 6.117478 | ... AV23: =SUM(AV28) -> 16.07117
A24: Recicláveis valorizados | B24: ton/ano
A25: Vidro | B25: ton/ano | E25: 0.3 | O25: =OPERACIONAL!H$13*$E$11 -> 946.05 | P25: =OPERACIONAL!I$13*$E$11 -> 953.55 | Q25: =OPERACIONAL!J$13*$E$11 -> 960.9 | R25: =OPERACIONAL!K$13*$E$11 -> 968.4 | S25: =OPERACIONAL!L$13*$E$11 -> 976.05 | T25: =OPERACIONAL!M$13*$E$11 -> 983.55 | U25: =OPERACIONAL!N$13*$E$11 -> 991.2 | V25: =OPERACIONAL!O$13*$E$11 -> 999 | ... AV25: =OPERACIONAL!AO$13*$E$11 -> 1216.95
A26: Metal | B26: ton/ano | E26: 0.7 | O26: =OPERACIONAL!H$13*$E$12 -> 2207.45 | P26: =OPERACIONAL!I$13*$E$12 -> 2224.95 | Q26: =OPERACIONAL!J$13*$E$12 -> 2242.1 | R26: =OPERACIONAL!K$13*$E$12 -> 2259.6 | S26: =OPERACIONAL!L$13*$E$12 -> 2277.45 | T26: =OPERACIONAL!M$13*$E$12 -> 2294.95 | U26: =OPERACIONAL!N$13*$E$12 -> 2312.8 | V26: =OPERACIONAL!O$13*$E$12 -> 2331 | ... AV26: =OPERACIONAL!AO$13*$E$12 -> 2839.55
A28: Venda de Recicláveis | B28: R$/ton | E28: =1/1000 -> 0.001 | F28: K R$/MM R$ | O28: =$E28*O32 -> 4.7104288 | P28: =$E28*P32 -> 4.8902048 | Q28: =$E28*Q32 -> 5.0757357 | R28: =$E28*R32 -> 5.2688133 | S28: =$E28*S32 -> 5.469748 | T28: =$E28*T32 -> 5.6771311 | U28: =$E28*U32 -> 5.8929261 | V28: =$E28*V32 -> 6.117478 | ... AV28: =$E28*AV32 -> 16.07117
A29: Preços unitários | E29: ='LOTE 3'!$B$12 -> 0 | F29: sensibilidade preço recicláveis | I29: 44105
A30: Vidro | B30: R$/ton | E30: =I30*(1+$E$15)/INDEX(MacroEco!$55:$55,MATCH($I$15,MacroEco!$51:$51,0)) -> 96.548896 | F30: R$/ton | I30: 80 | J30: R$/ton | K30: CEMPRE | O30: =$E30*O$4 -> 103.44284 | P30: =$E30*P$4 -> 106.54612 | Q30: =$E30*Q$4 -> 109.7425 | R30: =$E30*R$4 -> 113.03478 | S30: =$E30*S$4 -> 116.42582 | T30: =$E30*T$4 -> 119.9186 | U30: =$E30*U$4 -> 123.51616 | V30: =$E30*V$4 -> 127.22164 | ... AV30: =$E30*AV$4 -> 274.36508
A31: Metal | B31: R$/ton | E31: =I31*(1+$E$15)/INDEX(MacroEco!$55:$55,MATCH($I$15,MacroEco!$51:$51,0)) -> 1950.2877 | F31: R$/ton | I31: 1616 | J31: R$/ton | K31: CEMPRE | O31: =$E31*O$4 -> 2089.5453 | P31: =$E31*P$4 -> 2152.2316 | Q31: =$E31*Q$4 -> 2216.7986 | R31: =$E31*R$4 -> 2283.3025 | S31: =$E31*S$4 -> 2351.8016 | T31: =$E31*T$4 -> 2422.3557 | U31: =$E31*U$4 -> 2495.0263 | V31: =$E31*V$4 -> 2569.8771 | ... AV31: =$E31*AV$4 -> 5542.1746
A32: Receita | O32: =SUM(O33:O34) -> 4710.4288 | P32: =SUM(P33:P34) -> 4890.2048 | Q32: =SUM(Q33:Q34) -> 5075.7357 | R32: =SUM(R33:R34) -> 5268.8133 | S32: =SUM(S33:S34) -> 5469.748 | T32: =SUM(T33:T34) -> 5677.1311 | U32: =SUM(U33:U34) -> 5892.9261 | V32: =SUM(V33:V34) -> 6117.478 | ... AV32: =SUM(AV33:AV34) -> 16071.17
A33: Vidro | B33: k R$ | O33: =PRODUCT(O30,O25)*$E$14 -> 97.862094 | P33: =PRODUCT(P30,P25)*$E$14 -> 101.59705 | Q33: =PRODUCT(Q30,Q25)*$E$14 -> 105.45157 | R33: =PRODUCT(R30,R25)*$E$14 -> 109.46288 | S33: =PRODUCT(S30,S25)*$E$14 -> 113.63742 | T33: =PRODUCT(T30,T25)*$E$14 -> 117.94594 | U33: =PRODUCT(U30,U25)*$E$14 -> 122.42921 | V33: =PRODUCT(V30,V25)*$E$14 -> 127.09442 | ... AV33: =PRODUCT(AV30,AV25)*$E$14 -> 333.88858
A34: Metal | B34: k R$ | O34: =PRODUCT(O31,O26)*$E$14 -> 4612.5667 | P34: =PRODUCT(P31,P26)*$E$14 -> 4788.6078 | Q34: =PRODUCT(Q31,Q26)*$E$14 -> 4970.2841 | R34: =PRODUCT(R31,R26)*$E$14 -> 5159.3504 | S34: =PRODUCT(S31,S26)*$E$14 -> 5356.1106 | T34: =PRODUCT(T31,T26)*$E$14 -> 5559.1851 | U34: =PRODUCT(U31,U26)*$E$14 -> 5770.4969 | V34: =PRODUCT(V31,V26)*$E$14 -> 5990.3836 | ... AV34: =PRODUCT(AV31,AV26)*$E$14 -> 15737.282
A37: Energia Elétrica | O37: =SUM(O42) -> 4.7104288 | P37: =SUM(P42) -> 4.8902048 | Q37: =SUM(Q42) -> 5.0757357 | R37: =SUM(R42) -> 5.2688133 | S37: =SUM(S42) -> 5.469748 | T37: =SUM(T42) -> 5.6771311 | U37: =SUM(U42) -> 5.8929261 | V37: =SUM(V42) -> 6.117478 | ... AV37: =SUM(AV42) -> 16.07117
A38: Recicláveis valorizados | B38: ton/ano
A39: Vidro | B39: ton/ano | E39: 0.3 | O39: =OPERACIONAL!H$13*$E$11 -> 946.05 | P39: =OPERACIONAL!I$13*$E$11 -> 953.55 | Q39: =OPERACIONAL!J$13*$E$11 -> 960.9 | R39: =OPERACIONAL!K$13*$E$11 -> 968.4 | S39: =OPERACIONAL!L$13*$E$11 -> 976.05 | T39: =OPERACIONAL!M$13*$E$11 -> 983.55 | U39: =OPERACIONAL!N$13*$E$11 -> 991.2 | V39: =OPERACIONAL!O$13*$E$11 -> 999 | ... AV39: =OPERACIONAL!AO$13*$E$11 -> 1216.95
A40: Metal | B40: ton/ano | E40: 0.7 | O40: =OPERACIONAL!H$13*$E$12 -> 2207.45 | P40: =OPERACIONAL!I$13*$E$12 -> 2224.95 | Q40: =OPERACIONAL!J$13*$E$12 -> 2242.1 | R40: =OPERACIONAL!K$13*$E$12 -> 2259.6 | S40: =OPERACIONAL!L$13*$E$12 -> 2277.45 | T40: =OPERACIONAL!M$13*$E$12 -> 2294.95 | U40: =OPERACIONAL!N$13*$E$12 -> 2312.8 | V40: =OPERACIONAL!O$13*$E$12 -> 2331 | ... AV40: =OPERACIONAL!AO$13*$E$12 -> 2839.55
A42: Venda de Recicláveis | B42: R$/ton | E42: =1/1000 -> 0.001 | F42: K R$/MM R$ | O42: =$E42*O46 -> 4.7104288 | P42: =$E42*P46 -> 4.8902048 | Q42: =$E42*Q46 -> 5.0757357 | R42: =$E42*R46 -> 5.2688133 | S42: =$E42*S46 -> 5.469748 | T42: =$E42*T46 -> 5.6771311 | U42: =$E42*U46 -> 5.8929261 | V42: =$E42*V46 -> 6.117478 | ... AV42: =$E42*AV46 -> 16.07117
A43: Preços unitários | E43: ='LOTE 3'!$B$12 -> 0 | F43: sensibilidade preço recicláveis | I43: 44105
A44: Vidro | B44: R$/ton | E44: =I44*(1+$E$15)/INDEX(MacroEco!$55:$55,MATCH($I$15,MacroEco!$51:$51,0)) -> 96.548896 | F44: R$/ton | I44: 80 | J44: R$/ton | K44: CEMPRE | O44: =$E44*O$4 -> 103.44284 | P44: =$E44*P$4 -> 106.54612 | Q44: =$E44*Q$4 -> 109.7425 | R44: =$E44*R$4 -> 113.03478 | S44: =$E44*S$4 -> 116.42582 | T44: =$E44*T$4 -> 119.9186 | U44: =$E44*U$4 -> 123.51616 | V44: =$E44*V$4 -> 127.22164 | ... AV44: =$E44*AV$4 -> 274.36508
A45: Metal | B45: R$/ton | E45: =I45*(1+$E$15)/INDEX(MacroEco!$55:$55,MATCH($I$15,MacroEco!$51:$51,0)) -> 1950.2877 | F45: R$/ton | I45: 1616 | J45: R$/ton | K45: CEMPRE | O45: =$E45*O$4 -> 2089.5453 | P45: =$E45*P$4 -> 2152.2316 | Q45: =$E45*Q$4 -> 2216.7986 | R45: =$E45*R$4 -> 2283.3025 | S45: =$E45*S$4 -> 2351.8016 | T45: =$E45*T$4 -> 2422.3557 | U45: =$E45*U$4 -> 2495.0263 | V45: =$E45*V$4 -> 2569.8771 | ... AV45: =$E45*AV$4 -> 5542.1746
A46: Receita | O46: =SUM(O47:O48) -> 4710.4288 | P46: =SUM(P47:P48) -> 4890.2048 | Q46: =SUM(Q47:Q48) -> 5075.7357 | R46: =SUM(R47:R48) -> 5268.8133 | S46: =SUM(S47:S48) -> 5469.748 | T46: =SUM(T47:T48) -> 5677.1311 | U46: =SUM(U47:U48) -> 5892.9261 | V46: =SUM(V47:V48) -> 6117.478 | ... AV46: =SUM(AV47:AV48) -> 16071.17
A47: Vidro | B47: k R$ | O47: =PRODUCT(O44,O39)*$E$14 -> 97.862094 | P47: =PRODUCT(P44,P39)*$E$14 -> 101.59705 | Q47: =PRODUCT(Q44,Q39)*$E$14 -> 105.45157 | R47: =PRODUCT(R44,R39)*$E$14 -> 109.46288 | S47: =PRODUCT(S44,S39)*$E$14 -> 113.63742 | T47: =PRODUCT(T44,T39)*$E$14 -> 117.94594 | U47: =PRODUCT(U44,U39)*$E$14 -> 122.42921 | V47: =PRODUCT(V44,V39)*$E$14 -> 127.09442 | ... AV47: =PRODUCT(AV44,AV39)*$E$14 -> 333.88858
A48: Metal | B48: k R$ | O48: =PRODUCT(O45,O40)*$E$14 -> 4612.5667 | P48: =PRODUCT(P45,P40)*$E$14 -> 4788.6078 | Q48: =PRODUCT(Q45,Q40)*$E$14 -> 4970.2841 | R48: =PRODUCT(R45,R40)*$E$14 -> 5159.3504 | S48: =PRODUCT(S45,S40)*$E$14 -> 5356.1106 | T48: =PRODUCT(T45,T40)*$E$14 -> 5559.1851 | U48: =PRODUCT(U45,U40)*$E$14 -> 5770.4969 | V48: =PRODUCT(V45,V40)*$E$14 -> 5990.3836 | ... AV48: =PRODUCT(AV45,AV40)*$E$14 -> 15737.282
A53: CO2 | O53: =SUM(O58) -> 4.7104288 | P53: =SUM(P58) -> 4.8902048 | Q53: =SUM(Q58) -> 5.0757357 | R53: =SUM(R58) -> 5.2688133 | S53: =SUM(S58) -> 5.469748 | T53: =SUM(T58) -> 5.6771311 | U53: =SUM(U58) -> 5.8929261 | V53: =SUM(V58) -> 6.117478 | ... AV53: =SUM(AV58) -> 16.07117
A54: Recicláveis valorizados | B54: ton/ano
A55: Vidro | B55: ton/ano | E55: 0.3 | O55: =OPERACIONAL!H$13*$E$11 -> 946.05 | P55: =OPERACIONAL!I$13*$E$11 -> 953.55 | Q55: =OPERACIONAL!J$13*$E$11 -> 960.9 | R55: =OPERACIONAL!K$13*$E$11 -> 968.4 | S55: =OPERACIONAL!L$13*$E$11 -> 976.05 | T55: =OPERACIONAL!M$13*$E$11 -> 983.55 | U55: =OPERACIONAL!N$13*$E$11 -> 991.2 | V55: =OPERACIONAL!O$13*$E$11 -> 999 | ... AV55: =OPERACIONAL!AO$13*$E$11 -> 1216.95
A56: Metal | B56: ton/ano | E56: 0.7 | O56: =OPERACIONAL!H$13*$E$12 -> 2207.45 | P56: =OPERACIONAL!I$13*$E$12 -> 2224.95 | Q56: =OPERACIONAL!J$13*$E$12 -> 2242.1 | R56: =OPERACIONAL!K$13*$E$12 -> 2259.6 | S56: =OPERACIONAL!L$13*$E$12 -> 2277.45 | T56: =OPERACIONAL!M$13*$E$12 -> 2294.95 | U56: =OPERACIONAL!N$13*$E$12 -> 2312.8 | V56: =OPERACIONAL!O$13*$E$12 -> 2331 | ... AV56: =OPERACIONAL!AO$13*$E$12 -> 2839.55
A58: Venda de Recicláveis | B58: R$/ton | E58: =1/1000 -> 0.001 | F58: K R$/MM R$ | O58: =$E58*O62 -> 4.7104288 | P58: =$E58*P62 -> 4.8902048 | Q58: =$E58*Q62 -> 5.0757357 | R58: =$E58*R62 -> 5.2688133 | S58: =$E58*S62 -> 5.469748 | T58: =$E58*T62 -> 5.6771311 | U58: =$E58*U62 -> 5.8929261 | V58: =$E58*V62 -> 6.117478 | ... AV58: =$E58*AV62 -> 16.07117
A59: Preços unitários | E59: ='LOTE 3'!$B$12 -> 0 | F59: sensibilidade preço recicláveis | I59: 44105
A60: Vidro | B60: R$/ton | E60: =I60*(1+$E$15)/INDEX(MacroEco!$55:$55,MATCH($I$15,MacroEco!$51:$51,0)) -> 96.548896 | F60: R$/ton | I60: 80 | J60: R$/ton | K60: CEMPRE | O60: =$E60*O$4 -> 103.44284 | P60: =$E60*P$4 -> 106.54612 | Q60: =$E60*Q$4 -> 109.7425 | R60: =$E60*R$4 -> 113.03478 | S60: =$E60*S$4 -> 116.42582 | T60: =$E60*T$4 -> 119.9186 | U60: =$E60*U$4 -> 123.51616 | V60: =$E60*V$4 -> 127.22164 | ... AV60: =$E60*AV$4 -> 274.36508
A61: Metal | B61: R$/ton | E61: =I61*(1+$E$15)/INDEX(MacroEco!$55:$55,MATCH($I$15,MacroEco!$51:$51,0)) -> 1950.2877 | F61: R$/ton | I61: 1616 | J61: R$/ton | K61: CEMPRE | O61: =$E61*O$4 -> 2089.5453 | P61: =$E61*P$4 -> 2152.2316 | Q61: =$E61*Q$4 -> 2216.7986 | R61: =$E61*R$4 -> 2283.3025 | S61: =$E61*S$4 -> 2351.8016 | T61: =$E61*T$4 -> 2422.3557 | U61: =$E61*U$4 -> 2495.0263 | V61: =$E61*V$4 -> 2569.8771 | ... AV61: =$E61*AV$4 -> 5542.1746
A62: Receita | O62: =SUM(O63:O64) -> 4710.4288 | P62: =SUM(P63:P64) -> 4890.2048 | Q62: =SUM(Q63:Q64) -> 5075.7357 | R62: =SUM(R63:R64) -> 5268.8133 | S62: =SUM(S63:S64) -> 5469.748 | T62: =SUM(T63:T64) -> 5677.1311 | U62: =SUM(U63:U64) -> 5892.9261 | V62: =SUM(V63:V64) -> 6117.478 | ... AV62: =SUM(AV63:AV64) -> 16071.17
A63: Vidro | B63: k R$ | O63: =PRODUCT(O60,O55)*$E$14 -> 97.862094 | P63: =PRODUCT(P60,P55)*$E$14 -> 101.59705 | Q63: =PRODUCT(Q60,Q55)*$E$14 -> 105.45157 | R63: =PRODUCT(R60,R55)*$E$14 -> 109.46288 | S63: =PRODUCT(S60,S55)*$E$14 -> 113.63742 | T63: =PRODUCT(T60,T55)*$E$14 -> 117.94594 | U63: =PRODUCT(U60,U55)*$E$14 -> 122.42921 | V63: =PRODUCT(V60,V55)*$E$14 -> 127.09442 | ... AV63: =PRODUCT(AV60,AV55)*$E$14 -> 333.88858
A64: Metal | B64: k R$ | O64: =PRODUCT(O61,O56)*$E$14 -> 4612.5667 | P64: =PRODUCT(P61,P56)*$E$14 -> 4788.6078 | Q64: =PRODUCT(Q61,Q56)*$E$14 -> 4970.2841 | R64: =PRODUCT(R61,R56)*$E$14 -> 5159.3504 | S64: =PRODUCT(S61,S56)*$E$14 -> 5356.1106 | T64: =PRODUCT(T61,T56)*$E$14 -> 5559.1851 | U64: =PRODUCT(U61,U56)*$E$14 -> 5770.4969 | V64: =PRODUCT(V61,V56)*$E$14 -> 5990.3836 | ... AV64: =PRODUCT(AV61,AV56)*$E$14 -> 15737.282
A69: CBIOS | O69: =SUM(O74) -> 4.7104288 | P69: =SUM(P74) -> 4.8902048 | Q69: =SUM(Q74) -> 5.0757357 | R69: =SUM(R74) -> 5.2688133 | S69: =SUM(S74) -> 5.469748 | T69: =SUM(T74) -> 5.6771311 | U69: =SUM(U74) -> 5.8929261 | V69: =SUM(V74) -> 6.117478 | ... AV69: =SUM(AV74) -> 16.07117
A70: Recicláveis valorizados | B70: ton/ano
A71: Vidro | B71: ton/ano | E71: 0.3 | O71: =OPERACIONAL!H$13*$E$11 -> 946.05 | P71: =OPERACIONAL!I$13*$E$11 -> 953.55 | Q71: =OPERACIONAL!J$13*$E$11 -> 960.9 | R71: =OPERACIONAL!K$13*$E$11 -> 968.4 | S71: =OPERACIONAL!L$13*$E$11 -> 976.05 | T71: =OPERACIONAL!M$13*$E$11 -> 983.55 | U71: =OPERACIONAL!N$13*$E$11 -> 991.2 | V71: =OPERACIONAL!O$13*$E$11 -> 999 | ... AV71: =OPERACIONAL!AO$13*$E$11 -> 1216.95
A72: Metal | B72: ton/ano | E72: 0.7 | O72: =OPERACIONAL!H$13*$E$12 -> 2207.45 | P72: =OPERACIONAL!I$13*$E$12 -> 2224.95 | Q72: =OPERACIONAL!J$13*$E$12 -> 2242.1 | R72: =OPERACIONAL!K$13*$E$12 -> 2259.6 | S72: =OPERACIONAL!L$13*$E$12 -> 2277.45 | T72: =OPERACIONAL!M$13*$E$12 -> 2294.95 | U72: =OPERACIONAL!N$13*$E$12 -> 2312.8 | V72: =OPERACIONAL!O$13*$E$12 -> 2331 | ... AV72: =OPERACIONAL!AO$13*$E$12 -> 2839.55
A74: Venda de Recicláveis | B74: R$/ton | E74: =1/1000 -> 0.001 | F74: K R$/MM R$ | O74: =$E74*O78 -> 4.7104288 | P74: =$E74*P78 -> 4.8902048 | Q74: =$E74*Q78 -> 5.0757357 | R74: =$E74*R78 -> 5.2688133 | S74: =$E74*S78 -> 5.469748 | T74: =$E74*T78 -> 5.6771311 | U74: =$E74*U78 -> 5.8929261 | V74: =$E74*V78 -> 6.117478 | ... AV74: =$E74*AV78 -> 16.07117
A75: Preços unitários | E75: ='LOTE 3'!$B$12 -> 0 | F75: sensibilidade preço recicláveis | I75: 44105
A76: Vidro | B76: R$/ton | E76: =I76*(1+$E$15)/INDEX(MacroEco!$55:$55,MATCH($I$15,MacroEco!$51:$51,0)) -> 96.548896 | F76: R$/ton | I76: 80 | J76: R$/ton | K76: CEMPRE | O76: =$E76*O$4 -> 103.44284 | P76: =$E76*P$4 -> 106.54612 | Q76: =$E76*Q$4 -> 109.7425 | R76: =$E76*R$4 -> 113.03478 | S76: =$E76*S$4 -> 116.42582 | T76: =$E76*T$4 -> 119.9186 | U76: =$E76*U$4 -> 123.51616 | V76: =$E76*V$4 -> 127.22164 | ... AV76: =$E76*AV$4 -> 274.36508
A77: Metal | B77: R$/ton | E77: =I77*(1+$E$15)/INDEX(MacroEco!$55:$55,MATCH($I$15,MacroEco!$51:$51,0)) -> 1950.2877 | F77: R$/ton | I77: 1616 | J77: R$/ton | K77: CEMPRE | O77: =$E77*O$4 -> 2089.5453 | P77: =$E77*P$4 -> 2152.2316 | Q77: =$E77*Q$4 -> 2216.7986 | R77: =$E77*R$4 -> 2283.3025 | S77: =$E77*S$4 -> 2351.8016 | T77: =$E77*T$4 -> 2422.3557 | U77: =$E77*U$4 -> 2495.0263 | V77: =$E77*V$4 -> 2569.8771 | ... AV77: =$E77*AV$4 -> 5542.1746
A78: Receita | O78: =SUM(O79:O80) -> 4710.4288 | P78: =SUM(P79:P80) -> 4890.2048 | Q78: =SUM(Q79:Q80) -> 5075.7357 | R78: =SUM(R79:R80) -> 5268.8133 | S78: =SUM(S79:S80) -> 5469.748 | T78: =SUM(T79:T80) -> 5677.1311 | U78: =SUM(U79:U80) -> 5892.9261 | V78: =SUM(V79:V80) -> 6117.478 | ... AV78: =SUM(AV79:AV80) -> 16071.17
A79: Vidro | B79: k R$ | O79: =PRODUCT(O76,O71)*$E$14 -> 97.862094 | P79: =PRODUCT(P76,P71)*$E$14 -> 101.59705 | Q79: =PRODUCT(Q76,Q71)*$E$14 -> 105.45157 | R79: =PRODUCT(R76,R71)*$E$14 -> 109.46288 | S79: =PRODUCT(S76,S71)*$E$14 -> 113.63742 | T79: =PRODUCT(T76,T71)*$E$14 -> 117.94594 | U79: =PRODUCT(U76,U71)*$E$14 -> 122.42921 | V79: =PRODUCT(V76,V71)*$E$14 -> 127.09442 | ... AV79: =PRODUCT(AV76,AV71)*$E$14 -> 333.88858
A80: Metal | B80: k R$ | O80: =PRODUCT(O77,O72)*$E$14 -> 4612.5667 | P80: =PRODUCT(P77,P72)*$E$14 -> 4788.6078 | Q80: =PRODUCT(Q77,Q72)*$E$14 -> 4970.2841 | R80: =PRODUCT(R77,R72)*$E$14 -> 5159.3504 | S80: =PRODUCT(S77,S72)*$E$14 -> 5356.1106 | T80: =PRODUCT(T77,T72)*$E$14 -> 5559.1851 | U80: =PRODUCT(U77,U72)*$E$14 -> 5770.4969 | V80: =PRODUCT(V77,V72)*$E$14 -> 5990.3836 | ... AV80: =PRODUCT(AV77,AV72)*$E$14 -> 15737.282

Sheet Receita CP
B1: Unid | C1: Fonte | E1: Fator 1 | F1: Unid fator 1 | G1: Fonte Fator 1 | O1: =YEAR(Premissas!$D$13) -> 2025 | P1: =O1+1 -> 2026 | Q1: =P1+1 -> 2027 | R1: =Q1+1 -> 2028 | S1: =R1+1 -> 2029 | T1: =S1+1 -> 2030 | U1: =T1+1 -> 2031 | V1: =U1+1 -> 2032 | W1: =V1+1 -> 2033 | ... AW1: =AV1+1 -> 2059
A2: Premissas
A3: Geral
A4: =MacroEco!A$8 -> Índice de inflação brasileira (IPCA) | B4: =MacroEco!B$8 -> 44985 | E4: =Premissas!D$8 -> 1 | F4: [1: Nominais; 2: Reais] | O4: =MacroEco!AA$8 -> 1.0714036 | P4: =MacroEco!AB$8 -> 1.1035457 | Q4: =MacroEco!AC$8 -> 1.1366521 | R4: =MacroEco!AD$8 -> 1.1707517 | S4: =MacroEco!AE$8 -> 1.2058742 | T4: =MacroEco!AF$8 -> 1.2420504 | U4: =MacroEco!AG$8 -> 1.2793119 | V4: =MacroEco!AH$8 -> 1.3176913 | ... AW4: =MacroEco!BI$8 -> 2.9269732
A5: Meses em um ano | O5: 12 | P5: 12 | Q5: 12 | R5: 12 | S5: 12 | T5: 12 | U5: 12 | V5: 12 | W5: 12 | X5: 12 | Y5: 12 | Z5: 12 | AA5: 12 | AB5: 12 | AC5: 12 | AD5: 12 | AE5: 12 | AF5: 12 | AG5: 12 | AH5: 12 | AI5: 12 | AJ5: 12 | AK5: 12 | AL5: 12 | AM5: 12 | AN5: 12 | AO5: 12 | AP5: 12 | AQ5: 12 | AR5: 12 | AS5: 12 | AT5: 12 | AU5: 12 | AV5: 12 | AW5: 12
A7: Contraprestação anual | B7: MM R$/ano | E7: 114 | F7: R$/ton | O7: =SUM(O8,O12) -> 7190413.3 | P7: =SUM(P8,P12) -> 7247429.9 | Q7: =SUM(Q8,Q12) -> 7303306.9 | R7: =SUM(R8,R12) -> 7360324.7 | S7: =SUM(S8,S12) -> 7418483.2 | T7: =SUM(T8,T12) -> 7475502.2 | U7: =SUM(U8,U12) -> 7533662.1 | V7: =SUM(V8,V12) -> 7592962.7 | ... AW7: =SUM(AW8,AW12) -> 9318754
A8: Parcela fixa - Parcela A | B8: MM R$/ano | O8: =O9 -> 7189980 | P8: =P9 -> 7246980 | Q8: =Q9 -> 7302840 | R8: =R9 -> 7359840 | S8: =S9 -> 7417980 | T8: =T9 -> 7474980 | U8: =U9 -> 7533120 | V8: =V9 -> 7592400 | ... AW8: =AW9 -> 9317220
A9: Parcela fixa | B9: MM R$/ano | O9: =O15*$E$7 -> 7189980 | P9: =P15*$E$7 -> 7246980 | Q9: =Q15*$E$7 -> 7302840 | R9: =R15*$E$7 -> 7359840 | S9: =S15*$E$7 -> 7417980 | T9: =T15*$E$7 -> 7474980 | U9: =U15*$E$7 -> 7533120 | V9: =V15*$E$7 -> 7592400 | ... AW9: =AW15*$E$7 -> 9317220
A10: % parcela A | O10: =O8/O$7 -> 0.99993974 | P10: =P8/P$7 -> 0.99993793 | Q10: =Q8/Q$7 -> 0.99993607 | R10: =R8/R$7 -> 0.99993415 | S10: =S8/S$7 -> 0.99993217 | T10: =T8/T$7 -> 0.99993014 | U10: =U8/U$7 -> 0.99992804 | V10: =V8/V$7 -> 0.99992589 | ... AW10: =AW8/AW$7 -> 0.99983538
A12: Parcelas Variáveis | B12: MM R$/ano | E12: 0.0075 | F12: K R$/MM R$ | O12: =SUM(O13) -> 433.31459 | P12: =SUM(P13) -> 449.85227 | Q12: =SUM(Q13) -> 466.91935 | R12: =SUM(R13) -> 484.68065 | S12: =SUM(S13) -> 503.16473 | T12: =SUM(T13) -> 522.24199 | U12: =SUM(U13) -> 542.09308 | V12: =SUM(V13) -> 562.74972 | ... AW12: =SUM(AW13) -> 1534.008
A13: Parcela B - Volume | O13: =O14*O15*$E12^2 -> 433.31459 | P13: =P14*P15*$E12^2 -> 449.85227 | Q13: =Q14*Q15*$E12^2 -> 466.91935 | R13: =R14*R15*$E12^2 -> 484.68065 | S13: =S14*S15*$E12^2 -> 503.16473 | T13: =T14*T15*$E12^2 -> 522.24199 | U13: =U14*U15*$E12^2 -> 542.09308 | V13: =V14*V15*$E12^2 -> 562.74972 | ... AW13: =AW14*AW15*$E12^2 -> 1534.008
A14: CP unitário RSU corrigido | B14: R$/ton | E14: 114 | F14: R$/ton | G14: 0 | H14: R$/ton | I14: Fonte: Cotações de destinação final disponibilizadas pela Prefeitura | O14: =MAX($E14,$G$14)*O$4 -> 122.14001 | P14: =MAX($E14,$G$14)*P$4 -> 125.80421 | Q14: =MAX($E14,$G$14)*Q$4 -> 129.57834 | R14: =MAX($E14,$G$14)*R$4 -> 133.46569 | S14: =MAX($E14,$G$14)*S$4 -> 137.46966 | T14: =MAX($E14,$G$14)*T$4 -> 141.59375 | U14: =MAX($E14,$G$14)*U$4 -> 145.84156 | V14: =MAX($E14,$G$14)*V$4 -> 150.21681 | ... AW14: =MAX($E14,$G$14)*AW$4 -> 333.67494
A15: Toneladas de RSU recebidos | B15: ton/ano | O15: =SUM(OPERACIONAL!H7) -> 63070 | P15: =SUM(OPERACIONAL!I7) -> 63570 | Q15: =SUM(OPERACIONAL!J7) -> 64060 | R15: =SUM(OPERACIONAL!K7) -> 64560 | S15: =SUM(OPERACIONAL!L7) -> 65070 | T15: =SUM(OPERACIONAL!M7) -> 65570 | U15: =SUM(OPERACIONAL!N7) -> 66080 | V15: =SUM(OPERACIONAL!O7) -> 66600 | ... AW15: =SUM(OPERACIONAL!AP7) -> 81730

Sheet Capex
B1: Unidade | N1: =O1-1 -> 2025 | O1: 2026 | P1: =O1+1 -> 2027 | Q1: =P1+1 -> 2028 | R1: =Q1+1 -> 2029 | S1: =R1+1 -> 2030 | T1: =S1+1 -> 2031 | U1: =T1+1 -> 2032 | V1: =U1+1 -> 2033 | W1: =V1+1 -> 2034 | ... AW1: =AV1+1 -> 2060
O2: 1 | P2: =O2+1 -> 2 | Q2: =P2+1 -> 3 | R2: =Q2+1 -> 4 | S2: =R2+1 -> 5 | T2: =S2+1 -> 6 | U2: =T2+1 -> 7 | V2: =U2+1 -> 8 | W2: =V2+1 -> 9 | ... AW2: =AV2+1 -> 35
A3: MACRO-ECONÔMICOS
A4: Índice de inflação brasileira (IPCA) | B4: =MacroEco!B8 -> 44985 | D4: =Premissas!D$8 -> 1 | E4: =Premissas!E8 -> [1: Nominais; 2: Reais] | I4: =SUM(I8,I13,I18) -> 11079653 | O4: =MacroEco!AA8 -> 1.0714036 | P4: =MacroEco!AB8 -> 1.1035457 | Q4: =MacroEco!AC8 -> 1.1366521 | R4: =MacroEco!AD8 -> 1.1707517 | S4: =MacroEco!AE8 -> 1.2058742 | T4: =MacroEco!AF8 -> 1.2420504 | U4: =MacroEco!AG8 -> 1.2793119 | V4: =MacroEco!AH8 -> 1.3176913 | ... AW4: =MacroEco!BI8 -> 2.9269732
A6: CAPEX | B6: K R$ | F6: =SUM(O6:AR6) -> 0 | I6: 0.05
A8: =CAPEX_Input!C4 -> URE MARÍLIA - BIO+GÁS | I8: =SUM(O8:AR8) -> 5505675.3 | O8: =SUM(O9:O11) -> 5505675.3 | P8: =SUM(P9:P11) -> 0 | Q8: =SUM(Q9:Q11) -> 0 | R8: =SUM(R9:R11) -> 0 | S8: =SUM(S9:S11) -> 0 | T8: =SUM(T9:T11) -> 0 | U8: =SUM(U9:U11) -> 0 | V8: =SUM(V9:V11) -> 0 | ... AW8: =SUM(AW9:AW11) -> 0
A9: =CAPEX_Input!C6 -> Custos pré-operacionais | H9: 1 | I9: =SUM(O9:AR9) -> 48213.162 | O9: =O28*$I$6 -> 48213.162 | P9: =P28*$I$6 -> 0 | Q9: =Q28*$I$6 -> 0 | R9: =R28*$I$6 -> 0 | S9: =S28*$I$6 -> 0 | T9: =T28*$I$6 -> 0 | U9: =U28*$I$6 -> 0 | V9: =V28*$I$6 -> 0 | ... AW9: =AW28*$I$6 -> 0
A10: =CAPEX_Input!C7 -> Licenciamento (estudos, projetos e licenças) | H10: 2 | I10: =SUM(O10:AR10) -> 20088.818 | O10: =O31*$I$6 -> 20088.818 | P10: =P31*$I$6 -> 0 | Q10: =Q31*$I$6 -> 0 | R10: =R31*$I$6 -> 0 | S10: =S31*$I$6 -> 0 | T10: =T31*$I$6 -> 0 | U10: =U31*$I$6 -> 0 | V10: =V31*$I$6 -> 0 | ... AW10: =AW31*$I$6 -> 0
A11: =CAPEX_Input!C8 -> Equipamentos | H11: 3 | I11: =SUM(O11:AR11) -> 5437373.3 | O11: =O34*$I$6 -> 5437373.3 | P11: =P30*$I$6 -> 0 | Q11: =Q30*$I$6 -> 0 | R11: =R30*$I$6 -> 0 | S11: =S30*$I$6 -> 0 | T11: =T30*$I$6 -> 0 | U11: =U30*$I$6 -> 0 | V11: =V30*$I$6 -> 0 | W11: =W30*$I$6 -> 0 | ... AW11: =AW30*$I$6 -> 0
A13: =CAPEX_Input!C9 -> URE MARÍLIA - BIO | I13: =SUM(O13:AR13) -> 2559315.4 | O13: =SUM(O14:O16) -> 2559315.4 | P13: =SUM(P14:P16) -> 0 | Q13: =SUM(Q14:Q16) -> 0 | R13: =SUM(R14:R16) -> 0 | S13: =SUM(S14:S16) -> 0 | T13: =SUM(T14:T16) -> 0 | U13: =SUM(U14:U16) -> 0 | V13: =SUM(V14:V16) -> 0 | ... AW13: =SUM(AW14:AW16) -> 0
A14: =CAPEX_Input!C11 -> Custos pré-operacionais | H14: 1 | I14: =SUM(O14:AR14) -> 48213.162 | O14: =O39*$I$6 -> 48213.162 | P14: =P39*$I$6 -> 0 | Q14: =Q39*$I$6 -> 0 | R14: =R39*$I$6 -> 0 | S14: =S39*$I$6 -> 0 | T14: =T39*$I$6 -> 0 | U14: =U39*$I$6 -> 0 | V14: =V39*$I$6 -> 0 | ... AW14: =AW39*$I$6 -> 0
A15: =CAPEX_Input!C12 -> Licenciamento (estudos, projetos e licenças) | H15: 2 | I15: =SUM(O15:AR15) -> 20088.818 | O15: =O42*$I$6 -> 20088.818 | P15: =P42*$I$6 -> 0 | Q15: =Q42*$I$6 -> 0 | R15: =R42*$I$6 -> 0 | S15: =S42*$I$6 -> 0 | T15: =T42*$I$6 -> 0 | U15: =U42*$I$6 -> 0 | V15: =V42*$I$6 -> 0 | ... AW15: =AW42*$I$6 -> 0
A16: =CAPEX_Input!C13 -> Equipamentos | H16: 3 | I16: =SUM(O16:AR16) -> 2491013.4 | O16: =O45*$I$6 -> 2491013.4 | P16: =P45*$I$6 -> 0 | Q16: =Q41*$I$6 -> 0 | R16: =R41*$I$6 -> 0 | S16: =S41*$I$6 -> 0 | T16: =T41*$I$6 -> 0 | U16: =U41*$I$6 -> 0 | V16: =V41*$I$6 -> 0 | W16: =W41*$I$6 -> 0 | X16: =X41*$I$6 -> 0 | ... AW16: =AW41*$I$6 -> 0
A18: =CAPEX_Input!C14 -> URE MARÍLIA - GÁS | I18: =SUM(O18:AR18) -> 3014661.9 | O18: =SUM(O19:O21) -> 3014661.9 | P18: =SUM(P19:P21) -> 0 | Q18: =SUM(Q19:Q21) -> 0 | R18: =SUM(R19:R21) -> 0 | S18: =SUM(S19:S21) -> 0 | T18: =SUM(T19:T21) -> 0 | U18: =SUM(U19:U21) -> 0 | V18: =SUM(V19:V21) -> 0 | ... AW18: =SUM(AW19:AW21) -> 0
A19: =CAPEX_Input!C16 -> Custos pré-operacionais | H19: 1 | I19: =SUM(O19:AR19) -> 48213.162 | O19: =O50*$I$6 -> 48213.162 | P19: =P50*$I$6 -> 0 | Q19: =Q50*$I$6 -> 0 | R19: =R50*$I$6 -> 0 | S19: =S50*$I$6 -> 0 | T19: =T50*$I$6 -> 0 | U19: =U50*$I$6 -> 0 | V19: =V50*$I$6 -> 0 | ... AW19: =AW50*$I$6 -> 0
A20: =CAPEX_Input!C17 -> Licenciamento (estudos, projetos e licenças) | H20: 2 | I20: =SUM(O20:AR20) -> 20088.818 | O20: =O53*$I$6 -> 20088.818 | P20: =P53*$I$6 -> 0 | Q20: =Q53*$I$6 -> 0 | R20: =R53*$I$6 -> 0 | S20: =S53*$I$6 -> 0 | T20: =T53*$I$6 -> 0 | U20: =U53*$I$6 -> 0 | V20: =V53*$I$6 -> 0 | ... AW20: =AW53*$I$6 -> 0
A21: =CAPEX_Input!C18 -> Equipamentos | H21: 3 | I21: =SUM(O21:AR21) -> 2946359.9 | O21: =O56*$I$6 -> 2946359.9 | P21: =P52*$I$6 -> 0 | Q21: =Q52*$I$6 -> 0 | R21: =R52*$I$6 -> 0 | S21: =S52*$I$6 -> 0 | T21: =T52*$I$6 -> 0 | U21: =U52*$I$6 -> 0 | V21: =V52*$I$6 -> 0 | W21: =W52*$I$6 -> 0 | ... AW21: =AW52*$I$6 -> 0
A24: Desembolso | I24: =SUM(I26,I37,I48) -> 2.2159305e+08 | O24: =SUM(O26,O37,O48) -> 2.2159305e+08
D25: ='LOTE 3'!$B$18 -> 1 | E25: Sensibilidade CAPEX
A26: =A8 -> URE MARÍLIA - BIO+GÁS | I26: =SUM(O26:AR26) -> 1.1011351e+08 | O26: =SUM(O28,O31,O34) -> 1.1011351e+08 | P26: =SUM(P28,P31,P34) -> 0 | Q26: =SUM(Q28,Q31,Q34) -> 0 | R26: =SUM(R28,R31,R34) -> 0 | S26: =SUM(S28,S31,S34) -> 0 | T26: =SUM(T28,T31,T34) -> 0 | U26: =SUM(U28,U31,U34) -> 0 | V26: =SUM(V28,V31,V34) -> 0 | ... AW26: =SUM(AW28,AW31,AW34) -> 0
A28: =A29 -> Custos pré-operacionais | I28: =SUM(O28:AR28) -> 964263.25 | O28: =SUM(O29:O29) -> 964263.25 | P28: =SUM(P29:P29) -> 0 | Q28: =SUM(Q29:Q29) -> 0 | R28: =SUM(R29:R29) -> 0 | S28: =SUM(S29:S29) -> 0 | T28: =SUM(T29:T29) -> 0 | U28: =SUM(U29:U29) -> 0 | V28: =SUM(V29:V29) -> 0 | ... AW28: =SUM(AW29:AW29) -> 0
A29: =CAPEX_Input!C6 -> Custos pré-operacionais | B29: =CAPEX_Input!B6 -> 01.01.01 | I29: =SUM(O29:AR29) -> 964263.25 | O29: =IFERROR(INDEX(CAPEX_Input!$G:$G,MATCH($B29,CAPEX_Input!$B:$B,0),MATCH(O$2,CAPEX_Input!$G$2:$G$2,0)),0)*O$4*$D$25 -> 964263.25 | P29: =IFERROR(INDEX(CAPEX_Input!$G:$G,MATCH($B29,CAPEX_Input!$B:$B,0),MATCH(P$2,CAPEX_Input!$G$2:$G$2,0)),0)*P$4*$D$25 -> 0 | Q29: =IFERROR(INDEX(CAPEX_Input!$G:$G,MATCH($B29,CAPEX_Input!$B:$B,0),MATCH(Q$2,CAPEX_Input!$G$2:$G$2,0)),0)*Q$4*$D$25 -> 0 | R29: =IFERROR(INDEX(CAPEX_Input!$G:$G,MATCH($B29,CAPEX_Input!$B:$B,0),MATCH(R$2,CAPEX_Input!$G$2:$G$2,0)),0)*R$4*$D$25 -> 0 | S29: =IFERROR(INDEX(CAPEX_Input!$G:$G,MATCH($B29,CAPEX_Input!$B:$B,0),MATCH(S$2,CAPEX_Input!$G$2:$G$2,0)),0)*S$4*$D$25 -> 0 | T29: =IFERROR(INDEX(CAPEX_Input!$G:$G,MATCH($B29,CAPEX_Input!$B:$B,0),MATCH(T$2,CAPEX_Input!$G$2:$G$2,0)),0)*T$4*$D$25 -> 0 | U29: =IFERROR(INDEX(CAPEX_Input!$G:$G,MATCH($B29,CAPEX_Input!$B:$B,0),MATCH(U$2,CAPEX_Input!$G$2:$G$2,0)),0)*U$4*$D$25 -> 0 | V29: =IFERROR(INDEX(CAPEX_Input!$G:$G,MATCH($B29,CAPEX_Input!$B:$B,0),MATCH(V$2,CAPEX_Input!$G$2:$G$2,0)),0)*V$4*$D$25 -> 0 | ... AW29: =IFERROR(INDEX(CAPEX_Input!$G:$G,MATCH($B29,CAPEX_Input!$B:$B,0),MATCH(AW$2,CAPEX_Input!$G$2:$G$2,0)),0)*AW$4*$D$25 -> 0
A31: =A32 -> Licenciamento (estudos, projetos e licenças) | I31: =SUM(O31:AR31) -> 401776.35 | O31: =SUBTOTAL(9,O32:O32) -> 401776.35 | P31: =SUBTOTAL(9,P32:P32) -> 0 | Q31: =SUBTOTAL(9,Q32:Q32) -> 0 | R31: =SUBTOTAL(9,R32:R32) -> 0 | S31: =SUBTOTAL(9,S32:S32) -> 0 | T31: =SUBTOTAL(9,T32:T32) -> 0 | U31: =SUBTOTAL(9,U32:U32) -> 0 | V31: =SUBTOTAL(9,V32:V32) -> 0 | ... AW31: =SUBTOTAL(9,AW32:AW32) -> 0
A32: =CAPEX_Input!C7 -> Licenciamento (estudos, projetos e licenças) | B32: =CAPEX_Input!B7 -> 01.01.02 | I32: =SUM(O32:AR32) -> 401776.35 | O32: =IFERROR(INDEX(CAPEX_Input!$G:$G,MATCH($B32,CAPEX_Input!$B:$B,0),MATCH(O$2,CAPEX_Input!$G$2:$G$2,0)),0)*O$4*$D$25 -> 401776.35 | P32: =IFERROR(INDEX(CAPEX_Input!$G:$G,MATCH($B32,CAPEX_Input!$B:$B,0),MATCH(P$2,CAPEX_Input!$G$2:$G$2,0)),0)*P$4*$D$25 -> 0 | Q32: =IFERROR(INDEX(CAPEX_Input!$G:$G,MATCH($B32,CAPEX_Input!$B:$B,0),MATCH(Q$2,CAPEX_Input!$G$2:$G$2,0)),0)*Q$4*$D$25 -> 0 | R32: =IFERROR(INDEX(CAPEX_Input!$G:$G,MATCH($B32,CAPEX_Input!$B:$B,0),MATCH(R$2,CAPEX_Input!$G$2:$G$2,0)),0)*R$4*$D$25 -> 0 | S32: =IFERROR(INDEX(CAPEX_Input!$G:$G,MATCH($B32,CAPEX_Input!$B:$B,0),MATCH(S$2,CAPEX_Input!$G$2:$G$2,0)),0)*S$4*$D$25 -> 0 | T32: =IFERROR(INDEX(CAPEX_Input!$G:$G,MATCH($B32,CAPEX_Input!$B:$B,0),MATCH(T$2,CAPEX_Input!$G$2:$G$2,0)),0)*T$4*$D$25 -> 0 | U32: =IFERROR(INDEX(CAPEX_Input!$G:$G,MATCH($B32,CAPEX_Input!$B:$B,0),MATCH(U$2,CAPEX_Input!$G$2:$G$2,0)),0)*U$4*$D$25 -> 0 | V32: =IFERROR(INDEX(CAPEX_Input!$G:$G,MATCH($B32,CAPEX_Input!$B:$B,0),MATCH(V$2,CAPEX_Input!$G$2:$G$2,0)),0)*V$4*$D$25 -> 0 | ... AW32: =IFERROR(INDEX(CAPEX_Input!$G:$G,MATCH($B32,CAPEX_Input!$B:$B,0),MATCH(AW$2,CAPEX_Input!$G$2:$G$2,0)),0)*AW$4*$D$25 -> 0
A34: =A35 -> Equipamentos | I34: =SUM(O34:AR34) -> 1.0874747e+08 | O34: =SUBTOTAL(9,O35:O35) -> 1.0874747e+08 | P34: =SUBTOTAL(9,P35:P35) -> 0 | Q34: =SUBTOTAL(9,Q35:Q35) -> 0 | R34: =SUBTOTAL(9,R35:R35) -> 0 | S34: =SUBTOTAL(9,S35:S35) -> 0 | T34: =SUBTOTAL(9,T35:T35) -> 0 | U34: =SUBTOTAL(9,U35:U35) -> 0 | V34: =SUBTOTAL(9,V35:V35) -> 0 | ... AW34: =SUBTOTAL(9,AW35:AW35) -> 0
A35: =CAPEX_Input!C8 -> Equipamentos | B35: 01.01.03 | I35: =SUM(O35:AR35) -> 1.0874747e+08 | O35: =IFERROR(INDEX(CAPEX_Input!$G:$G,MATCH($B35,CAPEX_Input!$B:$B,0),MATCH(O$2,CAPEX_Input!$G$2:$G$2,0)),0)*O$4*$D$25 -> 1.0874747e+08 | P35: =IFERROR(INDEX(CAPEX_Input!$G:$G,MATCH($B35,CAPEX_Input!$B:$B,0),MATCH(P$2,CAPEX_Input!$G$2:$G$2,0)),0)*P$4*$D$25 -> 0 | Q35: =IFERROR(INDEX(CAPEX_Input!$G:$G,MATCH($B35,CAPEX_Input!$B:$B,0),MATCH(Q$2,CAPEX_Input!$G$2:$G$2,0)),0)*Q$4*$D$25 -> 0 | R35: =IFERROR(INDEX(CAPEX_Input!$G:$G,MATCH($B35,CAPEX_Input!$B:$B,0),MATCH(R$2,CAPEX_Input!$G$2:$G$2,0)),0)*R$4*$D$25 -> 0 | S35: =IFERROR(INDEX(CAPEX_Input!$G:$G,MATCH($B35,CAPEX_Input!$B:$B,0),MATCH(S$2,CAPEX_Input!$G$2:$G$2,0)),0)*S$4*$D$25 -> 0 | T35: =IFERROR(INDEX(CAPEX_Input!$G:$G,MATCH($B35,CAPEX_Input!$B:$B,0),MATCH(T$2,CAPEX_Input!$G$2:$G$2,0)),0)*T$4*$D$25 -> 0 | U35: =IFERROR(INDEX(CAPEX_Input!$G:$G,MATCH($B35,CAPEX_Input!$B:$B,0),MATCH(U$2,CAPEX_Input!$G$2:$G$2,0)),0)*U$4*$D$25 -> 0 | V35: =IFERROR(INDEX(CAPEX_Input!$G:$G,MATCH($B35,CAPEX_Input!$B:$B,0),MATCH(V$2,CAPEX_Input!$G$2:$G$2,0)),0)*V$4*$D$25 -> 0 | ... AW35: =IFERROR(INDEX(CAPEX_Input!$G:$G,MATCH($B35,CAPEX_Input!$B:$B,0),MATCH(AW$2,CAPEX_Input!$G$2:$G$2,0)),0)*AW$4*$D$25 -> 0
A37: =A13 -> URE MARÍLIA - BIO | I37: =SUM(O37:AR37) -> 51186308 | O37: =SUM(O39,O42,O45) -> 51186308 | P37: =SUM(P39,P42,P45) -> 0 | Q37: =SUM(Q39,Q42,Q45) -> 0 | R37: =SUM(R39,R42,R45) -> 0 | S37: =SUM(S39,S42,S45) -> 0 | T37: =SUM(T39,T42,T45) -> 0 | U37: =SUM(U39,U42,U45) -> 0 | V37: =SUM(V39,V42,V45) -> 0 | ... AW37: =SUM(AW39,AW42,AW45) -> 0
A39: =A40 -> Custos pré-operacionais | I39: =SUM(O39:AR39) -> 964263.25 | O39: =SUM(O40:O40) -> 964263.25 | P39: =SUM(P40:P40) -> 0 | Q39: =SUM(Q40:Q40) -> 0 | R39: =SUM(R40:R40) -> 0 | S39: =SUM(S40:S40) -> 0 | T39: =SUM(T40:T40) -> 0 | U39: =SUM(U40:U40) -> 0 | V39: =SUM(V40:V40) -> 0 | ... AW39: =SUM(AW40:AW40) -> 0
A40: =CAPEX_Input!C11 -> Custos pré-operacionais | B40: =CAPEX_Input!B11 -> 02.01.01 | I40: =SUM(O40:AR40) -> 964263.25 | O40: =IFERROR(INDEX(CAPEX_Input!$G:$G,MATCH($B40,CAPEX_Input!$B:$B,0),MATCH(O$2,CAPEX_Input!$G$2:$G$2,0)),0)*O$4*$D$25 -> 964263.25 | P40: =IFERROR(INDEX(CAPEX_Input!$G:$G,MATCH($B40,CAPEX_Input!$B:$B,0),MATCH(P$2,CAPEX_Input!$G$2:$G$2,0)),0)*P$4*$D$25 -> 0 | Q40: =IFERROR(INDEX(CAPEX_Input!$G:$G,MATCH($B40,CAPEX_Input!$B:$B,0),MATCH(Q$2,CAPEX_Input!$G$2:$G$2,0)),0)*Q$4*$D$25 -> 0 | R40: =IFERROR(INDEX(CAPEX_Input!$G:$G,MATCH($B40,CAPEX_Input!$B:$B,0),MATCH(R$2,CAPEX_Input!$G$2:$G$2,0)),0)*R$4*$D$25 -> 0 | S40: =IFERROR(INDEX(CAPEX_Input!$G:$G,MATCH($B40,CAPEX_Input!$B:$B,0),MATCH(S$2,CAPEX_Input!$G$2:$G$2,0)),0)*S$4*$D$25 -> 0 | T40: =IFERROR(INDEX(CAPEX_Input!$G:$G,MATCH($B40,CAPEX_Input!$B:$B,0),MATCH(T$2,CAPEX_Input!$G$2:$G$2,0)),0)*T$4*$D$25 -> 0 | U40: =IFERROR(INDEX(CAPEX_Input!$G:$G,MATCH($B40,CAPEX_Input!$B:$B,0),MATCH(U$2,CAPEX_Input!$G$2:$G$2,0)),0)*U$4*$D$25 -> 0 | V40: =IFERROR(INDEX(CAPEX_Input!$G:$G,MATCH($B40,CAPEX_Input!$B:$B,0),MATCH(V$2,CAPEX_Input!$G$2:$G$2,0)),0)*V$4*$D$25 -> 0 | ... AW40: =IFERROR(INDEX(CAPEX_Input!$G:$G,MATCH($B40,CAPEX_Input!$B:$B,0),MATCH(AW$2,CAPEX_Input!$G$2:$G$2,0)),0)*AW$4*$D$25 -> 0
A42: =A43 -> Licenciamento (estudos, projetos e licenças) | I42: =SUM(O42:AR42) -> 401776.35 | O42: =SUM(O43:O43) -> 401776.35 | P42: =SUM(P43:P43) -> 0 | Q42: =SUM(Q43:Q43) -> 0 | R42: =SUM(R43:R43) -> 0 | S42: =SUM(S43:S43) -> 0 | T42: =SUM(T43:T43) -> 0 | U42: =SUM(U43:U43) -> 0 | V42: =SUM(V43:V43) -> 0 | ... AW42: =SUM(AW43:AW43) -> 0
A43: =CAPEX_Input!C12 -> Licenciamento (estudos, projetos e licenças) | B43: 02.01.02 | I43: =SUM(O43:AR43) -> 401776.35 | O43: =IFERROR(INDEX(CAPEX_Input!$G:$G,MATCH($B43,CAPEX_Input!$B:$B,0),MATCH(O$2,CAPEX_Input!$G$2:$G$2,0)),0)*O$4*$D$25 -> 401776.35 | P43: =IFERROR(INDEX(CAPEX_Input!$G:$G,MATCH($B43,CAPEX_Input!$B:$B,0),MATCH(P$2,CAPEX_Input!$G$2:$G$2,0)),0)*P$4*$D$25 -> 0 | Q43: =IFERROR(INDEX(CAPEX_Input!$G:$G,MATCH($B43,CAPEX_Input!$B:$B,0),MATCH(Q$2,CAPEX_Input!$G$2:$G$2,0)),0)*Q$4*$D$25 -> 0 | R43: =IFERROR(INDEX(CAPEX_Input!$G:$G,MATCH($B43,CAPEX_Input!$B:$B,0),MATCH(R$2,CAPEX_Input!$G$2:$G$2,0)),0)*R$4*$D$25 -> 0 | S43: =IFERROR(INDEX(CAPEX_Input!$G:$G,MATCH($B43,CAPEX_Input!$B:$B,0),MATCH(S$2,CAPEX_Input!$G$2:$G$2,0)),0)*S$4*$D$25 -> 0 | T43: =IFERROR(INDEX(CAPEX_Input!$G:$G,MATCH($B43,CAPEX_Input!$B:$B,0),MATCH(T$2,CAPEX_Input!$G$2:$G$2,0)),0)*T$4*$D$25 -> 0 | U43: =IFERROR(INDEX(CAPEX_Input!$G:$G,MATCH($B43,CAPEX_Input!$B:$B,0),MATCH(U$2,CAPEX_Input!$G$2:$G$2,0)),0)*U$4*$D$25 -> 0 | V43: =IFERROR(INDEX(CAPEX_Input!$G:$G,MATCH($B43,CAPEX_Input!$B:$B,0),MATCH(V$2,CAPEX_Input!$G$2:$G$2,0)),0)*V$4*$D$25 -> 0 | ... AW43: =IFERROR(INDEX(CAPEX_Input!$G:$G,MATCH($B43,CAPEX_Input!$B:$B,0),MATCH(AW$2,CAPEX_Input!$G$2:$G$2,0)),0)*AW$4*$D$25 -> 0
A45: =A46 -> Equipamentos | I45: =SUM(O45:AR45) -> 49820268 | O45: =SUM(O46:O46) -> 49820268 | P45: =SUM(P46:P46) -> 0 | Q45: =SUM(Q46:Q46) -> 0 | R45: =SUM(R46:R46) -> 0 | S45: =SUM(S46:S46) -> 0 | T45: =SUM(T46:T46) -> 0 | U45: =SUM(U46:U46) -> 0 | V45: =SUM(V46:V46) -> 0 | ... AW45: =SUM(AW46:AW46) -> 0
A46: =CAPEX_Input!C13 -> Equipamentos | B46: 02.01.03 | I46: =SUM(O46:AR46) -> 49820268 | O46: =IFERROR(INDEX(CAPEX_Input!$G:$G,MATCH($B46,CAPEX_Input!$B:$B,0),MATCH(O$2,CAPEX_Input!$G$2:$G$2,0)),0)*O$4*$D$25 -> 49820268 | P46: =IFERROR(INDEX(CAPEX_Input!$G:$G,MATCH($B46,CAPEX_Input!$B:$B,0),MATCH(P$2,CAPEX_Input!$G$2:$G$2,0)),0)*P$4*$D$25 -> 0 | Q46: =IFERROR(INDEX(CAPEX_Input!$G:$G,MATCH($B46,CAPEX_Input!$B:$B,0),MATCH(Q$2,CAPEX_Input!$G$2:$G$2,0)),0)*Q$4*$D$25 -> 0 | R46: =IFERROR(INDEX(CAPEX_Input!$G:$G,MATCH($B46,CAPEX_Input!$B:$B,0),MATCH(R$2,CAPEX_Input!$G$2:$G$2,0)),0)*R$4*$D$25 -> 0 | S46: =IFERROR(INDEX(CAPEX_Input!$G:$G,MATCH($B46,CAPEX_Input!$B:$B,0),MATCH(S$2,CAPEX_Input!$G$2:$G$2,0)),0)*S$4*$D$25 -> 0 | T46: =IFERROR(INDEX(CAPEX_Input!$G:$G,MATCH($B46,CAPEX_Input!$B:$B,0),MATCH(T$2,CAPEX_Input!$G$2:$G$2,0)),0)*T$4*$D$25 -> 0 | U46: =IFERROR(INDEX(CAPEX_Input!$G:$G,MATCH($B46,CAPEX_Input!$B:$B,0),MATCH(U$2,CAPEX_Input!$G$2:$G$2,0)),0)*U$4*$D$25 -> 0 | V46: =IFERROR(INDEX(CAPEX_Input!$G:$G,MATCH($B46,CAPEX_Input!$B:$B,0),MATCH(V$2,CAPEX_Input!$G$2:$G$2,0)),0)*V$4*$D$25 -> 0 | ... AW46: =IFERROR(INDEX(CAPEX_Input!$G:$G,MATCH($B46,CAPEX_Input!$B:$B,0),MATCH(AW$2,CAPEX_Input!$G$2:$G$2,0)),0)*AW$4*$D$25 -> 0
A48: =CAPEX_Input!C14 -> URE MARÍLIA - GÁS | I48: =SUM(O48:AR48) -> 60293238 | O48: =SUM(O50,O53,O56) -> 60293238 | P48: =SUM(P50,P53,P56) -> 0 | Q48: =SUM(Q50,Q53,Q56) -> 0 | R48: =SUM(R50,R53,R56) -> 0 | S48: =SUM(S50,S53,S56) -> 0 | T48: =SUM(T50,T53,T56) -> 0 | U48: =SUM(U50,U53,U56) -> 0 | V48: =SUM(V50,V53,V56) -> 0 | ... AW48: =SUM(AW50,AW53,AW56) -> 0
A50: =A51 -> Custos pré-operacionais | I50: =SUM(O50:AR50) -> 964263.25 | O50: =SUM(O51:O51) -> 964263.25 | P50: =SUM(P51:P51) -> 0 | Q50: =SUM(Q51:Q51) -> 0 | R50: =SUM(R51:R51) -> 0 | S50: =SUM(S51:S51) -> 0 | T50: =SUM(T51:T51) -> 0 | U50: =SUM(U51:U51) -> 0 | V50: =SUM(V51:V51) -> 0 | ... AW50: =SUM(AW51:AW51) -> 0
A51: =CAPEX_Input!C16 -> Custos pré-operacionais | B51: 03.01.01 | I51: =SUM(O51:AR51) -> 964263.25 | O51: =IFERROR(INDEX(CAPEX_Input!$G:$G,MATCH($B51,CAPEX_Input!$B:$B,0),MATCH(O$2,CAPEX_Input!$G$2:$G$2,0)),0)*O$4*$D$25 -> 964263.25 | P51: =IFERROR(INDEX(CAPEX_Input!$G:$G,MATCH($B51,CAPEX_Input!$B:$B,0),MATCH(P$2,CAPEX_Input!$G$2:$G$2,0)),0)*P$4*$D$25 -> 0 | Q51: =IFERROR(INDEX(CAPEX_Input!$G:$G,MATCH($B51,CAPEX_Input!$B:$B,0),MATCH(Q$2,CAPEX_Input!$G$2:$G$2,0)),0)*Q$4*$D$25 -> 0 | R51: =IFERROR(INDEX(CAPEX_Input!$G:$G,MATCH($B51,CAPEX_Input!$B:$B,0),MATCH(R$2,CAPEX_Input!$G$2:$G$2,0)),0)*R$4*$D$25 -> 0 | S51: =IFERROR(INDEX(CAPEX_Input!$G:$G,MATCH($B51,CAPEX_Input!$B:$B,0),MATCH(S$2,CAPEX_Input!$G$2:$G$2,0)),0)*S$4*$D$25 -> 0 | T51: =IFERROR(INDEX(CAPEX_Input!$G:$G,MATCH($B51,CAPEX_Input!$B:$B,0),MATCH(T$2,CAPEX_Input!$G$2:$G$2,0)),0)*T$4*$D$25 -> 0 | U51: =IFERROR(INDEX(CAPEX_Input!$G:$G,MATCH($B51,CAPEX_Input!$B:$B,0),MATCH(U$2,CAPEX_Input!$G$2:$G$2,0)),0)*U$4*$D$25 -> 0 | V51: =IFERROR(INDEX(CAPEX_Input!$G:$G,MATCH($B51,CAPEX_Input!$B:$B,0),MATCH(V$2,CAPEX_Input!$G$2:$G$2,0)),0)*V$4*$D$25 -> 0 | ... AW51: =IFERROR(INDEX(CAPEX_Input!$G:$G,MATCH($B51,CAPEX_Input!$B:$B,0),MATCH(AW$2,CAPEX_Input!$G$2:$G$2,0)),0)*AW$4*$D$25 -> 0
A53: =A54 -> Licenciamento (estudos, projetos e licenças) | I53: =SUM(O53:AR53) -> 401776.35 | O53: =SUM(O54:O54) -> 401776.35 | P53: =SUM(P54:P54) -> 0 | Q53: =SUM(Q54:Q54) -> 0 | R53: =SUM(R54:R54) -> 0 | S53: =SUM(S54:S54) -> 0 | T53: =SUM(T54:T54) -> 0 | U53: =SUM(U54:U54) -> 0 | V53: =SUM(V54:V54) -> 0 | ... AW53: =SUM(AW54:AW54) -> 0
A54: =CAPEX_Input!C17 -> Licenciamento (estudos, projetos e licenças) | B54: 03.01.02 | I54: =SUM(O54:AR54) -> 401776.35 | O54: =IFERROR(INDEX(CAPEX_Input!$G:$G,MATCH($B54,CAPEX_Input!$B:$B,0),MATCH(O$2,CAPEX_Input!$G$2:$G$2,0)),0)*O$4*$D$25 -> 401776.35 | P54: =IFERROR(INDEX(CAPEX_Input!$G:$G,MATCH($B54,CAPEX_Input!$B:$B,0),MATCH(P$2,CAPEX_Input!$G$2:$G$2,0)),0)*P$4*$D$25 -> 0 | Q54: =IFERROR(INDEX(CAPEX_Input!$G:$G,MATCH($B54,CAPEX_Input!$B:$B,0),MATCH(Q$2,CAPEX_Input!$G$2:$G$2,0)),0)*Q$4*$D$25 -> 0 | R54: =IFERROR(INDEX(CAPEX_Input!$G:$G,MATCH($B54,CAPEX_Input!$B:$B,0),MATCH(R$2,CAPEX_Input!$G$2:$G$2,0)),0)*R$4*$D$25 -> 0 | S54: =IFERROR(INDEX(CAPEX_Input!$G:$G,MATCH($B54,CAPEX_Input!$B:$B,0),MATCH(S$2,CAPEX_Input!$G$2:$G$2,0)),0)*S$4*$D$25 -> 0 | T54: =IFERROR(INDEX(CAPEX_Input!$G:$G,MATCH($B54,CAPEX_Input!$B:$B,0),MATCH(T$2,CAPEX_Input!$G$2:$G$2,0)),0)*T$4*$D$25 -> 0 | U54: =IFERROR(INDEX(CAPEX_Input!$G:$G,MATCH($B54,CAPEX_Input!$B:$B,0),MATCH(U$2,CAPEX_Input!$G$2:$G$2,0)),0)*U$4*$D$25 -> 0 | V54: =IFERROR(INDEX(CAPEX_Input!$G:$G,MATCH($B54,CAPEX_Input!$B:$B,0),MATCH(V$2,CAPEX_Input!$G$2:$G$2,0)),0)*V$4*$D$25 -> 0 | ... AW54: =IFERROR(INDEX(CAPEX_Input!$G:$G,MATCH($B54,CAPEX_Input!$B:$B,0),MATCH(AW$2,CAPEX_Input!$G$2:$G$2,0)),0)*AW$4*$D$25 -> 0
A56: =A57 -> Equipamentos | I56: =SUM(O56:AR56) -> 58927199 | O56: =SUM(O57:O57) -> 58927199 | P56: =SUM(P57:P57) -> 0 | Q56: =SUM(Q57:Q57) -> 0 | R56: =SUM(R57:R57) -> 0 | S56: =SUM(S57:S57) -> 0 | T56: =SUM(T57:T57) -> 0 | U56: =SUM(U57:U57) -> 0 | V56: =SUM(V57:V57) -> 0 | ... AW56: =SUM(AW57:AW57) -> 0
A57: =CAPEX_Input!C18 -> Equipamentos | B57: 03.01.03 | I57: =SUM(O57:AR57) -> 58927199 | O57: =IFERROR(INDEX(CAPEX_Input!$G:$G,MATCH($B57,CAPEX_Input!$B:$B,0),MATCH(O$2,CAPEX_Input!$G$2:$G$2,0)),0)*O$4*$D$25 -> 58927199 | P57: =IFERROR(INDEX(CAPEX_Input!$G:$G,MATCH($B57,CAPEX_Input!$B:$B,0),MATCH(P$2,CAPEX_Input!$G$2:$G$2,0)),0)*P$4*$D$25 -> 0 | Q57: =IFERROR(INDEX(CAPEX_Input!$G:$G,MATCH($B57,CAPEX_Input!$B:$B,0),MATCH(Q$2,CAPEX_Input!$G$2:$G$2,0)),0)*Q$4*$D$25 -> 0 | R57: =IFERROR(INDEX(CAPEX_Input!$G:$G,MATCH($B57,CAPEX_Input!$B:$B,0),MATCH(R$2,CAPEX_Input!$G$2:$G$2,0)),0)*R$4*$D$25 -> 0 | S57: =IFERROR(INDEX(CAPEX_Input!$G:$G,MATCH($B57,CAPEX_Input!$B:$B,0),MATCH(S$2,CAPEX_Input!$G$2:$G$2,0)),0)*S$4*$D$25 -> 0 | T57: =IFERROR(INDEX(CAPEX_Input!$G:$G,MATCH($B57,CAPEX_Input!$B:$B,0),MATCH(T$2,CAPEX_Input!$G$2:$G$2,0)),0)*T$4*$D$25 -> 0 | U57: =IFERROR(INDEX(CAPEX_Input!$G:$G,MATCH($B57,CAPEX_Input!$B:$B,0),MATCH(U$2,CAPEX_Input!$G$2:$G$2,0)),0)*U$4*$D$25 -> 0 | V57: =IFERROR(INDEX(CAPEX_Input!$G:$G,MATCH($B57,CAPEX_Input!$B:$B,0),MATCH(V$2,CAPEX_Input!$G$2:$G$2,0)),0)*V$4*$D$25 -> 0 | ... AW57: =IFERROR(INDEX(CAPEX_Input!$G:$G,MATCH($B57,CAPEX_Input!$B:$B,0),MATCH(AW$2,CAPEX_Input!$G$2:$G$2,0)),0)*AW$4*$D$25 -> 0
A60: AMORTIZAÇÃO E DEPRECIAÇÃO | B60: K R$ | I60: =0.001 -> 0.001
A61: CAPEX p/ ser Amortizado/Depreciado | I61: =SUM(O61:AR61) -> 54608029 | O61: =SUM(O62,O64,O66) -> 0 | P61: =SUM(P62,P64,P66) -> 4688610.9 | Q61: =SUM(Q62,Q64,Q66) -> 5569157.6 | R61: =SUM(R62,R64,R66) -> 5569157.6 | S61: =SUM(S62,S64,S66) -> 5569157.6 | T61: =SUM(T62,T64,T66) -> 5569157.6 | U61: =SUM(U62,U64,U66) -> 5569157.6 | V61: =SUM(V62,V64,V66) -> 5518407.6 | ... AW61: =SUM(AW62,AW64,AW66) -> 0
A62: =A8 -> URE MARÍLIA - BIO+GÁS | O62: =SUM(O63:O63) -> 0 | P62: =SUM(P63:P63) -> 4060000 | Q62: =SUM(Q63:Q63) -> 4060000 | R62: =SUM(R63:R63) -> 4060000 | S62: =SUM(S63:S63) -> 4060000 | T62: =SUM(T63:T63) -> 4060000 | U62: =SUM(U63:U63) -> 4060000 | V62: =SUM(V63:V63) -> 4060000 | ... AW62: =SUM(AW63:AW63) -> 0
A63: Amortização | B63: K R$ | O63: ='DRE_URE MARÍLIA-BIO+GAS'!E37 -> 0 | P63: ='DRE_URE MARÍLIA-BIO+GAS'!F37*-1 -> 4060000 | Q63: ='DRE_URE MARÍLIA-BIO+GAS'!G37*-1 -> 4060000 | R63: ='DRE_URE MARÍLIA-BIO+GAS'!H37*-1 -> 4060000 | S63: ='DRE_URE MARÍLIA-BIO+GAS'!I37*-1 -> 4060000 | T63: ='DRE_URE MARÍLIA-BIO+GAS'!J37*-1 -> 4060000 | U63: ='DRE_URE MARÍLIA-BIO+GAS'!K37*-1 -> 4060000 | V63: ='DRE_URE MARÍLIA-BIO+GAS'!L37*-1 -> 4060000 | W63: ='DRE_URE MARÍLIA-BIO+GAS'!M37*-1 -> 4060000 | ... AW63: ='DRE_URE MARÍLIA-BIO+GAS'!AM37*-1 -> 0
A64: =A13 -> URE MARÍLIA - BIO | O64: =SUM(O65:O65) -> 0 | P64: =SUM(P65:P65) -> 465000 | Q64: =SUM(Q65:Q65) -> 465000 | R64: =SUM(R65:R65) -> 465000 | S64: =SUM(S65:S65) -> 465000 | T64: =SUM(T65:T65) -> 465000 | U64: =SUM(U65:U65) -> 465000 | V64: =SUM(V65:V65) -> 465000 | ... AW64: =SUM(AW65:AW65) -> 0
A65: Amortização | B65: K R$ | O65: ='DRE_URE MARÍLIA-BIO'!E37*-1 -> 0 | P65: ='DRE_URE MARÍLIA-BIO'!F37*-1 -> 465000 | Q65: ='DRE_URE MARÍLIA-BIO'!G37*-1 -> 465000 | R65: ='DRE_URE MARÍLIA-BIO'!H37*-1 -> 465000 | S65: ='DRE_URE MARÍLIA-BIO'!I37*-1 -> 465000 | T65: ='DRE_URE MARÍLIA-BIO'!J37*-1 -> 465000 | U65: ='DRE_URE MARÍLIA-BIO'!K37*-1 -> 465000 | V65: ='DRE_URE MARÍLIA-BIO'!L37*-1 -> 465000 | ... AW65: ='DRE_URE MARÍLIA-BIO'!AM37*-1 -> 0
A66: =A18 -> URE MARÍLIA - GÁS | O66: =SUM(O67:O67) -> 0 | P66: =SUM(P67:P67) -> 163610.86 | Q66: =SUM(Q67:Q67) -> 1044157.6 | R66: =SUM(R67:R67) -> 1044157.6 | S66: =SUM(S67:S67) -> 1044157.6 | T66: =SUM(T67:T67) -> 1044157.6 | U66: =SUM(U67:U67) -> 1044157.6 | V66: =SUM(V67:V67) -> 993407.63 | ... AW66: =SUM(AW67:AW67) -> 0
A67: Amortização | B67: K R$ | O67: ='DRE_URE MARÍLIA-GAS'!E37*-1 -> 0 | P67: ='DRE_URE MARÍLIA-GAS'!F37*-1 -> 163610.86 | Q67: ='DRE_URE MARÍLIA-GAS'!G37*-1 -> 1044157.6 | R67: ='DRE_URE MARÍLIA-GAS'!H37*-1 -> 1044157.6 | S67: ='DRE_URE MARÍLIA-GAS'!I37*-1 -> 1044157.6 | T67: ='DRE_URE MARÍLIA-GAS'!J37*-1 -> 1044157.6 | U67: ='DRE_URE MARÍLIA-GAS'!K37*-1 -> 1044157.6 | V67: ='DRE_URE MARÍLIA-GAS'!L37*-1 -> 993407.63 | ... AW67: ='DRE_URE MARÍLIA-GAS'!AM37*-1 -> 0
A69: Sínteze e Prazos | B69: K R$ | I69: flag | J69: =SUM(J70,J72,J74) -> 43394626 | N69: =SUM(O69:AR69) -> 54608029 | O69: =O70+O72+O74 -> 0 | P69: =P70+P72+P74 -> 4688610.9 | Q69: =Q70+Q72+Q74 -> 5569157.6 | R69: =R70+R72+R74 -> 5569157.6 | S69: =S70+S72+S74 -> 5569157.6 | T69: =T70+T72+T74 -> 5569157.6 | U69: =U70+U72+U74 -> 5569157.6 | V69: =V70+V72+V74 -> 5518407.6 | ... AW69: =AW70+AW72+AW74 -> 0
A70: =A62 -> URE MARÍLIA - BIO+GÁS | I70: =SUM(O70:AR70) -> 40600000 | J70: =SUM(J71:J71) -> 32324535 | O70: =SUM(O71:O71) -> 0 | P70: =SUM(P71:P71) -> 4060000 | Q70: =SUM(Q71:Q71) -> 4060000 | R70: =SUM(R71:R71) -> 4060000 | S70: =SUM(S71:S71) -> 4060000 | T70: =SUM(T71:T71) -> 4060000 | U70: =SUM(U71:U71) -> 4060000 | V70: =SUM(V71:V71) -> 4060000 | ... AW70: =SUM(AW71:AW71) -> 0
A71: =A11 -> Equipamentos | D71: 10 | E71: anos | I71: =Premissas!B22 -> G | J71: {=SUMPRODUCT(O71:AR71/$O$4:$AR$4)} -> 32324535 | K71: =J71/($J$70-J69) -> -2.9199882 | O71: =O63 -> 0 | P71: =P63 -> 4060000 | Q71: =Q63 -> 4060000 | R71: =R63 -> 4060000 | S71: =S63 -> 4060000 | T71: =T63 -> 4060000 | U71: =U63 -> 4060000 | V71: =V63 -> 4060000 | ... AW71: =AW63 -> 0
A72: =A64 -> URE MARÍLIA - BIO | I72: =SUM(O72:AR72) -> 4650000 | J72: =SUM(J73:J73) -> 3702194.3 | O72: =SUM(O73:O73) -> 0 | P72: =SUM(P73:P73) -> 465000 | Q72: =SUM(Q73:Q73) -> 465000 | R72: =SUM(R73:R73) -> 465000 | S72: =SUM(S73:S73) -> 465000 | T72: =SUM(T73:T73) -> 465000 | U72: =SUM(U73:U73) -> 465000 | V72: =SUM(V73:V73) -> 465000 | ... AW72: =SUM(AW73:AW73) -> 0
A73: =A16 -> Equipamentos | D73: 10 | E73: anos | I73: =Premissas!B25 -> G | J73: {=SUMPRODUCT(O73:AR73/$O$4:$AR$4)} -> 3702194.3 | K73: =J73/($J$72-J69) -> -0.093272045 | O73: =O65 -> 0 | P73: =P65 -> 465000 | Q73: =Q65 -> 465000 | R73: =R65 -> 465000 | S73: =S65 -> 465000 | T73: =T65 -> 465000 | U73: =U65 -> 465000 | V73: =V65 -> 465000 | ... AW73: =AW65 -> 0
A74: =A66 -> URE MARÍLIA - GÁS | I74: =SUM(O74:AR74) -> 9358029.5 | J74: =SUM(J75:J75) -> 7367896.8 | O74: =SUM(O75:O75) -> 0 | P74: =SUM(P75:P75) -> 163610.86 | Q74: =SUM(Q75:Q75) -> 1044157.6 | R74: =SUM(R75:R75) -> 1044157.6 | S74: =SUM(S75:S75) -> 1044157.6 | T74: =SUM(T75:T75) -> 1044157.6 | U74: =SUM(U75:U75) -> 1044157.6 | V74: =SUM(V75:V75) -> 993407.63 | ... AW74: =SUM(AW75:AW75) -> 0
A75: =A21 -> Equipamentos | D75: 10 | E75: anos | I75: =Premissas!B28 -> G | J75: {=SUMPRODUCT(O75:AR75/$O$4:$AR$4)} -> 7367896.8 | K75: =J75/($J$74-J69) -> -0.20451195 | O75: =O67 -> 0 | P75: =P67 -> 163610.86 | Q75: =Q67 -> 1044157.6 | R75: =R67 -> 1044157.6 | S75: =S67 -> 1044157.6 | T75: =T67 -> 1044157.6 | U75: =U67 -> 1044157.6 | V75: =V67 -> 993407.63 | ... AW75: =AW67 -> 0
A77: Cronograma de incorporação do ativo financeiro | I77: G | J77: =SUMIF(I71:I75,"G",J71:J75) -> 43394626 | O77: =SUMIF($I$71:$I$75,"G",O$71:O$75)/O$4 -> 0 | P77: =SUMIF($I$71:$I$75,"G",P$71:P$75)/P$4 -> 4248678.4 | Q77: =SUMIF($I$71:$I$75,"G",Q$71:Q$75)/Q$4 -> 4899615 | R77: =SUMIF($I$71:$I$75,"G",R$71:R$75)/R$4 -> 4756907.8 | S77: =SUMIF($I$71:$I$75,"G",S$71:S$75)/S$4 -> 4618357 | T77: =SUMIF($I$71:$I$75,"G",T$71:T$75)/T$4 -> 4483841.8 | U77: =SUMIF($I$71:$I$75,"G",U$71:U$75)/U$4 -> 4353244.5 | V77: =SUMIF($I$71:$I$75,"G",V$71:V$75)/V$4 -> 4187936.6 | ... AW77: =SUMIF($I$71:$I$75,"G",AW$71:AW$75)/AW$4 -> 0
O78: 1 | P78: 0 | Q78: 0 | R78: 0 | S78: 0 | T78: 0 | U78: 0 | V78: 0 | W78: 0 | X78: 0 | Y78: 0 | Z78: 0 | AA78: 0 | AB78: 0 | AC78: 0 | AD78: 0 | AE78: 0 | AF78: 0 | AG78: 0 | AH78: 0 | AI78: 0 | AJ78: 0 | AK78: 0 | AL78: 0 | AM78: 0 | AN78: 0 | AO78: 0 | AP78: 0 | AQ78: 0 | AR78: 0 | AS78: 0 | AT78: 0 | AU78: 0 | AV78: 0 | AW78: 0

Sheet CAPEX_Input
B2: Custos de Investimento - PMI URE MARÍLIA - CAPEX | G2: 1
B3: Item | C3: Descrição | D3: Unidade | E3: Preço Unitário | F3: Quantidade Ano 1 | G3: Preço Total Ano 1 | H3: Preço Total Geral | I3: Participação percentual
B4: 1 | C4: URE MARÍLIA - BIO+GÁS
B5: 01.01 | C5: Despesas Operacionais | E5: -1 | G5: =SUBTOTAL(9,G6:G7) -> 1275000 | H5: =SUBTOTAL(9,H6:H7) -> 1275000 | I5: =ROUND(SUBTOTAL(9,I6:I7),2) -> 0.01
B6: 01.01.01 | C6: Custos pré-operacionais | D6: un | E6: ='DRE_URE MARÍLIA-BIO+GAS'!E21*$E$5 -> 900000 | F6: 1 | G6: =$E6*F6 -> 900000 | H6: =SUM(G6) -> 900000 | I6: =ROUND(H6/$H$19,4) -> 0.0059
B7: 01.01.02 | C7: Licenciamento (estudos, projetos e licenças) | D7: un | E7: ='DRE_URE MARÍLIA-BIO+GAS'!E22*$E$5 -> 375000 | F7: 1 | G7: =$E7*F7 -> 375000 | H7: =SUM(G7) -> 375000 | I7: =ROUND(H7/$H$19,4) -> 0.0025
B8: 01.01.03 | C8: Equipamentos | D8: un | E8: ='DRE_URE MARÍLIA-GAS'!Q81 -> 101500000 | F8: 1 | G8: =$E8*F8 -> 101500000 | H8: =SUM(G8) -> 101500000 | I8: =ROUND(H8/$H$19,4) -> 0.6685
B9: 2 | C9: URE MARÍLIA - BIO
B10: 02.01 | C10: Despesas Operacionais | E10: -1 | G10: =SUBTOTAL(9,G11:G12) -> 1275000 | H10: =SUBTOTAL(9,H11:H12) -> 1275000 | I10: =ROUND(SUBTOTAL(9,I11:I12),2) -> 0.01
B11: 02.01.01 | C11: Custos pré-operacionais | D11: un | E11: ='DRE_URE MARÍLIA-BIO'!E21*$E$5 -> 900000 | F11: 1 | G11: =$E11*F11 -> 900000 | H11: =SUM(G11) -> 900000 | I11: =ROUND(H11/$H$19,4) -> 0.0059
B12: 02.01.02 | C12: Licenciamento (estudos, projetos e licenças) | D12: un | E12: ='DRE_URE MARÍLIA-BIO'!E22*$E$5 -> 375000 | F12: 1 | G12: =$E12*F12 -> 375000 | H12: =SUM(G12) -> 375000 | I12: =ROUND(H12/$H$19,4) -> 0.0025
B13: 02.01.03 | C13: Equipamentos | D13: un | E13: ='DRE_URE MARÍLIA-BIO'!Q79 -> 46500000 | F13: 1 | G13: =$E13*F13 -> 46500000 | H13: =SUM(G13) -> 46500000 | I13: =ROUND(H13/$H$19,4) -> 0.3063
B14: 3 | C14: URE MARÍLIA - GÁS
B15: 03.01 | C15: Despesas Operacionais | E15: -1 | G15: =SUBTOTAL(9,G16:G17) -> 1275000 | H15: =SUBTOTAL(9,H16:H17) -> 1275000 | I15: =ROUND(SUBTOTAL(9,I16:I17),2) -> 0.01
B16: 03.01.01 | C16: Custos pré-operacionais | D16: un | E16: ='DRE_URE MARÍLIA-GAS'!E21*$E$5 -> 900000 | F16: 1 | G16: =$E16*F16 -> 900000 | H16: =SUM(G16) -> 900000 | I16: =ROUND(H16/$H$19,4) -> 0.0059
B17: 03.01.02 | C17: Licenciamento (estudos, projetos e licenças) | D17: un | E17: ='DRE_URE MARÍLIA-GAS'!E22*$E$5 -> 375000 | F17: 1 | G17: =$E17*F17 -> 375000 | H17: =SUM(G17) -> 375000 | I17: =ROUND(H17/$H$19,4) -> 0.0025
B18: 03.01.03 | C18: Equipamentos | D18: un | E18: ='DRE_URE MARÍLIA-GAS'!Q80 -> 55000000 | F18: 1 | G18: =$E18*F18 -> 55000000 | H18: =SUM(G18) -> 55000000 | I18: =ROUND(H18/$H$19,4) -> 0.3623
E19: SUBTOTAL | G19: =SUBTOTAL(9,G4:G17) -> 151825000 | H19: =SUBTOTAL(9,H4:H17) -> 151825000 | I19: =ROUND(SUBTOTAL(9,I4:I17),2) -> 1

Sheet Opex
C1: Unidade | D1: Fator 1 | E1: Unidade Fator 1 | F1: Fonte Fator 1 | G1: Fator 2 | Z1: 2025 | AA1: =Z1+1 -> 2026 | AB1: =AA1+1 -> 2027 | AC1: =AB1+1 -> 2028 | AD1: =AC1+1 -> 2029 | AE1: =AD1+1 -> 2030 | AF1: =AE1+1 -> 2031 | AG1: =AF1+1 -> 2032 | AH1: =AG1+1 -> 2033 | ... BG1: =BF1+1 -> 2058
A2: MACRO-ECONÔMICOS | Z2: 1 | AA2: =Z2+1 -> 2 | AB2: =AA2+1 -> 3 | AC2: =AB2+1 -> 4 | AD2: =AC2+1 -> 5 | AE2: =AD2+1 -> 6 | AF2: =AE2+1 -> 7 | AG2: =AF2+1 -> 8 | AH2: =AG2+1 -> 9 | ... BG2: =BF2+1 -> 34
A3: =MacroEco!A8 -> Índice de inflação brasileira (IPCA) | B3: =MacroEco!B8 -> 44985 | D3: =Premissas!D$8 -> 1 | E3: =Premissas!E8 -> [1: Nominais; 2: Reais] | Z3: =MacroEco!AA8 -> 1.0714036 | AA3: =MacroEco!AB8 -> 1.1035457 | AB3: =MacroEco!AC8 -> 1.1366521 | AC3: =MacroEco!AD8 -> 1.1707517 | AD3: =MacroEco!AE8 -> 1.2058742 | AE3: =MacroEco!AF8 -> 1.2420504 | AF3: =MacroEco!AG8 -> 1.2793119 | AG3: =MacroEco!AH8 -> 1.3176913 | ... BG3: =MacroEco!BH8 -> 2.8417216
A4: =MacroEco!A$11 -> Câmbio (nominal) (média do período) | B4: =MacroEco!B$12 -> R$/Euro | D4: =Premissas!D$8 -> 1 | E4: =Premissas!E$8 -> [1: Nominais; 2: Reais] | I4: =MacroEco!I$12 -> 0 | J4: =MacroEco!J$12 -> 0 | K4: =MacroEco!K$12 -> 2.6733583 | L4: =MacroEco!L$12 -> 2.769175 | M4: =MacroEco!M$12 -> 2.3352083 | N4: =MacroEco!N$12 -> 2.3281833 | O4: =MacroEco!O$12 -> 2.5115583 | P4: =MacroEco!P$12 -> 2.8676667 | ... Y4: =MacroEco!Y$12 -> 5.4441417 | Z4: =MacroEco!AA$12 -> 5.496797 | AA4: =MacroEco!AB$12 -> 5.5344095 | AB4: =MacroEco!AC$12 -> 5.5722794 | AC4: =MacroEco!AD$12 -> 5.6104083 | AD4: =MacroEco!AE$12 -> 5.6487982 | AE4: =MacroEco!AF$12 -> 5.6874508 | AF4: =MacroEco!AG$12 -> 5.7263679 | AG4: =MacroEco!AH$12 -> 5.7655512 | ... BG4: =MacroEco!BH$12 -> 6.8840212
A6: Custo Total / Síntese [valores nominais] | D6: =1/1000 -> 0.001 | E6: R$/K R$
A7: =A57 -> URE MARÍLIA - BIO+GÁS
A8: Total anual | C8: R$/K/ano | Z8: =SUM(Z10:Z11) -> 20778716 | AA8: =SUM(AA10:AA11) -> 1.145694e+08 | AB8: =SUM(AB10:AB11) -> 1.7161365e+08 | AC8: =SUM(AC10:AC11) -> 1.7676206e+08 | AD8: =SUM(AD10:AD11) -> 1.8206492e+08 | AE8: =SUM(AE10:AE11) -> 1.8752687e+08 | AF8: =SUM(AF10:AF11) -> 1.9315267e+08 | AG8: =SUM(AG10:AG11) -> 1.9894725e+08 | ... BG8: =SUM(BG10:BG11) -> 4.2904791e+08
A9: Meses de operação | C9: # meses | Z9: 12 | AA9: 12 | AB9: 12 | AC9: 12 | AD9: 12 | AE9: 12 | AF9: 12 | AG9: 12 | AH9: 12 | AI9: 12 | AJ9: 12 | AK9: 12 | AL9: 12 | AM9: 12 | AN9: 12 | AO9: 12 | AP9: 12 | AQ9: 12 | AR9: 12 | AS9: 12 | AT9: 12 | AU9: 12 | AV9: 12 | AW9: 12 | AX9: 12 | AY9: 12 | AZ9: 12 | BA9: 12 | BB9: 12 | BC9: 12 | BD9: 12 | BE9: 12 | BF9: 12 | BG9: 12
A10: Mão de Obra | C10: R$/K/ano | Z10: =Z15*Z$9 -> 18532368 | AA10: =AA15*AA$9 -> 1.0300071e+08 | AB10: =AB15*AB$9 -> 1.0832477e+08 | AC10: =AC15*AC$9 -> 1.1157451e+08 | AD10: =AD15*AD$9 -> 1.1492175e+08 | AE10: =AE15*AE$9 -> 1.183694e+08 | AF10: =AF15*AF$9 -> 1.2192048e+08 | AG10: =AG15*AG$9 -> 1.255781e+08 | ... BG10: =BG15*BG$9 -> 2.7082062e+08
A11: Outros custos | C11: R$/K/ano | Z11: =Z16*Z$9 -> 2246347.7 | AA11: =AA16*AA$9 -> 11568690 | AB11: =AB16*AB$9 -> 63288880 | AC11: =AC16*AC$9 -> 65187546 | AD11: =AD16*AD$9 -> 67143173 | AE11: =AE16*AE$9 -> 69157468 | AF11: =AF16*AF$9 -> 71232192 | AG11: =AG16*AG$9 -> 73369158 | ... BG11: =BG16*BG$9 -> 1.5822728e+08
A14: Total mensal | C14: R$/k/mês | Z14: =SUM(Z15:Z16) -> 1731559.7 | AA14: =SUM(AA15:AA16) -> 9547449.8 | AB14: =SUM(AB15:AB16) -> 14301137 | AC14: =SUM(AC15:AC16) -> 14730171 | AD14: =SUM(AD15:AD16) -> 15172077 | AE14: =SUM(AE15:AE16) -> 15627239 | AF14: =SUM(AF15:AF16) -> 16096056 | AG14: =SUM(AG15:AG16) -> 16578938 | ... BG14: =SUM(BG15:BG16) -> 35753992
A15: Mão de Obra | C15: R$/k/mês | Z15: =SUM(Z56:Z58)*Z$3 -> 1544364 | AA15: =SUM(AA56:AA58)*AA$3 -> 8583392.3 | AB15: =SUM(AB56:AB58)*AB$3 -> 9027064 | AC15: =SUM(AC56:AC58)*AC$3 -> 9297876 | AD15: =SUM(AD56:AD58)*AD$3 -> 9576812.2 | AE15: =SUM(AE56:AE58)*AE$3 -> 9864116.6 | AF15: =SUM(AF56:AF58)*AF$3 -> 10160040 | AG15: =SUM(AG56:AG58)*AG$3 -> 10464841 | ... BG15: =SUM(BG56:BG58)*BG$3 -> 22568385
A16: Outros custos | C16: R$/k/mês | Z16: =(SUM(Z59:Z59))*Z$3 -> 187195.64 | AA16: =(SUM(AA59:AA59))*AA$3 -> 964057.54 | AB16: =(SUM(AB59:AB59))*AB$3 -> 5274073.3 | AC16: =(SUM(AC59:AC59))*AC$3 -> 5432295.5 | AD16: =(SUM(AD59:AD59))*AD$3 -> 5595264.4 | AE16: =(SUM(AE59:AE59))*AE$3 -> 5763122.3 | AF16: =(SUM(AF59:AF59))*AF$3 -> 5936016 | AG16: =(SUM(AG59:AG59))*AG$3 -> 6114096.5 | ... BG16: =(SUM(BG59:BG59))*BG$3 -> 13185607
A18: R$/ton | Z18: =Z8/OPERACIONAL!H7*1000/Z$3 -> 307498.34 | AA18: =AA8/OPERACIONAL!I6*1000/AA$3 -> 1633150.1 | AB18: =AB8/OPERACIONAL!J6*1000/AB$3 -> 2356879.3 | AC18: =AC8/OPERACIONAL!K6*1000/AC$3 -> 2338625.9 | AD18: =AD8/OPERACIONAL!L6*1000/AD$3 -> 2320296.4 | AE18: =AE8/OPERACIONAL!M6*1000/AE$3 -> 2302603.1 | AF18: =AF8/OPERACIONAL!N6*1000/AF$3 -> 2284831.8 | AG18: =AG8/OPERACIONAL!O6*1000/AG$3 -> 2266992.3 | AH18: =AH8/OPERACIONAL!P6*1000/AH$3 -> 2249429.2 | ... BG18: =BG8/OPERACIONAL!AO6*1000/BG$3 -> 1860984.7
A19: R$/per capita | Z19: =Z8*1000/OPERACIONAL!H4/Z$3 -> 82122.324 | AA19: =AA8*1000/OPERACIONAL!I4/AA$3 -> 429994.98 | AB19: =AB8*1000/OPERACIONAL!J4/AB$3 -> 611644.12 | AC19: =AC8*1000/OPERACIONAL!K4/AC$3 -> 593684.5 | AD19: =AD8*1000/OPERACIONAL!L4/AD$3 -> 589242.81 | AE19: =AE8*1000/OPERACIONAL!M4/AE$3 -> 584651.94 | AF19: =AF8*1000/OPERACIONAL!N4/AF$3 -> 580080.78 | AG19: =AG8*1000/OPERACIONAL!O4/AG$3 -> 575530.09 | ... BG19: =BG8*1000/OPERACIONAL!AO4/BG$3 -> 472281.19
A20: Diferença em relação à média Sudeste | D20: 144.62 | E20: R$/hab/ano | F20: ANA (Relatório de Impacto Regulatório n 01/2021) | Z20: =Z19/$D$20-1 -> 566.84901 | AA20: =AA19/$D$20-1 -> 2972.2746 | AB20: =AB19/$D$20-1 -> 4228.3191 | AC20: =AC19/$D$20-1 -> 4104.1341 | AD20: =AD19/$D$20-1 -> 4073.4213 | AE20: =AE19/$D$20-1 -> 4041.6769 | AF20: =AF19/$D$20-1 -> 4010.0689 | AG20: =AG19/$D$20-1 -> 3978.6023 | ... BG20: =BG19/$D$20-1 -> 3264.67
A23: =A58 -> URE MARÍLIA - BIO
A24: Total anual | C24: R$/K/ano | Z24: =SUM(Z26:Z27) -> 6257682.8 | AA24: =SUM(AA26:AA27) -> 39786077 | AB24: =SUM(AB26:AB27) -> 40979660 | AC24: =SUM(AC26:AC27) -> 42209049 | AD24: =SUM(AD26:AD27) -> 43475321 | AE24: =SUM(AE26:AE27) -> 44779581 | AF24: =SUM(AF26:AF27) -> 46122968 | AG24: =SUM(AG26:AG27) -> 47506657 | ... BG24: =SUM(BG26:BG27) -> 1.0245244e+08
A25: Meses de operação | C25: # meses | Z25: 12 | AA25: 12 | AB25: 12 | AC25: 12 | AD25: 12 | AE25: 12 | AF25: 12 | AG25: 12 | AH25: 12 | AI25: 12 | AJ25: 12 | AK25: 12 | AL25: 12 | AM25: 12 | AN25: 12 | AO25: 12 | AP25: 12 | AQ25: 12 | AR25: 12 | AS25: 12 | AT25: 12 | AU25: 12 | AV25: 12 | AW25: 12 | AX25: 12 | AY25: 12 | AZ25: 12 | BA25: 12 | BB25: 12 | BC25: 12 | BD25: 12 | BE25: 12 | BF25: 12 | BG25: 12
A26: Mão de Obra | C26: R$/K/ano | Z26: =Z30*Z$9 -> 6257682.8 | AA26: =AA30*AA$9 -> 38526242 | AB26: =AB30*AB$9 -> 39682029 | AC26: =AC30*AC$9 -> 40872490 | AD26: =AD30*AD$9 -> 42098665 | AE26: =AE30*AE$9 -> 43361625 | AF26: =AF30*AF$9 -> 44662474 | AG26: =AG30*AG$9 -> 46002348 | ... BG26: =BG30*BG$9 -> 99208262
A27: Outros custos | C27: R$/K/ano | Z27: =Z31*Z$9 -> 0 | AA27: =AA31*AA$9 -> 1259835.2 | AB27: =AB31*AB$9 -> 1297630.2 | AC27: =AC31*AC$9 -> 1336559.1 | AD27: =AD31*AD$9 -> 1376655.9 | AE27: =AE31*AE$9 -> 1417955.6 | AF27: =AF31*AF$9 -> 1460494.2 | AG27: =AG31*AG$9 -> 1504309.1 | ... BG27: =BG31*BG$9 -> 3244179.8
A29: Total mensal | C29: R$/k/mês | Z29: =SUM(Z30:Z31) -> 521473.57 | AA29: =SUM(AA30:AA31) -> 3315506.4 | AB29: =SUM(AB30:AB31) -> 3414971.6 | AC29: =SUM(AC30:AC31) -> 3517420.8 | AD29: =SUM(AD30:AD31) -> 3622943.4 | AE29: =SUM(AE30:AE31) -> 3731631.7 | AF29: =SUM(AF30:AF31) -> 3843580.7 | AG29: =SUM(AG30:AG31) -> 3958888.1 | ... BG29: =SUM(BG30:BG31) -> 8537703.5
A30: Mão de Obra | C30: R$/k/mês | Z30: =SUM(Z70:Z72)*Z$3 -> 521473.57 | AA30: =SUM(AA70:AA72)*AA$3 -> 3210520.2 | AB30: =SUM(AB70:AB72)*AB$3 -> 3306835.8 | AC30: =SUM(AC70:AC72)*AC$3 -> 3406040.9 | AD30: =SUM(AD70:AD72)*AD$3 -> 3508222.1 | AE30: =SUM(AE70:AE72)*AE$3 -> 3613468.7 | AF30: =SUM(AF70:AF72)*AF$3 -> 3721872.8 | AG30: =SUM(AG70:AG72)*AG$3 -> 3833529 | ... BG30: =SUM(BG70:BG72)*BG$3 -> 8267355.2
A31: Outros custos | C31: R$/k/mês | Z31: =(SUM(Z73:Z73))*Z$3 -> 0 | AA31: =(SUM(AA73:AA73))*AA$3 -> 104986.26 | AB31: =(SUM(AB73:AB73))*AB$3 -> 108135.85 | AC31: =(SUM(AC73:AC73))*AC$3 -> 111379.93 | AD31: =(SUM(AD73:AD73))*AD$3 -> 114721.32 | AE31: =(SUM(AE73:AE73))*AE$3 -> 118162.96 | AF31: =(SUM(AF73:AF73))*AF$3 -> 121707.85 | AG31: =(SUM(AG73:AG73))*AG$3 -> 125359.09 | ... BG31: =(SUM(BG73:BG73))*BG$3 -> 270348.32
A33: R$/ton | Z33: =Z24/OPERACIONAL!H7*1000/Z$3 -> 92605.676 | AA33: =AA24/OPERACIONAL!I7*1000/AA$3 -> 567137.78 | AB33: =AB24/OPERACIONAL!J7*1000/AB$3 -> 562799.7 | AC33: =AC24/OPERACIONAL!K7*1000/AC$3 -> 558440.97 | AD33: =AD24/OPERACIONAL!L7*1000/AD$3 -> 554064.07 | AE33: =AE24/OPERACIONAL!M7*1000/AE$3 -> 549839.08 | AF33: =AF24/OPERACIONAL!N7*1000/AF$3 -> 545595.47 | AG33: =AG24/OPERACIONAL!O7*1000/AG$3 -> 541335.57 | ... BG33: =BG24/OPERACIONAL!AO7*1000/BG$3 -> 444384.92
A34: R$/per capita | Z34: =Z24*1000/OPERACIONAL!H4/Z$3 -> 24731.819 | AA34: =AA24*1000/OPERACIONAL!I4/AA$3 -> 149322.71 | AB34: =AB24*1000/OPERACIONAL!J4/AB$3 -> 146054.63 | AC34: =AC24*1000/OPERACIONAL!K4/AC$3 -> 141766.05 | AD34: =AD24*1000/OPERACIONAL!L4/AD$3 -> 140705.42 | AE34: =AE24*1000/OPERACIONAL!M4/AE$3 -> 139609.16 | AF34: =AF24*1000/OPERACIONAL!N4/AF$3 -> 138517.61 | AG34: =AG24*1000/OPERACIONAL!O4/AG$3 -> 137430.95 | ... BG34: =BG24*1000/OPERACIONAL!AO4/BG$3 -> 112776.13
A35: Diferença em relação à média Sudeste | D35: 144.62 | E35: R$/hab/ano | F35: ANA (Relatório de Impacto Regulatório n 01/2021) | Z35: =Z34/$D$20-1 -> 170.01244 | AA35: =AA34/$D$20-1 -> 1031.5177 | AB35: =AB34/$D$20-1 -> 1008.92 | AC35: =AC34/$D$20-1 -> 979.26585 | AD35: =AD34/$D$20-1 -> 971.93193 | AE35: =AE34/$D$20-1 -> 964.35168 | AF35: =AF34/$D$20-1 -> 956.80399 | AG35: =AG34/$D$20-1 -> 949.29008 | ... BG35: =BG34/$D$20-1 -> 778.81003
A38: =A59 -> URE MARÍLIA - GÁS
A39: Total anual | C39: R$/K/ano | Z39: =SUM(Z41:Z42) -> 2246347.7 | AA39: =SUM(AA41:AA42) -> 11568690 | AB39: =SUM(AB41:AB42) -> 63288880 | AC39: =SUM(AC41:AC42) -> 65187546 | AD39: =SUM(AD41:AD42) -> 67143173 | AE39: =SUM(AE41:AE42) -> 69157468 | AF39: =SUM(AF41:AF42) -> 71232192 | AG39: =SUM(AG41:AG42) -> 73369158 | ... BG39: =SUM(BG41:BG42) -> 1.5822728e+08
A40: Meses de operação | C40: # meses | Z40: 12 | AA40: 12 | AB40: 12 | AC40: 12 | AD40: 12 | AE40: 12 | AF40: 12 | AG40: 12 | AH40: 12 | AI40: 12 | AJ40: 12 | AK40: 12 | AL40: 12 | AM40: 12 | AN40: 12 | AO40: 12 | AP40: 12 | AQ40: 12 | AR40: 12 | AS40: 12 | AT40: 12 | AU40: 12 | AV40: 12 | AW40: 12 | AX40: 12 | AY40: 12 | AZ40: 12 | BA40: 12 | BB40: 12 | BC40: 12 | BD40: 12 | BE40: 12 | BF40: 12 | BG40: 12
A41: Mão de Obra | C41: R$/K/ano | Z41: =Z45*Z$9 -> 0 | AA41: =AA45*AA$9 -> 0 | AB41: =AB45*AB$9 -> 3710123.8 | AC41: =AC45*AC$9 -> 3821427.5 | AD41: =AD45*AD$9 -> 3936070.4 | AE41: =AE45*AE$9 -> 4054152.5 | AF41: =AF45*AF$9 -> 4175777 | AG41: =AG45*AG$9 -> 4301050.3 | ... BG41: =BG45*BG$9 -> 9275607.6
A42: Outros custos | C42: R$/K/ano | Z42: =Z46*Z$9 -> 2246347.7 | AA42: =AA46*AA$9 -> 11568690 | AB42: =AB46*AB$9 -> 59578756 | AC42: =AC46*AC$9 -> 61366119 | AD42: =AD46*AD$9 -> 63207102 | AE42: =AE46*AE$9 -> 65103315 | AF42: =AF46*AF$9 -> 67056415 | AG42: =AG46*AG$9 -> 69068107 | ... BG42: =BG46*BG$9 -> 1.4895168e+08
A44: Total mensal | C44: R$/k/mês | Z44: =SUM(Z45:Z46) -> 187195.64 | AA44: =SUM(AA45:AA46) -> 964057.54 | AB44: =SUM(AB45:AB46) -> 5274073.3 | AC44: =SUM(AC45:AC46) -> 5432295.5 | AD44: =SUM(AD45:AD46) -> 5595264.4 | AE44: =SUM(AE45:AE46) -> 5763122.3 | AF44: =SUM(AF45:AF46) -> 5936016 | AG44: =SUM(AG45:AG46) -> 6114096.5 | ... BG44: =SUM(BG45:BG46) -> 13185607
A45: Mão de Obra | C45: R$/k/mês | Z45: =SUM(Z80:Z81)*Z$3 -> 0 | AA45: =SUM(AA80:AA81)*AA$3 -> 0 | AB45: =SUM(AB80:AB81)*AB$3 -> 309176.98 | AC45: =SUM(AC80:AC81)*AC$3 -> 318452.29 | AD45: =SUM(AD80:AD81)*AD$3 -> 328005.86 | AE45: =SUM(AE80:AE81)*AE$3 -> 337846.04 | AF45: =SUM(AF80:AF81)*AF$3 -> 347981.42 | AG45: =SUM(AG80:AG81)*AG$3 -> 358420.86 | ... BG45: =SUM(BG80:BG81)*BG$3 -> 772967.3
A46: Outros custos | C46: R$/k/mês | Z46: =(SUM(Z82))*Z$3 -> 187195.64 | AA46: =(SUM(AA82))*AA$3 -> 964057.54 | AB46: =(SUM(AB82))*AB$3 -> 4964896.3 | AC46: =(SUM(AC82))*AC$3 -> 5113843.2 | AD46: =(SUM(AD82))*AD$3 -> 5267258.5 | AE46: =(SUM(AE82))*AE$3 -> 5425276.3 | AF46: =(SUM(AF82))*AF$3 -> 5588034.6 | AG46: =(SUM(AG82))*AG$3 -> 5755675.6 | ... BG46: =(SUM(BG82))*BG$3 -> 12412640
A48: R$/ton | Z48: =Z39/OPERACIONAL!H7*1000/Z$3 -> 33243.063 | AA48: =AA39/OPERACIONAL!I7*1000/AA$3 -> 164907.98 | AB48: =AB39/OPERACIONAL!J7*1000/AB$3 -> 869186.39 | AC48: =AC39/OPERACIONAL!K7*1000/AC$3 -> 862454.78 | AD48: =AD39/OPERACIONAL!L7*1000/AD$3 -> 855695.1 | AE48: =AE39/OPERACIONAL!M7*1000/AE$3 -> 849170.05 | AF48: =AF39/OPERACIONAL!N7*1000/AF$3 -> 842616.23 | AG48: =AG39/OPERACIONAL!O7*1000/AG$3 -> 836037.24 | ... BG48: =BG39/OPERACIONAL!AO7*1000/BG$3 -> 686306.92
A49: R$/per capita | Z49: =Z39*1000/OPERACIONAL!H4/Z$3 -> 8878.089 | AA49: =AA39*1000/OPERACIONAL!I4/AA$3 -> 43418.914 | AB49: =AB39*1000/OPERACIONAL!J4/AB$3 -> 225566.39 | AC49: =AC39*1000/OPERACIONAL!K4/AC$3 -> 218943.11 | AD49: =AD39*1000/OPERACIONAL!L4/AD$3 -> 217305.08 | AE49: =AE39*1000/OPERACIONAL!M4/AE$3 -> 215612.02 | AF49: =AF39*1000/OPERACIONAL!N4/AF$3 -> 213926.24 | AG49: =AG39*1000/OPERACIONAL!O4/AG$3 -> 212248.01 | ... BG49: =BG39*1000/OPERACIONAL!AO4/BG$3 -> 174171.16
A50: Diferença em relação à média Sudeste | D50: 144.62 | E50: R$/hab/ano | F50: ANA (Relatório de Impacto Regulatório n 01/2021) | Z50: =Z49/$D$20-1 -> 60.389082 | AA50: =AA49/$D$20-1 -> 299.22759 | AB50: =AB49/$D$20-1 -> 1558.7178 | AC50: =AC49/$D$20-1 -> 1512.92 | AD50: =AD49/$D$20-1 -> 1501.5935 | AE50: =AE49/$D$20-1 -> 1489.8866 | AF50: =AF49/$D$20-1 -> 1478.23 | AG50: =AG49/$D$20-1 -> 1466.6255 | ... BG50: =BG49/$D$20-1 -> 1203.3366
A53: Opex / Por item [valores reais] | D53: 1 | E53: 1 - sem BDI / 2 - com BDI
D54: ='LOTE 3'!$B$19 -> 1
A55: Total mensal | C55: R$/k/mês | Z55: =SUM(Z56:Z59) -> 1616160 | AA55: =SUM(AA56:AA59) -> 8651612.4 | AB55: =SUM(AB56:AB59) -> 12581807 | AC55: =SUM(AC56:AC59) -> 12581807 | AD55: =SUM(AD56:AD59) -> 12581807 | AE55: =SUM(AE56:AE59) -> 12581807 | AF55: =SUM(AF56:AF59) -> 12581807 | AG55: =SUM(AG56:AG59) -> 12581807 | ... BG55: =SUM(BG56:BG59) -> 12581807
A57: =A61 -> URE MARÍLIA - BIO+GÁS | B57: =B61 -> 0 | C57: =C61 -> R$/mês | G57: =G61 -> 1.7314314e+08 | I57: =I61 -> 0 | J57: =J61 -> 0 | K57: =K61 -> 0 | L57: =L61 -> 0 | M57: =M61 -> 0 | N57: =N61 -> 0 | O57: =O61 -> 0 | P57: =P61 -> 0 | ... BG57: =BG61 -> 5222794.2
A58: =A70 -> URE MARÍLIA - BIO | B58: =B70 -> 0 | C58: =C70 -> R$/mês | G58: =G70 -> 90213925 | I58: =I70 -> 0 | J58: =J70 -> 0 | K58: =K70 -> 0 | L58: =L70 -> 0 | M58: =M70 -> 0 | N58: =N70 -> 0 | O58: =O70 -> 0 | P58: =P70 -> 0 | ... BG58: =BG70 -> 2719006.2
A59: =A78 -> URE MARÍLIA - GÁS | B59: =B78 -> 0 | C59: =C78 -> R$/mês | G59: =G78 -> 1.4952853e+08 | I59: =I78 -> 0 | J59: =J78 -> 0 | K59: =K78 -> 0 | L59: =L78 -> 0 | M59: =M78 -> 0 | N59: =N78 -> 0 | O59: =O78 -> 0 | P59: =P78 -> 0 | ... BG59: =BG78 -> 4640006.7
A61: ='OPEX Input'!C4 -> URE MARÍLIA - BIO+GÁS | C61: R$/mês | F61: 1 | G61: =SUM(Z61:BG61) -> 1.7314314e+08 | Z61: =SUM(Z62:Z68) -> 954720 | AA61: =SUM(AA62:AA68) -> 5059006.2 | AB61: =SUM(AB62:AB68) -> 5222794.2 | AC61: =SUM(AC62:AC68) -> 5222794.2 | AD61: =SUM(AD62:AD68) -> 5222794.2 | AE61: =SUM(AE62:AE68) -> 5222794.2 | AF61: =SUM(AF62:AF68) -> 5222794.2 | AG61: =SUM(AG62:AG68) -> 5222794.2 | ... BG61: =SUM(BG62:BG68) -> 5222794.2
A62: =A61 -> URE MARÍLIA - BIO+GÁS
A63: ='OPEX Input'!C8 -> Despesas mão de obra tratamento térmico (3 turnos) | B63: 01.01.01 | D63: ='LOTE 3'!$B$23 -> 1 | Z63: =IFERROR(INDEX('OPEX Input'!$G:$BM,MATCH($B63,'OPEX Input'!$B:$B,0),MATCH(Z$2,'OPEX Input'!$G$2:$BM$2,0)),0)*$D$54 -> 0 | AA63: =IFERROR(INDEX('OPEX Input'!$G:$BM,MATCH($B63,'OPEX Input'!$B:$B,0),MATCH(AA$2,'OPEX Input'!$G$2:$BM$2,0)),0)*$D$54 -> 190270.8 | AB63: =IFERROR(INDEX('OPEX Input'!$G:$BM,MATCH($B63,'OPEX Input'!$B:$B,0),MATCH(AB$2,'OPEX Input'!$G$2:$BM$2,0)),0)*$D$54 -> 299462.8 | AC63: =IFERROR(INDEX('OPEX Input'!$G:$BM,MATCH($B63,'OPEX Input'!$B:$B,0),MATCH(AC$2,'OPEX Input'!$G$2:$BM$2,0)),0)*$D$54 -> 299462.8 | AD63: =IFERROR(INDEX('OPEX Input'!$G:$BM,MATCH($B63,'OPEX Input'!$B:$B,0),MATCH(AD$2,'OPEX Input'!$G$2:$BM$2,0)),0)*$D$54 -> 299462.8 | AE63: =IFERROR(INDEX('OPEX Input'!$G:$BM,MATCH($B63,'OPEX Input'!$B:$B,0),MATCH(AE$2,'OPEX Input'!$G$2:$BM$2,0)),0)*$D$54 -> 299462.8 | AF63: =IFERROR(INDEX('OPEX Input'!$G:$BM,MATCH($B63,'OPEX Input'!$B:$B,0),MATCH(AF$2,'OPEX Input'!$G$2:$BM$2,0)),0)*$D$54 -> 299462.8 | AG63: =IFERROR(INDEX('OPEX Input'!$G:$BM,MATCH($B63,'OPEX Input'!$B:$B,0),MATCH(AG$2,'OPEX Input'!$G$2:$BM$2,0)),0)*$D$54 -> 299462.8 | ... BB63: =IFERROR(INDEX('OPEX Input'!$G:$BM,MATCH($B63,'OPEX Input'!$B:$B,0),MATCH(BB$2,'OPEX Input'!$G$2:$BM$2,0)),0)*$D$54 -> 299462.8 | BC63: =IFERROR(INDEX('OPEX Input'!$G:$BU,MATCH($B63,'OPEX Input'!$B:$B,0),MATCH(BC$2,'OPEX Input'!$G$2:$BU$2,0)),0)*$D$54 -> 299462.8 | BD63: =IFERROR(INDEX('OPEX Input'!$G:$BU,MATCH($B63,'OPEX Input'!$B:$B,0),MATCH(BD$2,'OPEX Input'!$G$2:$BU$2,0)),0)*$D$54 -> 299462.8 | BE63: =IFERROR(INDEX('OPEX Input'!$G:$BU,MATCH($B63,'OPEX Input'!$B:$B,0),MATCH(BE$2,'OPEX Input'!$G$2:$BU$2,0)),0)*$D$54 -> 299462.8 | BF63: =IFERROR(INDEX('OPEX Input'!$G:$BU,MATCH($B63,'OPEX Input'!$B:$B,0),MATCH(BF$2,'OPEX Input'!$G$2:$BU$2,0)),0)*$D$54 -> 299462.8 | BG63: =IFERROR(INDEX('OPEX Input'!$G:$BU,MATCH($B63,'OPEX Input'!$B:$B,0),MATCH(BG$2,'OPEX Input'!$G$2:$BU$2,0)),0)*$D$54 -> 299462.8
A64: ='OPEX Input'!C9 -> Despesas mão de obra Biodigestão (3 turnos) | B64: 01.01.02 | D64: ='LOTE 3'!$B$23 -> 1 | Z64: =IFERROR(INDEX('OPEX Input'!$G:$BM,MATCH($B64,'OPEX Input'!$B:$B,0),MATCH(Z$2,'OPEX Input'!$G$2:$BM$2,0)),0)*$D$54 -> 0 | AA64: =IFERROR(INDEX('OPEX Input'!$G:$BM,MATCH($B64,'OPEX Input'!$B:$B,0),MATCH(AA$2,'OPEX Input'!$G$2:$BM$2,0)),0)*$D$54 -> 95135.4 | AB64: =IFERROR(INDEX('OPEX Input'!$G:$BM,MATCH($B64,'OPEX Input'!$B:$B,0),MATCH(AB$2,'OPEX Input'!$G$2:$BM$2,0)),0)*$D$54 -> 149731.4 | AC64: =IFERROR(INDEX('OPEX Input'!$G:$BM,MATCH($B64,'OPEX Input'!$B:$B,0),MATCH(AC$2,'OPEX Input'!$G$2:$BM$2,0)),0)*$D$54 -> 149731.4 | AD64: =IFERROR(INDEX('OPEX Input'!$G:$BM,MATCH($B64,'OPEX Input'!$B:$B,0),MATCH(AD$2,'OPEX Input'!$G$2:$BM$2,0)),0)*$D$54 -> 149731.4 | AE64: =IFERROR(INDEX('OPEX Input'!$G:$BM,MATCH($B64,'OPEX Input'!$B:$B,0),MATCH(AE$2,'OPEX Input'!$G$2:$BM$2,0)),0)*$D$54 -> 149731.4 | AF64: =IFERROR(INDEX('OPEX Input'!$G:$BM,MATCH($B64,'OPEX Input'!$B:$B,0),MATCH(AF$2,'OPEX Input'!$G$2:$BM$2,0)),0)*$D$54 -> 149731.4 | AG64: =IFERROR(INDEX('OPEX Input'!$G:$BM,MATCH($B64,'OPEX Input'!$B:$B,0),MATCH(AG$2,'OPEX Input'!$G$2:$BM$2,0)),0)*$D$54 -> 149731.4 | ... BB64: =IFERROR(INDEX('OPEX Input'!$G:$BM,MATCH($B64,'OPEX Input'!$B:$B,0),MATCH(BB$2,'OPEX Input'!$G$2:$BM$2,0)),0)*$D$54 -> 149731.4 | BC64: =IFERROR(INDEX('OPEX Input'!$G:$BU,MATCH($B64,'OPEX Input'!$B:$B,0),MATCH(BC$2,'OPEX Input'!$G$2:$BU$2,0)),0)*$D$54 -> 149731.4 | BD64: =IFERROR(INDEX('OPEX Input'!$G:$BU,MATCH($B64,'OPEX Input'!$B:$B,0),MATCH(BD$2,'OPEX Input'!$G$2:$BU$2,0)),0)*$D$54 -> 149731.4 | BE64: =IFERROR(INDEX('OPEX Input'!$G:$BU,MATCH($B64,'OPEX Input'!$B:$B,0),MATCH(BE$2,'OPEX Input'!$G$2:$BU$2,0)),0)*$D$54 -> 149731.4 | BF64: =IFERROR(INDEX('OPEX Input'!$G:$BU,MATCH($B64,'OPEX Input'!$B:$B,0),MATCH(BF$2,'OPEX Input'!$G$2:$BU$2,0)),0)*$D$54 -> 149731.4 | BG64: =IFERROR(INDEX('OPEX Input'!$G:$BU,MATCH($B64,'OPEX Input'!$B:$B,0),MATCH(BG$2,'OPEX Input'!$G$2:$BU$2,0)),0)*$D$54 -> 149731.4
A65: ='OPEX Input'!C10 -> Despesas mão de obra CO2 (3 turnos) | B65: 01.01.03 | D65: ='LOTE 3'!$B$23 -> 1 | Z65: =IFERROR(INDEX('OPEX Input'!$G:$BM,MATCH($B65,'OPEX Input'!$B:$B,0),MATCH(Z$2,'OPEX Input'!$G$2:$BM$2,0)),0)*$D$54 -> 436800 | AA65: =IFERROR(INDEX('OPEX Input'!$G:$BM,MATCH($B65,'OPEX Input'!$B:$B,0),MATCH(AA$2,'OPEX Input'!$G$2:$BM$2,0)),0)*$D$54 -> 2184000 | AB65: =IFERROR(INDEX('OPEX Input'!$G:$BM,MATCH($B65,'OPEX Input'!$B:$B,0),MATCH(AB$2,'OPEX Input'!$G$2:$BM$2,0)),0)*$D$54 -> 2184000 | AC65: =IFERROR(INDEX('OPEX Input'!$G:$BM,MATCH($B65,'OPEX Input'!$B:$B,0),MATCH(AC$2,'OPEX Input'!$G$2:$BM$2,0)),0)*$D$54 -> 2184000 | AD65: =IFERROR(INDEX('OPEX Input'!$G:$BM,MATCH($B65,'OPEX Input'!$B:$B,0),MATCH(AD$2,'OPEX Input'!$G$2:$BM$2,0)),0)*$D$54 -> 2184000 | AE65: =IFERROR(INDEX('OPEX Input'!$G:$BM,MATCH($B65,'OPEX Input'!$B:$B,0),MATCH(AE$2,'OPEX Input'!$G$2:$BM$2,0)),0)*$D$54 -> 2184000 | AF65: =IFERROR(INDEX('OPEX Input'!$G:$BM,MATCH($B65,'OPEX Input'!$B:$B,0),MATCH(AF$2,'OPEX Input'!$G$2:$BM$2,0)),0)*$D$54 -> 2184000 | AG65: =IFERROR(INDEX('OPEX Input'!$G:$BM,MATCH($B65,'OPEX Input'!$B:$B,0),MATCH(AG$2,'OPEX Input'!$G$2:$BM$2,0)),0)*$D$54 -> 2184000 | ... BB65: =IFERROR(INDEX('OPEX Input'!$G:$BM,MATCH($B65,'OPEX Input'!$B:$B,0),MATCH(BB$2,'OPEX Input'!$G$2:$BM$2,0)),0)*$D$54 -> 2184000 | BC65: =IFERROR(INDEX('OPEX Input'!$G:$BU,MATCH($B65,'OPEX Input'!$B:$B,0),MATCH(BC$2,'OPEX Input'!$G$2:$BU$2,0)),0)*$D$54 -> 2184000 | BD65: =IFERROR(INDEX('OPEX Input'!$G:$BU,MATCH($B65,'OPEX Input'!$B:$B,0),MATCH(BD$2,'OPEX Input'!$G$2:$BU$2,0)),0)*$D$54 -> 2184000 | BE65: =IFERROR(INDEX('OPEX Input'!$G:$BU,MATCH($B65,'OPEX Input'!$B:$B,0),MATCH(BE$2,'OPEX Input'!$G$2:$BU$2,0)),0)*$D$54 -> 2184000 | BF65: =IFERROR(INDEX('OPEX Input'!$G:$BU,MATCH($B65,'OPEX Input'!$B:$B,0),MATCH(BF$2,'OPEX Input'!$G$2:$BU$2,0)),0)*$D$54 -> 2184000 | BG65: =IFERROR(INDEX('OPEX Input'!$G:$BU,MATCH($B65,'OPEX Input'!$B:$B,0),MATCH(BG$2,'OPEX Input'!$G$2:$BU$2,0)),0)*$D$54 -> 2184000
A66: ='OPEX Input'!C11 -> Despesas mão de obra INDIRETA | B66: 01.01.04 | D66: ='LOTE 3'!$B$23 -> 1 | Z66: =IFERROR(INDEX('OPEX Input'!$G:$BM,MATCH($B66,'OPEX Input'!$B:$B,0),MATCH(Z$2,'OPEX Input'!$G$2:$BM$2,0)),0)*$D$54 -> 249600 | AA66: =IFERROR(INDEX('OPEX Input'!$G:$BM,MATCH($B66,'OPEX Input'!$B:$B,0),MATCH(AA$2,'OPEX Input'!$G$2:$BM$2,0)),0)*$D$54 -> 1248000 | AB66: =IFERROR(INDEX('OPEX Input'!$G:$BM,MATCH($B66,'OPEX Input'!$B:$B,0),MATCH(AB$2,'OPEX Input'!$G$2:$BM$2,0)),0)*$D$54 -> 1248000 | AC66: =IFERROR(INDEX('OPEX Input'!$G:$BM,MATCH($B66,'OPEX Input'!$B:$B,0),MATCH(AC$2,'OPEX Input'!$G$2:$BM$2,0)),0)*$D$54 -> 1248000 | AD66: =IFERROR(INDEX('OPEX Input'!$G:$BM,MATCH($B66,'OPEX Input'!$B:$B,0),MATCH(AD$2,'OPEX Input'!$G$2:$BM$2,0)),0)*$D$54 -> 1248000 | AE66: =IFERROR(INDEX('OPEX Input'!$G:$BM,MATCH($B66,'OPEX Input'!$B:$B,0),MATCH(AE$2,'OPEX Input'!$G$2:$BM$2,0)),0)*$D$54 -> 1248000 | AF66: =IFERROR(INDEX('OPEX Input'!$G:$BM,MATCH($B66,'OPEX Input'!$B:$B,0),MATCH(AF$2,'OPEX Input'!$G$2:$BM$2,0)),0)*$D$54 -> 1248000 | AG66: =IFERROR(INDEX('OPEX Input'!$G:$BM,MATCH($B66,'OPEX Input'!$B:$B,0),MATCH(AG$2,'OPEX Input'!$G$2:$BM$2,0)),0)*$D$54 -> 1248000 | ... BB66: =IFERROR(INDEX('OPEX Input'!$G:$BM,MATCH($B66,'OPEX Input'!$B:$B,0),MATCH(BB$2,'OPEX Input'!$G$2:$BM$2,0)),0)*$D$54 -> 1248000 | BC66: =IFERROR(INDEX('OPEX Input'!$G:$BU,MATCH($B66,'OPEX Input'!$B:$B,0),MATCH(BC$2,'OPEX Input'!$G$2:$BU$2,0)),0)*$D$54 -> 1248000 | BD66: =IFERROR(INDEX('OPEX Input'!$G:$BU,MATCH($B66,'OPEX Input'!$B:$B,0),MATCH(BD$2,'OPEX Input'!$G$2:$BU$2,0)),0)*$D$54 -> 1248000 | BE66: =IFERROR(INDEX('OPEX Input'!$G:$BU,MATCH($B66,'OPEX Input'!$B:$B,0),MATCH(BE$2,'OPEX Input'!$G$2:$BU$2,0)),0)*$D$54 -> 1248000 | BF66: =IFERROR(INDEX('OPEX Input'!$G:$BU,MATCH($B66,'OPEX Input'!$B:$B,0),MATCH(BF$2,'OPEX Input'!$G$2:$BU$2,0)),0)*$D$54 -> 1248000 | BG66: =IFERROR(INDEX('OPEX Input'!$G:$BU,MATCH($B66,'OPEX Input'!$B:$B,0),MATCH(BG$2,'OPEX Input'!$G$2:$BU$2,0)),0)*$D$54 -> 1248000
A67: ='OPEX Input'!C12 -> Energia Elétrica da planta | B67: 01.01.05 | D67: ='LOTE 3'!$B$23 -> 1 | Z67: =IFERROR(INDEX('OPEX Input'!$G:$BM,MATCH($B67,'OPEX Input'!$B:$B,0),MATCH(Z$2,'OPEX Input'!$G$2:$BM$2,0)),0)*$D$54 -> 268320 | AA67: =IFERROR(INDEX('OPEX Input'!$G:$BM,MATCH($B67,'OPEX Input'!$B:$B,0),MATCH(AA$2,'OPEX Input'!$G$2:$BM$2,0)),0)*$D$54 -> 1341600 | AB67: =IFERROR(INDEX('OPEX Input'!$G:$BM,MATCH($B67,'OPEX Input'!$B:$B,0),MATCH(AB$2,'OPEX Input'!$G$2:$BM$2,0)),0)*$D$54 -> 1341600 | AC67: =IFERROR(INDEX('OPEX Input'!$G:$BM,MATCH($B67,'OPEX Input'!$B:$B,0),MATCH(AC$2,'OPEX Input'!$G$2:$BM$2,0)),0)*$D$54 -> 1341600 | AD67: =IFERROR(INDEX('OPEX Input'!$G:$BM,MATCH($B67,'OPEX Input'!$B:$B,0),MATCH(AD$2,'OPEX Input'!$G$2:$BM$2,0)),0)*$D$54 -> 1341600 | AE67: =IFERROR(INDEX('OPEX Input'!$G:$BM,MATCH($B67,'OPEX Input'!$B:$B,0),MATCH(AE$2,'OPEX Input'!$G$2:$BM$2,0)),0)*$D$54 -> 1341600 | AF67: =IFERROR(INDEX('OPEX Input'!$G:$BM,MATCH($B67,'OPEX Input'!$B:$B,0),MATCH(AF$2,'OPEX Input'!$G$2:$BM$2,0)),0)*$D$54 -> 1341600 | AG67: =IFERROR(INDEX('OPEX Input'!$G:$BM,MATCH($B67,'OPEX Input'!$B:$B,0),MATCH(AG$2,'OPEX Input'!$G$2:$BM$2,0)),0)*$D$54 -> 1341600 | ... BB67: =IFERROR(INDEX('OPEX Input'!$G:$BM,MATCH($B67,'OPEX Input'!$B:$B,0),MATCH(BB$2,'OPEX Input'!$G$2:$BM$2,0)),0)*$D$54 -> 1341600 | BC67: =IFERROR(INDEX('OPEX Input'!$G:$BU,MATCH($B67,'OPEX Input'!$B:$B,0),MATCH(BC$2,'OPEX Input'!$G$2:$BU$2,0)),0)*$D$54 -> 1341600 | BD67: =IFERROR(INDEX('OPEX Input'!$G:$BU,MATCH($B67,'OPEX Input'!$B:$B,0),MATCH(BD$2,'OPEX Input'!$G$2:$BU$2,0)),0)*$D$54 -> 1341600 | BE67: =IFERROR(INDEX('OPEX Input'!$G:$BU,MATCH($B67,'OPEX Input'!$B:$B,0),MATCH(BE$2,'OPEX Input'!$G$2:$BU$2,0)),0)*$D$54 -> 1341600 | BF67: =IFERROR(INDEX('OPEX Input'!$G:$BU,MATCH($B67,'OPEX Input'!$B:$B,0),MATCH(BF$2,'OPEX Input'!$G$2:$BU$2,0)),0)*$D$54 -> 1341600 | BG67: =IFERROR(INDEX('OPEX Input'!$G:$BU,MATCH($B67,'OPEX Input'!$B:$B,0),MATCH(BG$2,'OPEX Input'!$G$2:$BU$2,0)),0)*$D$54 -> 1341600
A68: ='OPEX Input'!C13 -> Manutenção | B68: 01.01.06 | D68: 2
A70: ='OPEX Input'!C14 -> URE MARÍLIA - BIO | C70: R$/mês | F70: 2 | G70: =SUM(Z70:BG70) -> 90213925 | Z70: =SUM(Z71:Z76) -> 486720 | AA70: =SUM(AA71:AA76) -> 2719006.2 | AB70: =SUM(AB71:AB76) -> 2719006.2 | AC70: =SUM(AC71:AC76) -> 2719006.2 | AD70: =SUM(AD71:AD76) -> 2719006.2 | AE70: =SUM(AE71:AE76) -> 2719006.2 | AF70: =SUM(AF71:AF76) -> 2719006.2 | AG70: =SUM(AG71:AG76) -> 2719006.2 | ... BG70: =SUM(BG71:BG76) -> 2719006.2
A71: =A70 -> URE MARÍLIA - BIO
A72: ='OPEX Input'!C18 -> Despesas mão de obra Biodigestão (3 turnos) | B72: 02.01.01 | D72: ='LOTE 3'!$B$23 -> 1 | Z72: =IFERROR(INDEX('OPEX Input'!$G:$BM,MATCH($B72,'OPEX Input'!$B:$B,0),MATCH(Z$2,'OPEX Input'!$G$2:$BM$2,0)),0)*$D$54 -> 0 | AA72: =IFERROR(INDEX('OPEX Input'!$G:$BM,MATCH($B72,'OPEX Input'!$B:$B,0),MATCH(AA$2,'OPEX Input'!$G$2:$BM$2,0)),0)*$D$54 -> 190270.8 | AB72: =IFERROR(INDEX('OPEX Input'!$G:$BM,MATCH($B72,'OPEX Input'!$B:$B,0),MATCH(AB$2,'OPEX Input'!$G$2:$BM$2,0)),0)*$D$54 -> 190270.8 | AC72: =IFERROR(INDEX('OPEX Input'!$G:$BM,MATCH($B72,'OPEX Input'!$B:$B,0),MATCH(AC$2,'OPEX Input'!$G$2:$BM$2,0)),0)*$D$54 -> 190270.8 | AD72: =IFERROR(INDEX('OPEX Input'!$G:$BM,MATCH($B72,'OPEX Input'!$B:$B,0),MATCH(AD$2,'OPEX Input'!$G$2:$BM$2,0)),0)*$D$54 -> 190270.8 | AE72: =IFERROR(INDEX('OPEX Input'!$G:$BM,MATCH($B72,'OPEX Input'!$B:$B,0),MATCH(AE$2,'OPEX Input'!$G$2:$BM$2,0)),0)*$D$54 -> 190270.8 | AF72: =IFERROR(INDEX('OPEX Input'!$G:$BM,MATCH($B72,'OPEX Input'!$B:$B,0),MATCH(AF$2,'OPEX Input'!$G$2:$BM$2,0)),0)*$D$54 -> 190270.8 | AG72: =IFERROR(INDEX('OPEX Input'!$G:$BM,MATCH($B72,'OPEX Input'!$B:$B,0),MATCH(AG$2,'OPEX Input'!$G$2:$BM$2,0)),0)*$D$54 -> 190270.8 | ... BB72: =IFERROR(INDEX('OPEX Input'!$G:$BM,MATCH($B72,'OPEX Input'!$B:$B,0),MATCH(BB$2,'OPEX Input'!$G$2:$BM$2,0)),0)*$D$54 -> 190270.8 | BC72: =IFERROR(INDEX('OPEX Input'!$G:$BU,MATCH($B72,'OPEX Input'!$B:$B,0),MATCH(BC$2,'OPEX Input'!$G$2:$BU$2,0)),0)*$D$54 -> 190270.8 | BD72: =IFERROR(INDEX('OPEX Input'!$G:$BU,MATCH($B72,'OPEX Input'!$B:$B,0),MATCH(BD$2,'OPEX Input'!$G$2:$BU$2,0)),0)*$D$54 -> 190270.8 | BE72: =IFERROR(INDEX('OPEX Input'!$G:$BU,MATCH($B72,'OPEX Input'!$B:$B,0),MATCH(BE$2,'OPEX Input'!$G$2:$BU$2,0)),0)*$D$54 -> 190270.8 | BF72: =IFERROR(INDEX('OPEX Input'!$G:$BU,MATCH($B72,'OPEX Input'!$B:$B,0),MATCH(BF$2,'OPEX Input'!$G$2:$BU$2,0)),0)*$D$54 -> 190270.8 | BG72: =IFERROR(INDEX('OPEX Input'!$G:$BU,MATCH($B72,'OPEX Input'!$B:$B,0),MATCH(BG$2,'OPEX Input'!$G$2:$BU$2,0)),0)*$D$54 -> 190270.8
A73: ='OPEX Input'!C19 -> Despesas mão de obra CO2 (3 turnos) | B73: 02.01.02 | D73: ='LOTE 3'!$B$23 -> 1 | Z73: =IFERROR(INDEX('OPEX Input'!$G:$BM,MATCH($B73,'OPEX Input'!$B:$B,0),MATCH(Z$2,'OPEX Input'!$G$2:$BM$2,0)),0)*$D$54 -> 0 | AA73: =IFERROR(INDEX('OPEX Input'!$G:$BM,MATCH($B73,'OPEX Input'!$B:$B,0),MATCH(AA$2,'OPEX Input'!$G$2:$BM$2,0)),0)*$D$54 -> 95135.4 | AB73: =IFERROR(INDEX('OPEX Input'!$G:$BM,MATCH($B73,'OPEX Input'!$B:$B,0),MATCH(AB$2,'OPEX Input'!$G$2:$BM$2,0)),0)*$D$54 -> 95135.4 | AC73: =IFERROR(INDEX('OPEX Input'!$G:$BM,MATCH($B73,'OPEX Input'!$B:$B,0),MATCH(AC$2,'OPEX Input'!$G$2:$BM$2,0)),0)*$D$54 -> 95135.4 | AD73: =IFERROR(INDEX('OPEX Input'!$G:$BM,MATCH($B73,'OPEX Input'!$B:$B,0),MATCH(AD$2,'OPEX Input'!$G$2:$BM$2,0)),0)*$D$54 -> 95135.4 | AE73: =IFERROR(INDEX('OPEX Input'!$G:$BM,MATCH($B73,'OPEX Input'!$B:$B,0),MATCH(AE$2,'OPEX Input'!$G$2:$BM$2,0)),0)*$D$54 -> 95135.4 | AF73: =IFERROR(INDEX('OPEX Input'!$G:$BM,MATCH($B73,'OPEX Input'!$B:$B,0),MATCH(AF$2,'OPEX Input'!$G$2:$BM$2,0)),0)*$D$54 -> 95135.4 | AG73: =IFERROR(INDEX('OPEX Input'!$G:$BM,MATCH($B73,'OPEX Input'!$B:$B,0),MATCH(AG$2,'OPEX Input'!$G$2:$BM$2,0)),0)*$D$54 -> 95135.4 | ... BB73: =IFERROR(INDEX('OPEX Input'!$G:$BM,MATCH($B73,'OPEX Input'!$B:$B,0),MATCH(BB$2,'OPEX Input'!$G$2:$BM$2,0)),0)*$D$54 -> 95135.4 | BC73: =IFERROR(INDEX('OPEX Input'!$G:$BU,MATCH($B73,'OPEX Input'!$B:$B,0),MATCH(BC$2,'OPEX Input'!$G$2:$BU$2,0)),0)*$D$54 -> 95135.4 | BD73: =IFERROR(INDEX('OPEX Input'!$G:$BU,MATCH($B73,'OPEX Input'!$B:$B,0),MATCH(BD$2,'OPEX Input'!$G$2:$BU$2,0)),0)*$D$54 -> 95135.4 | BE73: =IFERROR(INDEX('OPEX Input'!$G:$BU,MATCH($B73,'OPEX Input'!$B:$B,0),MATCH(BE$2,'OPEX Input'!$G$2:$BU$2,0)),0)*$D$54 -> 95135.4 | BF73: =IFERROR(INDEX('OPEX Input'!$G:$BU,MATCH($B73,'OPEX Input'!$B:$B,0),MATCH(BF$2,'OPEX Input'!$G$2:$BU$2,0)),0)*$D$54 -> 95135.4 | BG73: =IFERROR(INDEX('OPEX Input'!$G:$BU,MATCH($B73,'OPEX Input'!$B:$B,0),MATCH(BG$2,'OPEX Input'!$G$2:$BU$2,0)),0)*$D$54 -> 95135.4
A74: ='OPEX Input'!C20 -> Despesas mão de obra INDIRETA | B74: 02.01.03 | D74: ='LOTE 3'!$B$23 -> 1 | Z74: =IFERROR(INDEX('OPEX Input'!$G:$BM,MATCH($B74,'OPEX Input'!$B:$B,0),MATCH(Z$2,'OPEX Input'!$G$2:$BM$2,0)),0)*$D$54 -> 187200 | AA74: =IFERROR(INDEX('OPEX Input'!$G:$BM,MATCH($B74,'OPEX Input'!$B:$B,0),MATCH(AA$2,'OPEX Input'!$G$2:$BM$2,0)),0)*$D$54 -> 936000 | AB74: =IFERROR(INDEX('OPEX Input'!$G:$BM,MATCH($B74,'OPEX Input'!$B:$B,0),MATCH(AB$2,'OPEX Input'!$G$2:$BM$2,0)),0)*$D$54 -> 936000 | AC74: =IFERROR(INDEX('OPEX Input'!$G:$BM,MATCH($B74,'OPEX Input'!$B:$B,0),MATCH(AC$2,'OPEX Input'!$G$2:$BM$2,0)),0)*$D$54 -> 936000 | AD74: =IFERROR(INDEX('OPEX Input'!$G:$BM,MATCH($B74,'OPEX Input'!$B:$B,0),MATCH(AD$2,'OPEX Input'!$G$2:$BM$2,0)),0)*$D$54 -> 936000 | AE74: =IFERROR(INDEX('OPEX Input'!$G:$BM,MATCH($B74,'OPEX Input'!$B:$B,0),MATCH(AE$2,'OPEX Input'!$G$2:$BM$2,0)),0)*$D$54 -> 936000 | AF74: =IFERROR(INDEX('OPEX Input'!$G:$BM,MATCH($B74,'OPEX Input'!$B:$B,0),MATCH(AF$2,'OPEX Input'!$G$2:$BM$2,0)),0)*$D$54 -> 936000 | AG74: =IFERROR(INDEX('OPEX Input'!$G:$BM,MATCH($B74,'OPEX Input'!$B:$B,0),MATCH(AG$2,'OPEX Input'!$G$2:$BM$2,0)),0)*$D$54 -> 936000 | ... BB74: =IFERROR(INDEX('OPEX Input'!$G:$BM,MATCH($B74,'OPEX Input'!$B:$B,0),MATCH(BB$2,'OPEX Input'!$G$2:$BM$2,0)),0)*$D$54 -> 936000 | BC74: =IFERROR(INDEX('OPEX Input'!$G:$BU,MATCH($B74,'OPEX Input'!$B:$B,0),MATCH(BC$2,'OPEX Input'!$G$2:$BU$2,0)),0)*$D$54 -> 936000 | BD74: =IFERROR(INDEX('OPEX Input'!$G:$BU,MATCH($B74,'OPEX Input'!$B:$B,0),MATCH(BD$2,'OPEX Input'!$G$2:$BU$2,0)),0)*$D$54 -> 936000 | BE74: =IFERROR(INDEX('OPEX Input'!$G:$BU,MATCH($B74,'OPEX Input'!$B:$B,0),MATCH(BE$2,'OPEX Input'!$G$2:$BU$2,0)),0)*$D$54 -> 936000 | BF74: =IFERROR(INDEX('OPEX Input'!$G:$BU,MATCH($B74,'OPEX Input'!$B:$B,0),MATCH(BF$2,'OPEX Input'!$G$2:$BU$2,0)),0)*$D$54 -> 936000 | BG74: =IFERROR(INDEX('OPEX Input'!$G:$BU,MATCH($B74,'OPEX Input'!$B:$B,0),MATCH(BG$2,'OPEX Input'!$G$2:$BU$2,0)),0)*$D$54 -> 936000
A75: ='OPEX Input'!C21 -> Energia Elétrica da planta | B75: 02.01.04 | D75: ='LOTE 3'!$B$23 -> 1 | Z75: =IFERROR(INDEX('OPEX Input'!$G:$BM,MATCH($B75,'OPEX Input'!$B:$B,0),MATCH(Z$2,'OPEX Input'!$G$2:$BM$2,0)),0)*$D$54 -> 212160 | AA75: =IFERROR(INDEX('OPEX Input'!$G:$BM,MATCH($B75,'OPEX Input'!$B:$B,0),MATCH(AA$2,'OPEX Input'!$G$2:$BM$2,0)),0)*$D$54 -> 1060800 | AB75: =IFERROR(INDEX('OPEX Input'!$G:$BM,MATCH($B75,'OPEX Input'!$B:$B,0),MATCH(AB$2,'OPEX Input'!$G$2:$BM$2,0)),0)*$D$54 -> 1060800 | AC75: =IFERROR(INDEX('OPEX Input'!$G:$BM,MATCH($B75,'OPEX Input'!$B:$B,0),MATCH(AC$2,'OPEX Input'!$G$2:$BM$2,0)),0)*$D$54 -> 1060800 | AD75: =IFERROR(INDEX('OPEX Input'!$G:$BM,MATCH($B75,'OPEX Input'!$B:$B,0),MATCH(AD$2,'OPEX Input'!$G$2:$BM$2,0)),0)*$D$54 -> 1060800 | AE75: =IFERROR(INDEX('OPEX Input'!$G:$BM,MATCH($B75,'OPEX Input'!$B:$B,0),MATCH(AE$2,'OPEX Input'!$G$2:$BM$2,0)),0)*$D$54 -> 1060800 | AF75: =IFERROR(INDEX('OPEX Input'!$G:$BM,MATCH($B75,'OPEX Input'!$B:$B,0),MATCH(AF$2,'OPEX Input'!$G$2:$BM$2,0)),0)*$D$54 -> 1060800 | AG75: =IFERROR(INDEX('OPEX Input'!$G:$BM,MATCH($B75,'OPEX Input'!$B:$B,0),MATCH(AG$2,'OPEX Input'!$G$2:$BM$2,0)),0)*$D$54 -> 1060800 | ... BB75: =IFERROR(INDEX('OPEX Input'!$G:$BM,MATCH($B75,'OPEX Input'!$B:$B,0),MATCH(BB$2,'OPEX Input'!$G$2:$BM$2,0)),0)*$D$54 -> 1060800 | BC75: =IFERROR(INDEX('OPEX Input'!$G:$BU,MATCH($B75,'OPEX Input'!$B:$B,0),MATCH(BC$2,'OPEX Input'!$G$2:$BU$2,0)),0)*$D$54 -> 1060800 | BD75: =IFERROR(INDEX('OPEX Input'!$G:$BU,MATCH($B75,'OPEX Input'!$B:$B,0),MATCH(BD$2,'OPEX Input'!$G$2:$BU$2,0)),0)*$D$54 -> 1060800 | BE75: =IFERROR(INDEX('OPEX Input'!$G:$BU,MATCH($B75,'OPEX Input'!$B:$B,0),MATCH(BE$2,'OPEX Input'!$G$2:$BU$2,0)),0)*$D$54 -> 1060800 | BF75: =IFERROR(INDEX('OPEX Input'!$G:$BU,MATCH($B75,'OPEX Input'!$B:$B,0),MATCH(BF$2,'OPEX Input'!$G$2:$BU$2,0)),0)*$D$54 -> 1060800 | BG75: =IFERROR(INDEX('OPEX Input'!$G:$BU,MATCH($B75,'OPEX Input'!$B:$B,0),MATCH(BG$2,'OPEX Input'!$G$2:$BU$2,0)),0)*$D$54 -> 1060800
A76: ='OPEX Input'!C22 -> Manutenção | B76: 02.01.05 | D76: 2 | Z76: =IFERROR(INDEX('OPEX Input'!$G:$BM,MATCH($B76,'OPEX Input'!$B:$B,0),MATCH(Z$2,'OPEX Input'!$G$2:$BM$2,0)),0)*$D$54 -> 87360 | AA76: =IFERROR(INDEX('OPEX Input'!$G:$BM,MATCH($B76,'OPEX Input'!$B:$B,0),MATCH(AA$2,'OPEX Input'!$G$2:$BM$2,0)),0)*$D$54 -> 436800 | AB76: =IFERROR(INDEX('OPEX Input'!$G:$BM,MATCH($B76,'OPEX Input'!$B:$B,0),MATCH(AB$2,'OPEX Input'!$G$2:$BM$2,0)),0)*$D$54 -> 436800 | AC76: =IFERROR(INDEX('OPEX Input'!$G:$BM,MATCH($B76,'OPEX Input'!$B:$B,0),MATCH(AC$2,'OPEX Input'!$G$2:$BM$2,0)),0)*$D$54 -> 436800 | AD76: =IFERROR(INDEX('OPEX Input'!$G:$BM,MATCH($B76,'OPEX Input'!$B:$B,0),MATCH(AD$2,'OPEX Input'!$G$2:$BM$2,0)),0)*$D$54 -> 436800 | AE76: =IFERROR(INDEX('OPEX Input'!$G:$BM,MATCH($B76,'OPEX Input'!$B:$B,0),MATCH(AE$2,'OPEX Input'!$G$2:$BM$2,0)),0)*$D$54 -> 436800 | AF76: =IFERROR(INDEX('OPEX Input'!$G:$BM,MATCH($B76,'OPEX Input'!$B:$B,0),MATCH(AF$2,'OPEX Input'!$G$2:$BM$2,0)),0)*$D$54 -> 436800 | AG76: =IFERROR(INDEX('OPEX Input'!$G:$BM,MATCH($B76,'OPEX Input'!$B:$B,0),MATCH(AG$2,'OPEX Input'!$G$2:$BM$2,0)),0)*$D$54 -> 436800 | ... BB76: =IFERROR(INDEX('OPEX Input'!$G:$BM,MATCH($B76,'OPEX Input'!$B:$B,0),MATCH(BB$2,'OPEX Input'!$G$2:$BM$2,0)),0)*$D$54 -> 436800 | BC76: =IFERROR(INDEX('OPEX Input'!$G:$BU,MATCH($B76,'OPEX Input'!$B:$B,0),MATCH(BC$2,'OPEX Input'!$G$2:$BU$2,0)),0)*$D$54 -> 436800 | BD76: =IFERROR(INDEX('OPEX Input'!$G:$BU,MATCH($B76,'OPEX Input'!$B:$B,0),MATCH(BD$2,'OPEX Input'!$G$2:$BU$2,0)),0)*$D$54 -> 436800 | BE76: =IFERROR(INDEX('OPEX Input'!$G:$BU,MATCH($B76,'OPEX Input'!$B:$B,0),MATCH(BE$2,'OPEX Input'!$G$2:$BU$2,0)),0)*$D$54 -> 436800 | BF76: =IFERROR(INDEX('OPEX Input'!$G:$BU,MATCH($B76,'OPEX Input'!$B:$B,0),MATCH(BF$2,'OPEX Input'!$G$2:$BU$2,0)),0)*$D$54 -> 436800 | BG76: =IFERROR(INDEX('OPEX Input'!$G:$BU,MATCH($B76,'OPEX Input'!$B:$B,0),MATCH(BG$2,'OPEX Input'!$G$2:$BU$2,0)),0)*$D$54 -> 436800
A78: ='OPEX Input'!C23 -> URE MARÍLIA - GÁS | C78: R$/mês | F78: 3 | G78: =SUM(Z78:BG78) -> 1.4952853e+08 | Z78: =SUM(Z79:Z82) -> 174720 | AA78: =SUM(AA79:AA82) -> 873600 | AB78: =SUM(AB79:AB82) -> 4640006.7 | AC78: =SUM(AC79:AC82) -> 4640006.7 | AD78: =SUM(AD79:AD82) -> 4640006.7 | AE78: =SUM(AE79:AE82) -> 4640006.7 | AF78: =SUM(AF79:AF82) -> 4640006.7 | AG78: =SUM(AG79:AG82) -> 4640006.7 | ... BG78: =SUM(BG79:BG82) -> 4640006.7
A79: =A78 -> URE MARÍLIA - GÁS
A80: ='OPEX Input'!C27 -> Despesas mão de obra Biodigestão (3 turnos) | B80: 03.01.01 | D80: ='LOTE 3'!$B$23 -> 1 | Z80: =IFERROR(INDEX('OPEX Input'!$G:$BM,MATCH($B80,'OPEX Input'!$B:$B,0),MATCH(Z$2,'OPEX Input'!$G$2:$BM$2,0)),0)*$D$54*$D80 -> 0 | AA80: =IFERROR(INDEX('OPEX Input'!$G:$BM,MATCH($B80,'OPEX Input'!$B:$B,0),MATCH(AA$2,'OPEX Input'!$G$2:$BM$2,0)),0)*$D$54*$D80 -> 0 | AB80: =IFERROR(INDEX('OPEX Input'!$G:$BM,MATCH($B80,'OPEX Input'!$B:$B,0),MATCH(AB$2,'OPEX Input'!$G$2:$BM$2,0)),0)*$D$54*$D80 -> 181337.8 | AC80: =IFERROR(INDEX('OPEX Input'!$G:$BM,MATCH($B80,'OPEX Input'!$B:$B,0),MATCH(AC$2,'OPEX Input'!$G$2:$BM$2,0)),0)*$D$54*$D80 -> 181337.8 | AD80: =IFERROR(INDEX('OPEX Input'!$G:$BM,MATCH($B80,'OPEX Input'!$B:$B,0),MATCH(AD$2,'OPEX Input'!$G$2:$BM$2,0)),0)*$D$54*$D80 -> 181337.8 | AE80: =IFERROR(INDEX('OPEX Input'!$G:$BM,MATCH($B80,'OPEX Input'!$B:$B,0),MATCH(AE$2,'OPEX Input'!$G$2:$BM$2,0)),0)*$D$54*$D80 -> 181337.8 | AF80: =IFERROR(INDEX('OPEX Input'!$G:$BM,MATCH($B80,'OPEX Input'!$B:$B,0),MATCH(AF$2,'OPEX Input'!$G$2:$BM$2,0)),0)*$D$54*$D80 -> 181337.8 | AG80: =IFERROR(INDEX('OPEX Input'!$G:$BM,MATCH($B80,'OPEX Input'!$B:$B,0),MATCH(AG$2,'OPEX Input'!$G$2:$BM$2,0)),0)*$D$54*$D80 -> 181337.8 | ... BB80: =IFERROR(INDEX('OPEX Input'!$G:$BM,MATCH($B80,'OPEX Input'!$B:$B,0),MATCH(BB$2,'OPEX Input'!$G$2:$BM$2,0)),0)*$D$54*$D80 -> 181337.8 | BC80: =IFERROR(INDEX('OPEX Input'!$G:$BU,MATCH($B80,'OPEX Input'!$B:$B,0),MATCH(BC$2,'OPEX Input'!$G$2:$BU$2,0)),0)*$D$54*$D80 -> 181337.8 | BD80: =IFERROR(INDEX('OPEX Input'!$G:$BU,MATCH($B80,'OPEX Input'!$B:$B,0),MATCH(BD$2,'OPEX Input'!$G$2:$BU$2,0)),0)*$D$54*$D80 -> 181337.8 | BE80: =IFERROR(INDEX('OPEX Input'!$G:$BU,MATCH($B80,'OPEX Input'!$B:$B,0),MATCH(BE$2,'OPEX Input'!$G$2:$BU$2,0)),0)*$D$54*$D80 -> 181337.8 | BF80: =IFERROR(INDEX('OPEX Input'!$G:$BU,MATCH($B80,'OPEX Input'!$B:$B,0),MATCH(BF$2,'OPEX Input'!$G$2:$BU$2,0)),0)*$D$54*$D80 -> 181337.8 | BG80: =IFERROR(INDEX('OPEX Input'!$G:$BU,MATCH($B80,'OPEX Input'!$B:$B,0),MATCH(BG$2,'OPEX Input'!$G$2:$BU$2,0)),0)*$D$54*$D80 -> 181337.8
A81: ='OPEX Input'!C28 -> Despesas mão de obra INDIRETA | B81: 03.01.02 | D81: ='LOTE 3'!$B$23 -> 1 | Z81: =IFERROR(INDEX('OPEX Input'!$G:$BM,MATCH($B81,'OPEX Input'!$B:$B,0),MATCH(Z$2,'OPEX Input'!$G$2:$BM$2,0)),0)*$D$54*$D81 -> 0 | AA81: =IFERROR(INDEX('OPEX Input'!$G:$BM,MATCH($B81,'OPEX Input'!$B:$B,0),MATCH(AA$2,'OPEX Input'!$G$2:$BM$2,0)),0)*$D$54*$D81 -> 0 | AB81: =IFERROR(INDEX('OPEX Input'!$G:$BM,MATCH($B81,'OPEX Input'!$B:$B,0),MATCH(AB$2,'OPEX Input'!$G$2:$BM$2,0)),0)*$D$54*$D81 -> 90668.9 | AC81: =IFERROR(INDEX('OPEX Input'!$G:$BM,MATCH($B81,'OPEX Input'!$B:$B,0),MATCH(AC$2,'OPEX Input'!$G$2:$BM$2,0)),0)*$D$54*$D81 -> 90668.9 | AD81: =IFERROR(INDEX('OPEX Input'!$G:$BM,MATCH($B81,'OPEX Input'!$B:$B,0),MATCH(AD$2,'OPEX Input'!$G$2:$BM$2,0)),0)*$D$54*$D81 -> 90668.9 | AE81: =IFERROR(INDEX('OPEX Input'!$G:$BM,MATCH($B81,'OPEX Input'!$B:$B,0),MATCH(AE$2,'OPEX Input'!$G$2:$BM$2,0)),0)*$D$54*$D81 -> 90668.9 | AF81: =IFERROR(INDEX('OPEX Input'!$G:$BM,MATCH($B81,'OPEX Input'!$B:$B,0),MATCH(AF$2,'OPEX Input'!$G$2:$BM$2,0)),0)*$D$54*$D81 -> 90668.9 | AG81: =IFERROR(INDEX('OPEX Input'!$G:$BM,MATCH($B81,'OPEX Input'!$B:$B,0),MATCH(AG$2,'OPEX Input'!$G$2:$BM$2,0)),0)*$D$54*$D81 -> 90668.9 | ... BB81: =IFERROR(INDEX('OPEX Input'!$G:$BM,MATCH($B81,'OPEX Input'!$B:$B,0),MATCH(BB$2,'OPEX Input'!$G$2:$BM$2,0)),0)*$D$54*$D81 -> 90668.9 | BC81: =IFERROR(INDEX('OPEX Input'!$G:$BU,MATCH($B81,'OPEX Input'!$B:$B,0),MATCH(BC$2,'OPEX Input'!$G$2:$BU$2,0)),0)*$D$54*$D81 -> 90668.9 | BD81: =IFERROR(INDEX('OPEX Input'!$G:$BU,MATCH($B81,'OPEX Input'!$B:$B,0),MATCH(BD$2,'OPEX Input'!$G$2:$BU$2,0)),0)*$D$54*$D81 -> 90668.9 | BE81: =IFERROR(INDEX('OPEX Input'!$G:$BU,MATCH($B81,'OPEX Input'!$B:$B,0),MATCH(BE$2,'OPEX Input'!$G$2:$BU$2,0)),0)*$D$54*$D81 -> 90668.9 | BF81: =IFERROR(INDEX('OPEX Input'!$G:$BU,MATCH($B81,'OPEX Input'!$B:$B,0),MATCH(BF$2,'OPEX Input'!$G$2:$BU$2,0)),0)*$D$54*$D81 -> 90668.9 | BG81: =IFERROR(INDEX('OPEX Input'!$G:$BU,MATCH($B81,'OPEX Input'!$B:$B,0),MATCH(BG$2,'OPEX Input'!$G$2:$BU$2,0)),0)*$D$54*$D81 -> 90668.9
